Workbook

Sheet Overzicht
A1: Marge-overzicht offerte Ville de Mons – BO.F.2026/Signalétique int & ext/GC
A2: INTERN – niet bij de offerte voegen. Verkoopprijzen = ingediende offerte; aankoopprijzen = invullen uit Igepa (tab Materialen).
B4: Totaal verkoop excl. btw | C4: Verkoop posten met volledige kost | D4: Kost (volledige posten) | E4: Marge (volledige posten) | F4: Marge % | G4: Posten niet volledig
A5: Lot 1 | B5: ='Lot 1'!Z36 | C5: ='Lot 1'!Y36 | D5: ='Lot 1'!AA36 | E5: ='Lot 1'!AB36 | F5: =IF(C5=0,"",E5/C5) | G5: =COUNTIF('Lot 1'!AC2:AC34,"<>OK")
A6: Lot 2 | B6: ='Lot 2'!Z133 | C6: ='Lot 2'!Y133 | D6: ='Lot 2'!AA133 | E6: ='Lot 2'!AB133 | F6: =IF(C6=0,"",E6/C6) | G6: =COUNTIF('Lot 2'!AC2:AC131,"<>OK")
A7: Totaal | B7: =SUM(B5:B6) | C7: =SUM(C5:C6) | D7: =SUM(D5:D6) | E7: =SUM(E5:E6) | F7: =IF(C7=0,"",E7/C7) | G7: =SUM(G5:G6)
A10: Werkwijze:
A11: 1. Tab Materialen: per materiaal het Igepa-artikel kiezen, aankoopformaat, m² per rol/plaat en uw nettoprijs invullen (gele cellen).
A12: 2. Tab Instellingen: inktprijs/verbruik, afval % en intern uurtarief invullen.
A13: 3. Tabs Lot 1 / Lot 2: per post eventueel arbeidsminuten en overige kosten (hoogwerker, transport) invullen.
A14: 4. Kolom 'Marge %' kleurt rood onder de doelmarge, oranje tot +15 punten, groen daarboven.
A15: 5. 'Verkoop / m²' vs 'Aankoop mat. / m²' toont per post de factor tussen verkoop en materiaalprijs.
A16: Aannames om te controleren: verbruik in m² = nettoformaat × (1 + afval %); oogjes geteld volgens bestek (om de 30/50 cm);
A17: zomen, gaines en lasnaden niet apart in m² meegerekend; posten 22 (per 10) en 23 (per stuk) volgen de interpretatie uit de offerte.

Sheet Instellingen
A1: Instellingen kostprijsberekening (gele cellen = invullen)
A3: Afval % rolmedia (zeil, vinyl, textiel, film) | B3: 0.1 | C3: Aanname – aanpassen aan uw praktijk
A4: Afval % plaatmateriaal (Forex, Dibond, plexi, karton, biprint) | B4: 0.15 | C4: Aanname – hangt af van nesting op plaatformaat
A5: Latex-inkt: prijs per cartridge excl. btw | C5: Uit Igepa (bv. HP Latex 775 ml / 1 L)
A6: Latex-inkt: ml per cartridge | C6: bv. 775 of 1000
A7: Latex-inkt: verbruik ml per m² | C7: Uit uw RIP / printerlog, per printmodus
A8: Inktkost per m² (berekend) | B8: =IF(AND(B5>0,B6>0,B7>0),B5/B6*B7,0) | C8: prijs ÷ ml per cartridge × ml/m²
A9: Intern uurtarief (loonkost) excl. btw | C9: Voor de kolom arbeid in Lot 1 / Lot 2
A10: Doelmarge (ondergrens, voor kleurcode) | B10: 0.35 | C10: Rood onder deze marge

Sheet Materialen
A1: ID | B1: Materiaal (eis uit bestek) | C1: Zoekterm Igepa | D1: Type | E1: Bedrukt (J/N) | F1: Aankoopformaat (bv. rol 1,60 x 50 m / plaat 3,05 x 2,03 m) | G1: m² per aankoopeenheid (stukgoed: aantal stuks per verpakking) | H1: Aankoopprijs per eenheid excl. btw | I1: Aankoopprijs per m² / stuk | J1: Igepa artikelnr. | K1: Opmerking
A2: M01 | B2: Backlit PVC-zeil 650 g/m², M2/B1 (backlight 3x4 m) | C2: backlit 650 / Blockout backlit | D2: rol | E2: J | I2: =IF(AND(G2>0,H2>0),H2/G2,"")
A3: M02 | B3: Frontlit PVC-zeil 450 g/m² (kakémono entrées, Warocqué, bas rue Neuve, bannière) | C3: frontlit 450 | D3: rol | E3: J | I3: =IF(AND(G3>0,H3>0),H3/G3,"")
A4: M03 | B4: PVC-zeil 550 g/m² 'pro' (Duesberg, cube VisitMons) | C4: frontlit 510/550 | D4: rol | E4: J | I4: =IF(AND(G4>0,H4>0),H4/G4,"")
A5: M04 | B5: Mesh micro-geperforeerd 450 g/m² (kakémono Imagix) | C5: mesh 450 / mesh backlit | D5: rol | E5: J | I5: =IF(AND(G5>0,H5>0),H5/G5,"")
A6: M05 | B6: Mesh 350 g/m² (bâche travaux) | C6: mesh 350 | D6: rol | E6: J | I6: =IF(AND(G6>0,H6>0),H6/G6,"")
A7: M06 | B7: Mesh micro-geperforeerd 290 g/m² (Heras, Nadar) | C7: mesh 270/290 | D7: rol | E7: J | I7: =IF(AND(G7>0,H7>0),H7/G7,"")
A8: M07 | B8: PVC-zeil 330 g/m² (bâches cubes) | C8: frontlit 340 / light | D8: rol | E8: J | I8: =IF(AND(G8>0,H8>0),H8/G8,"")
A9: M10 | B9: Roll-up film (PET/PP greyback, anti-curl) | C9: roll-up film | D9: rol | E9: J | I9: =IF(AND(G9>0,H9>0),H9/G9,"")
A10: M11 | B10: Roll-up cassette 85 x 200 cm + tas | C10: roll-up 85 | D10: stuk | E10: N | G10: 1 | I10: =IF(AND(G10>0,H10>0),H10/G10,"")
A11: M12 | B11: Roll-up cassette 60 x 160 cm + tas | C11: roll-up 60 | D11: stuk | E11: N | G11: 1 | I11: =IF(AND(G11>0,H11>0),H11/G11,"")
A12: M13 | B12: Elektrostatische folie (type Yupo Tako / static cling) | C12: static cling / Yupo Tako | D12: rol | E12: J | I12: =IF(AND(G12>0,H12>0),H12/G12,"")
A13: M14 | B13: Polymeer vinyl transparant glanzend (Prix Mercure, wit onderdruk) | C13: polymeer transparant glans | D13: rol | E13: J | I13: =IF(AND(G13>0,H13>0),H13/G13,"")
A14: M15 | B14: Monomeer vinyl wit (stickers, vitrine, totem, Lot 2 vinyl binnen) | C14: monomeer wit glans/mat | D14: rol | E14: J | I14: =IF(AND(G14>0,H14>0),H14/G14,"")
A15: M16 | B15: One-way vision / micro-geperforeerd raamvinyl (voertuig) | C15: one way vision | D15: rol | E15: J | I15: =IF(AND(G15>0,H15>0),H15/G15,"")
A16: M17 | B16: Cast/polymeer wrapfolie carrosserie (+ evt. laminaat) | C16: cast wrap / polymeer | D16: rol | E16: J | I16: =IF(AND(G16>0,H16>0),H16/G16,"")
A17: M18 | B17: Polymeer vinyl buiten | C17: polymeer wit | D17: rol | E17: J | I17: =IF(AND(G17>0,H17>0),H17/G17,"")
A18: M19 | B18: Laminaat monomeer glanzend (totem) | C18: laminaat monomeer glans | D18: rol | E18: N | I18: =IF(AND(G18>0,H18>0),H18/G18,"")
A19: M20 | B19: Beachflag-textiel polyester knit ±110 g/m² | C19: flag 110 / vlaggendoek | D19: rol | E19: J | I19: =IF(AND(G19>0,H19>0),H19/G19,"")
A20: M21 | B20: Beachflag-kit: alu mast 350 cm, horizontale arm, kruisvoet, tas | C20: beachflag kit | D20: stuk | E20: N | G20: 1 | I20: =IF(AND(G20>0,H20>0),H20/G20,"")
A21: M22 | B21: Biprint / PP-alveolair 3 mm | C21: biprint 3 mm | D21: plaat | E21: J | I21: =IF(AND(G21>0,H21>0),H21/G21,"")
A22: M23 | B22: Akylux / PP-alveolair (3,5 mm? bestek: '3,5 cm' – te verifiëren) | C22: akylux | D22: plaat | E22: J | I22: =IF(AND(G22>0,H22>0),H22/G22,"")
A23: M24 | B23: Balelastiek 5 mm, 15 cm | C23: balelastiek | D23: stuk | E23: N | G23: 1 | I23: =IF(AND(G23>0,H23>0),H23/G23,"")
A24: M25 | B24: Metalen oogjes (per stuk, incl. ring) | C24: oogjes / zeilringen | D24: stuk | E24: N | G24: 1 | I24: =IF(AND(G24>0,H24>0),H24/G24,"")
A25: M26 | B25: Ophangsysteem / klemlijsten op maat (backlight) | C25: klemprofiel / spieprofiel | D25: stuk | E25: N | G25: 1 | I25: =IF(AND(G25>0,H25>0),H25/G25,"")
A26: M30 | B26: Polyester textiel 300 g/m² wit M1, wandkleefbaar | C26: textiel 300 M1 / wallpaper textile | D26: rol | E26: J | I26: =IF(AND(G26>0,H26>0),H26/G26,"")
A27: M31 | B27: Forex (PVC-hardschuim) 2 mm wit | C27: forex 2 mm | D27: plaat | E27: J | I27: =IF(AND(G27>0,H27>0),H27/G27,"")
A28: M32 | B28: Forex 3 mm wit | C28: forex 3 mm | D28: plaat | E28: J | I28: =IF(AND(G28>0,H28>0),H28/G28,"")
A29: M33 | B29: Forex 5 mm wit | C29: forex 5 mm | D29: plaat | E29: J | I29: =IF(AND(G29>0,H29>0),H29/G29,"")
A30: M34 | B30: Plexi (PMMA) opaal mat 2 mm | C30: plexi opaal 2 mm | D30: plaat | E30: J | I30: =IF(AND(G30>0,H30>0),H30/G30,"")
A31: M35 | B31: Plexi (PMMA) opaal mat 3 mm | C31: plexi opaal 3 mm | D31: plaat | E31: J | I31: =IF(AND(G31>0,H31>0),H31/G31,"")
A32: M36 | B32: Karton 2 mm (bedrukbaar) | C32: karton 2 mm / honingraat / reboard | D32: plaat | E32: J | I32: =IF(AND(G32>0,H32>0),H32/G32,"")
A33: M37 | B33: Karton 1 mm (bedrukbaar) | C33: karton 1 mm | D33: plaat | E33: J | I33: =IF(AND(G33>0,H33>0),H33/G33,"")
A34: M39 | B34: Dibond / alu-composiet 2 mm wit | C34: dibond 2 mm | D34: plaat | E34: J | I34: =IF(AND(G34>0,H34>0),H34/G34,"")
A35: M40 | B35: Dibond / alu-composiet 3 mm wit | C35: dibond 3 mm | D35: plaat | E35: J | I35: =IF(AND(G35>0,H35>0),H35/G35,"")
A36: M41 | B36: Snijvinyl gekleurd/zwart (type Oracal 641/651) | C36: snijfolie / plotterfolie | D36: rol | E36: N | I36: =IF(AND(G36>0,H36>0),H36/G36,"")
A37: M42 | B37: Applicatietape (transfer) | C37: applicatietape | D37: rol | E37: N | I37: =IF(AND(G37>0,H37>0),H37/G37,"")
A38: M43 | B38: Dubbelzijdige tape wandmontage (per lopende meter) | C38: dubbelzijdig montagetape | D38: stuk | E38: N | G38: 1 | I38: =IF(AND(G38>0,H38>0),H38/G38,"")
A39: M44 | B39: Metalen U-profiel / ophanglat (per stuk) | C39: U-profiel / ophangprofiel | D39: stuk | E39: N | G39: 1 | I39: =IF(AND(G39>0,H39>0),H39/G39,"")

Sheet Lot 1
A1: N° | B1: Rubriek | C1: Omschrijving | D1: Eenheid | E1: Q | F1: Verkoop PU excl. btw | G1: Materiaal 1 | H1: m² mat. 1 / eenheid | I1: Materiaal 2 | J1: m² mat. 2 / eenheid | K1: Acc. 1 | L1: Aantal acc. 1 | M1: Acc. 2 | N1: Aantal acc. 2 | O1: Afval % | P1: Materiaalkost / eenheid | Q1: Inktkost / eenheid | R1: Arbeid min / eenheid | S1: Arbeid € / eenheid | T1: Overige kost / eenheid (huur, transport) | U1: Kostprijs / eenheid | V1: Marge € / eenheid | W1: Marge % | X1: Verkoop / m² | Y1: Aankoop mat. / m² | Z1: Totaal verkoop | AA1: Totaal kost | AB1: Totaal marge | AC1: Controle | AD1: Opmerking
A2: 1 | B2: BÂCHE BACKLIGHT | C2: Format 3x4m (format utile 280x380cm) - Bâche rétroéclairée M2 de 650gr - Quadrichromie - attaches par réglette sur mesure | D2: pièce | E2: 20 | F2: 225 | G2: M01 | H2: 12 | K2: M26 | L2: 1 | O2: =IF(G2="","",IF(IFERROR(VLOOKUP(G2,Materialen!$A$2:$I$39,4,0),"")="plaat",Instellingen!$B$4,Instellingen!$B$3)) | P2: =ROUND(N(H2)*IFERROR(IF(VLOOKUP(G2,Materialen!$A$2:$I$39,9,0)="",0,VLOOKUP(G2,Materialen!$A$2:$I$39,9,0)),0)*(1+N(O2))+N(J2)*IFERROR(IF(VLOOKUP(I2,Materialen!$A$2:$I$39,9,0)="",0,VLOOKUP(I2,Materialen!$A$2:$I$39,9,0)),0)*(1+N(O2))+N(L2)*IFERROR(IF(VLOOKUP(K2,Materialen!$A$2:$I$39,9,0)="",0,VLOOKUP(K2,Materialen!$A$2:$I$39,9,0)),0)+N(N2)*IFERROR(IF(VLOOKUP(M2,Materialen!$A$2:$I$39,9,0)="",0,VLOOKUP(M2,Materialen!$A$2:$I$39,9,0)),0),2) | Q2: =IF(G2="",0,IF(IFERROR(VLOOKUP(G2,Materialen!$A$2:$I$39,5,0),"N")="J",ROUND(N(H2)*(1+N(O2))*Instellingen!$B$8,2),0)) | S2: =ROUND(N(R2)/60*Instellingen!$B$9,2) | U2: =P2+Q2+S2+N(T2) | V2: =IF(AC2<>"OK","",F2-U2) | W2: =IF(OR(F2=0,AC2<>"OK"),"",V2/F2) | X2: =IF(N(H2)>0,F2/H2,"") | Y2: =IF(N(H2)>0,IFERROR(IF(VLOOKUP(G2,Materialen!$A$2:$I$39,9,0)="",0,VLOOKUP(G2,Materialen!$A$2:$I$39,9,0)),0),"") | Z2: =ROUND(E2*F2,2) | AA2: =IF(AC2<>"OK","",ROUND(E2*U2,2)) | AB2: =IF(AC2<>"OK","",Z2-AA2) | AC2: =IF((IF(G2="",0,IF(IFERROR(IF(VLOOKUP(G2,Materialen!$A$2:$I$39,9,0)="",0,VLOOKUP(G2,Materialen!$A$2:$I$39,9,0)),0)=0,1,0))+IF(I2="",0,IF(IFERROR(IF(VLOOKUP(I2,Materialen!$A$2:$I$39,9,0)="",0,VLOOKUP(I2,Materialen!$A$2:$I$39,9,0)),0)=0,1,0))+IF(K2="",0,IF(IFERROR(IF(VLOOKUP(K2,Materialen!$A$2:$I$39,9,0)="",0,VLOOKUP(K2,Materialen!$A$2:$I$39,9,0)),0)=0,1,0))+IF(M2="",0,IF(IFERROR(IF(VLOOKUP(M2,Materialen!$A$2:$I$39,9,0)="",0,VLOOKUP(M2,Materialen!$A$2:$I$39,9,0)),0)=0,1,0)))>0,"aankoopprijs ontbreekt",IF(AND(G2="",K2="",N(T2)=0,N(R2)=0),"kost invullen (arbeid/overig)","OK")) | AD2: Drukformaat 3x4 m
A3: 2 | B3: BÂCHE BACKLIGHT | C3: Placement de la bâche sur place (8, rue neuve) à l'aide d'un élévateur (8, rue neuve) | D3: placement | E3: 20 | F3: 165 | O3: =IF(G3="","",IF(IFERROR(VLOOKUP(G3,Materialen!$A$2:$I$39,4,0),"")="plaat",Instellingen!$B$4,Instellingen!$B$3)) | P3: =ROUND(N(H3)*IFERROR(IF(VLOOKUP(G3,Materialen!$A$2:$I$39,9,0)="",0,VLOOKUP(G3,Materialen!$A$2:$I$39,9,0)),0)*(1+N(O3))+N(J3)*IFERROR(IF(VLOOKUP(I3,Materialen!$A$2:$I$39,9,0)="",0,VLOOKUP(I3,Materialen!$A$2:$I$39,9,0)),0)*(1+N(O3))+N(L3)*IFERROR(IF(VLOOKUP(K3,Materialen!$A$2:$I$39,9,0)="",0,VLOOKUP(K3,Materialen!$A$2:$I$39,9,0)),0)+N(N3)*IFERROR(IF(VLOOKUP(M3,Materialen!$A$2:$I$39,9,0)="",0,VLOOKUP(M3,Materialen!$A$2:$I$39,9,0)),0),2) | Q3: =IF(G3="",0,IF(IFERROR(VLOOKUP(G3,Materialen!$A$2:$I$39,5,0),"N")="J",ROUND(N(H3)*(1+N(O3))*Instellingen!$B$8,2),0)) | S3: =ROUND(N(R3)/60*Instellingen!$B$9,2) | U3: =P3+Q3+S3+N(T3) | V3: =IF(AC3<>"OK","",F3-U3) | W3: =IF(OR(F3=0,AC3<>"OK"),"",V3/F3) | X3: =IF(N(H3)>0,F3/H3,"") | Y3: =IF(N(H3)>0,IFERROR(IF(VLOOKUP(G3,Materialen!$A$2:$I$39,9,0)="",0,VLOOKUP(G3,Materialen!$A$2:$I$39,9,0)),0),"") | Z3: =ROUND(E3*F3,2) | AA3: =IF(AC3<>"OK","",ROUND(E3*U3,2)) | AB3: =IF(AC3<>"OK","",Z3-AA3) | AC3: =IF((IF(G3="",0,IF(IFERROR(IF(VLOOKUP(G3,Materialen!$A$2:$I$39,9,0)="",0,VLOOKUP(G3,Materialen!$A$2:$I$39,9,0)),0)=0,1,0))+IF(I3="",0,IF(IFERROR(IF(VLOOKUP(I3,Materialen!$A$2:$I$39,9,0)="",0,VLOOKUP(I3,Materialen!$A$2:$I$39,9,0)),0)=0,1,0))+IF(K3="",0,IF(IFERROR(IF(VLOOKUP(K3,Materialen!$A$2:$I$39,9,0)="",0,VLOOKUP(K3,Materialen!$A$2:$I$39,9,0)),0)=0,1,0))+IF(M3="",0,IF(IFERROR(IF(VLOOKUP(M3,Materialen!$A$2:$I$39,9,0)="",0,VLOOKUP(M3,Materialen!$A$2:$I$39,9,0)),0)=0,1,0)))>0,"aankoopprijs ontbreekt",IF(AND(G3="",K3="",N(T3)=0,N(R3)=0),"kost invullen (arbeid/overig)","OK")) | AD3: Hoogwerker + plaatsing → kolom 'overige kost' en arbeid
A4: 3 | B4: KAKEMONOS | C4: Musée Duesberg : H 251 cm x 79 cm - impression quadri recto / verso - ourlet supérieur et inférieur | D4: pièce | E4: 10 | F4: 48 | G4: M03 | H4: 1.9829 | O4: =IF(G4="","",IF(IFERROR(VLOOKUP(G4,Materialen!$A$2:$I$39,4,0),"")="plaat",Instellingen!$B$4,Instellingen!$B$3)) | P4: =ROUND(N(H4)*IFERROR(IF(VLOOKUP(G4,Materialen!$A$2:$I$39,9,0)="",0,VLOOKUP(G4,Materialen!$A$2:$I$39,9,0)),0)*(1+N(O4))+N(J4)*IFERROR(IF(VLOOKUP(I4,Materialen!$A$2:$I$39,9,0)="",0,VLOOKUP(I4,Materialen!$A$2:$I$39,9,0)),0)*(1+N(O4))+N(L4)*IFERROR(IF(VLOOKUP(K4,Materialen!$A$2:$I$39,9,0)="",0,VLOOKUP(K4,Materialen!$A$2:$I$39,9,0)),0)+N(N4)*IFERROR(IF(VLOOKUP(M4,Materialen!$A$2:$I$39,9,0)="",0,VLOOKUP(M4,Materialen!$A$2:$I$39,9,0)),0),2) | Q4: =IF(G4="",0,IF(IFERROR(VLOOKUP(G4,Materialen!$A$2:$I$39,5,0),"N")="J",ROUND(N(H4)*(1+N(O4))*Instellingen!$B$8,2),0)) | S4: =ROUND(N(R4)/60*Instellingen!$B$9,2) | U4: =P4+Q4+S4+N(T4) | V4: =IF(AC4<>"OK","",F4-U4) | W4: =IF(OR(F4=0,AC4<>"OK"),"",V4/F4) | X4: =IF(N(H4)>0,F4/H4,"") | Y4: =IF(N(H4)>0,IFERROR(IF(VLOOKUP(G4,Materialen!$A$2:$I$39,9,0)="",0,VLOOKUP(G4,Materialen!$A$2:$I$39,9,0)),0),"") | Z4: =ROUND(E4*F4,2) | AA4: =IF(AC4<>"OK","",ROUND(E4*U4,2)) | AB4: =IF(AC4<>"OK","",Z4-AA4) | AC4: =IF((IF(G4="",0,IF(IFERROR(IF(VLOOKUP(G4,Materialen!$A$2:$I$39,9,0)="",0,VLOOKUP(G4,Materialen!$A$2:$I$39,9,0)),0)=0,1,0))+IF(I4="",0,IF(IFERROR(IF(VLOOKUP(I4,Materialen!$A$2:$I$39,9,0)="",0,VLOOKUP(I4,Materialen!$A$2:$I$39,9,0)),0)=0,1,0))+IF(K4="",0,IF(IFERROR(IF(VLOOKUP(K4,Materialen!$A$2:$I$39,9,0)="",0,VLOOKUP(K4,Materialen!$A$2:$I$39,9,0)),0)=0,1,0))+IF(M4="",0,IF(IFERROR(IF(VLOOKUP(M4,Materialen!$A$2:$I$39,9,0)="",0,VLOOKUP(M4,Materialen!$A$2:$I$39,9,0)),0)=0,1,0)))>0,"aankoopprijs ontbreekt",IF(AND(G4="",K4="",N(T4)=0,N(R4)=0),"kost invullen (arbeid/overig)","OK"))
A5: 4 | B5: KAKEMONOS | C5: Entrées de ville : Format L100 x H300 cm - bâche sur Frontlit 450 gr quadri recto UV, avec gaines cousues haut et bas de 8 cm à plat | D5: pièce | E5: 130 | F5: 49 | G5: M02 | H5: 3 | O5: =IF(G5="","",IF(IFERROR(VLOOKUP(G5,Materialen!$A$2:$I$39,4,0),"")="plaat",Instellingen!$B$4,Instellingen!$B$3)) | P5: =ROUND(N(H5)*IFERROR(IF(VLOOKUP(G5,Materialen!$A$2:$I$39,9,0)="",0,VLOOKUP(G5,Materialen!$A$2:$I$39,9,0)),0)*(1+N(O5))+N(J5)*IFERROR(IF(VLOOKUP(I5,Materialen!$A$2:$I$39,9,0)="",0,VLOOKUP(I5,Materialen!$A$2:$I$39,9,0)),0)*(1+N(O5))+N(L5)*IFERROR(IF(VLOOKUP(K5,Materialen!$A$2:$I$39,9,0)="",0,VLOOKUP(K5,Materialen!$A$2:$I$39,9,0)),0)+N(N5)*IFERROR(IF(VLOOKUP(M5,Materialen!$A$2:$I$39,9,0)="",0,VLOOKUP(M5,Materialen!$A$2:$I$39,9,0)),0),2) | Q5: =IF(G5="",0,IF(IFERROR(VLOOKUP(G5,Materialen!$A$2:$I$39,5,0),"N")="J",ROUND(N(H5)*(1+N(O5))*Instellingen!$B$8,2),0)) | S5: =ROUND(N(R5)/60*Instellingen!$B$9,2) | U5: =P5+Q5+S5+N(T5) | V5: =IF(AC5<>"OK","",F5-U5) | W5: =IF(OR(F5=0,AC5<>"OK"),"",V5/F5) | X5: =IF(N(H5)>0,F5/H5,"") | Y5: =IF(N(H5)>0,IFERROR(IF(VLOOKUP(G5,Materialen!$A$2:$I$39,9,0)="",0,VLOOKUP(G5,Materialen!$A$2:$I$39,9,0)),0),"") | Z5: =ROUND(E5*F5,2) | AA5: =IF(AC5<>"OK","",ROUND(E5*U5,2)) | AB5: =IF(AC5<>"OK","",Z5-AA5) | AC5: =IF((IF(G5="",0,IF(IFERROR(IF(VLOOKUP(G5,Materialen!$A$2:$I$39,9,0)="",0,VLOOKUP(G5,Materialen!$A$2:$I$39,9,0)),0)=0,1,0))+IF(I5="",0,IF(IFERROR(IF(VLOOKUP(I5,Materialen!$A$2:$I$39,9,0)="",0,VLOOKUP(I5,Materialen!$A$2:$I$39,9,0)),0)=0,1,0))+IF(K5="",0,IF(IFERROR(IF(VLOOKUP(K5,Materialen!$A$2:$I$39,9,0)="",0,VLOOKUP(K5,Materialen!$A$2:$I$39,9,0)),0)=0,1,0))+IF(M5="",0,IF(IFERROR(IF(VLOOKUP(M5,Materialen!$A$2:$I$39,9,0)="",0,VLOOKUP(M5,Materialen!$A$2:$I$39,9,0)),0)=0,1,0)))>0,"aankoopprijs ontbreekt",IF(AND(G5="",K5="",N(T5)=0,N(R5)=0),"kost invullen (arbeid/overig)","OK")) | AD5: Gaines 8 cm: + stof voor zomen niet meegeteld
A6: 5 | B6: KAKEMONOS | C6: Imagix: Format L150 x H450 cm - bâche micro-perforée 450 gr quadri recto UV, avec gaines cousues haut et bas de 8 cm à plat | D6: pièce | E6: 35 | F6: 110 | G6: M04 | H6: 6.75 | O6: =IF(G6="","",IF(IFERROR(VLOOKUP(G6,Materialen!$A$2:$I$39,4,0),"")="plaat",Instellingen!$B$4,Instellingen!$B$3)) | P6: =ROUND(N(H6)*IFERROR(IF(VLOOKUP(G6,Materialen!$A$2:$I$39,9,0)="",0,VLOOKUP(G6,Materialen!$A$2:$I$39,9,0)),0)*(1+N(O6))+N(J6)*IFERROR(IF(VLOOKUP(I6,Materialen!$A$2:$I$39,9,0)="",0,VLOOKUP(I6,Materialen!$A$2:$I$39,9,0)),0)*(1+N(O6))+N(L6)*IFERROR(IF(VLOOKUP(K6,Materialen!$A$2:$I$39,9,0)="",0,VLOOKUP(K6,Materialen!$A$2:$I$39,9,0)),0)+N(N6)*IFERROR(IF(VLOOKUP(M6,Materialen!$A$2:$I$39,9,0)="",0,VLOOKUP(M6,Materialen!$A$2:$I$39,9,0)),0),2) | Q6: =IF(G6="",0,IF(IFERROR(VLOOKUP(G6,Materialen!$A$2:$I$39,5,0),"N")="J",ROUND(N(H6)*(1+N(O6))*Instellingen!$B$8,2),0)) | S6: =ROUND(N(R6)/60*Instellingen!$B$9,2) | U6: =P6+Q6+S6+N(T6) | V6: =IF(AC6<>"OK","",F6-U6) | W6: =IF(OR(F6=0,AC6<>"OK"),"",V6/F6) | X6: =IF(N(H6)>0,F6/H6,"") | Y6: =IF(N(H6)>0,IFERROR(IF(VLOOKUP(G6,Materialen!$A$2:$I$39,9,0)="",0,VLOOKUP(G6,Materialen!$A$2:$I$39,9,0)),0),"") | Z6: =ROUND(E6*F6,2) | AA6: =IF(AC6<>"OK","",ROUND(E6*U6,2)) | AB6: =IF(AC6<>"OK","",Z6-AA6) | AC6: =IF((IF(G6="",0,IF(IFERROR(IF(VLOOKUP(G6,Materialen!$A$2:$I$39,9,0)="",0,VLOOKUP(G6,Materialen!$A$2:$I$39,9,0)),0)=0,1,0))+IF(I6="",0,IF(IFERROR(IF(VLOOKUP(I6,Materialen!$A$2:$I$39,9,0)="",0,VLOOKUP(I6,Materialen!$A$2:$I$39,9,0)),0)=0,1,0))+IF(K6="",0,IF(IFERROR(IF(VLOOKUP(K6,Materialen!$A$2:$I$39,9,0)="",0,VLOOKUP(K6,Materialen!$A$2:$I$39,9,0)),0)=0,1,0))+IF(M6="",0,IF(IFERROR(IF(VLOOKUP(M6,Materialen!$A$2:$I$39,9,0)="",0,VLOOKUP(M6,Materialen!$A$2:$I$39,9,0)),0)=0,1,0)))>0,"aankoopprijs ontbreekt",IF(AND(G6="",K6="",N(T6)=0,N(R6)=0),"kost invullen (arbeid/overig)","OK"))
A7: 6 | B7: BÂCHE | C7: Bâche travaux: Bâche microperforée mesh 350gr/m² Format L 280cm x H 380cm Impression digital quadricouleur Finition doublure + œillets métalliques tous les 50cm | D7: pièce | E7: 20 | F7: 130 | G7: M05 | H7: 10.64 | K7: M25 | L7: 27 | O7: =IF(G7="","",IF(IFERROR(VLOOKUP(G7,Materialen!$A$2:$I$39,4,0),"")="plaat",Instellingen!$B$4,Instellingen!$B$3)) | P7: =ROUND(N(H7)*IFERROR(IF(VLOOKUP(G7,Materialen!$A$2:$I$39,9,0)="",0,VLOOKUP(G7,Materialen!$A$2:$I$39,9,0)),0)*(1+N(O7))+N(J7)*IFERROR(IF(VLOOKUP(I7,Materialen!$A$2:$I$39,9,0)="",0,VLOOKUP(I7,Materialen!$A$2:$I$39,9,0)),0)*(1+N(O7))+N(L7)*IFERROR(IF(VLOOKUP(K7,Materialen!$A$2:$I$39,9,0)="",0,VLOOKUP(K7,Materialen!$A$2:$I$39,9,0)),0)+N(N7)*IFERROR(IF(VLOOKUP(M7,Materialen!$A$2:$I$39,9,0)="",0,VLOOKUP(M7,Materialen!$A$2:$I$39,9,0)),0),2) | Q7: =IF(G7="",0,IF(IFERROR(VLOOKUP(G7,Materialen!$A$2:$I$39,5,0),"N")="J",ROUND(N(H7)*(1+N(O7))*Instellingen!$B$8,2),0)) | S7: =ROUND(N(R7)/60*Instellingen!$B$9,2) | U7: =P7+Q7+S7+N(T7) | V7: =IF(AC7<>"OK","",F7-U7) | W7: =IF(OR(F7=0,AC7<>"OK"),"",V7/F7) | X7: =IF(N(H7)>0,F7/H7,"") | Y7: =IF(N(H7)>0,IFERROR(IF(VLOOKUP(G7,Materialen!$A$2:$I$39,9,0)="",0,VLOOKUP(G7,Materialen!$A$2:$I$39,9,0)),0),"") | Z7: =ROUND(E7*F7,2) | AA7: =IF(AC7<>"OK","",ROUND(E7*U7,2)) | AB7: =IF(AC7<>"OK","",Z7-AA7) | AC7: =IF((IF(G7="",0,IF(IFERROR(IF(VLOOKUP(G7,Materialen!$A$2:$I$39,9,0)="",0,VLOOKUP(G7,Materialen!$A$2:$I$39,9,0)),0)=0,1,0))+IF(I7="",0,IF(IFERROR(IF(VLOOKUP(I7,Materialen!$A$2:$I$39,9,0)="",0,VLOOKUP(I7,Materialen!$A$2:$I$39,9,0)),0)=0,1,0))+IF(K7="",0,IF(IFERROR(IF(VLOOKUP(K7,Materialen!$A$2:$I$39,9,0)="",0,VLOOKUP(K7,Materialen!$A$2:$I$39,9,0)),0)=0,1,0))+IF(M7="",0,IF(IFERROR(IF(VLOOKUP(M7,Materialen!$A$2:$I$39,9,0)="",0,VLOOKUP(M7,Materialen!$A$2:$I$39,9,0)),0)=0,1,0)))>0,"aankoopprijs ontbreekt",IF(AND(G7="",K7="",N(T7)=0,N(R7)=0),"kost invullen (arbeid/overig)","OK")) | AD7: Oogjes om de 50 cm
A8: 7 | B8: BÂCHE | C8: Bâche barrières HERAS : Bâche micro perforée290gr format H 1,7 m x 3,4 m impression quadri finition doublure + œillets métalliques tous les 50 cm | D8: pièce | E8: 30 | F8: 70 | G8: M06 | H8: 5.78 | K8: M25 | L8: 21 | O8: =IF(G8="","",IF(IFERROR(VLOOKUP(G8,Materialen!$A$2:$I$39,4,0),"")="plaat",Instellingen!$B$4,Instellingen!$B$3)) | P8: =ROUND(N(H8)*IFERROR(IF(VLOOKUP(G8,Materialen!$A$2:$I$39,9,0)="",0,VLOOKUP(G8,Materialen!$A$2:$I$39,9,0)),0)*(1+N(O8))+N(J8)*IFERROR(IF(VLOOKUP(I8,Materialen!$A$2:$I$39,9,0)="",0,VLOOKUP(I8,Materialen!$A$2:$I$39,9,0)),0)*(1+N(O8))+N(L8)*IFERROR(IF(VLOOKUP(K8,Materialen!$A$2:$I$39,9,0)="",0,VLOOKUP(K8,Materialen!$A$2:$I$39,9,0)),0)+N(N8)*IFERROR(IF(VLOOKUP(M8,Materialen!$A$2:$I$39,9,0)="",0,VLOOKUP(M8,Materialen!$A$2:$I$39,9,0)),0),2) | Q8: =IF(G8="",0,IF(IFERROR(VLOOKUP(G8,Materialen!$A$2:$I$39,5,0),"N")="J",ROUND(N(H8)*(1+N(O8))*Instellingen!$B$8,2),0)) | S8: =ROUND(N(R8)/60*Instellingen!$B$9,2) | U8: =P8+Q8+S8+N(T8) | V8: =IF(AC8<>"OK","",F8-U8) | W8: =IF(OR(F8=0,AC8<>"OK"),"",V8/F8) | X8: =IF(N(H8)>0,F8/H8,"") | Y8: =IF(N(H8)>0,IFERROR(IF(VLOOKUP(G8,Materialen!$A$2:$I$39,9,0)="",0,VLOOKUP(G8,Materialen!$A$2:$I$39,9,0)),0),"") | Z8: =ROUND(E8*F8,2) | AA8: =IF(AC8<>"OK","",ROUND(E8*U8,2)) | AB8: =IF(AC8<>"OK","",Z8-AA8) | AC8: =IF((IF(G8="",0,IF(IFERROR(IF(VLOOKUP(G8,Materialen!$A$2:$I$39,9,0)="",0,VLOOKUP(G8,Materialen!$A$2:$I$39,9,0)),0)=0,1,0))+IF(I8="",0,IF(IFERROR(IF(VLOOKUP(I8,Materialen!$A$2:$I$39,9,0)="",0,VLOOKUP(I8,Materialen!$A$2:$I$39,9,0)),0)=0,1,0))+IF(K8="",0,IF(IFERROR(IF(VLOOKUP(K8,Materialen!$A$2:$I$39,9,0)="",0,VLOOKUP(K8,Materialen!$A$2:$I$39,9,0)),0)=0,1,0))+IF(M8="",0,IF(IFERROR(IF(VLOOKUP(M8,Materialen!$A$2:$I$39,9,0)="",0,VLOOKUP(M8,Materialen!$A$2:$I$39,9,0)),0)=0,1,0)))>0,"aankoopprijs ontbreekt",IF(AND(G8="",K8="",N(T8)=0,N(R8)=0),"kost invullen (arbeid/overig)","OK")) | AD8: Oogjes om de 50 cm
A9: 8 | B9: BÂCHE | C9: Bâche bas de la rue Neuve: H380 x L260 cm, avec œillets tous les 30 cm et élastiques, impression en quadrichromie | D9: pièce | E9: 10 | F9: 115 | G9: M02 | H9: 9.88 | K9: M25 | L9: 43 | M9: M24 | N9: 43 | O9: =IF(G9="","",IF(IFERROR(VLOOKUP(G9,Materialen!$A$2:$I$39,4,0),"")="plaat",Instellingen!$B$4,Instellingen!$B$3)) | P9: =ROUND(N(H9)*IFERROR(IF(VLOOKUP(G9,Materialen!$A$2:$I$39,9,0)="",0,VLOOKUP(G9,Materialen!$A$2:$I$39,9,0)),0)*(1+N(O9))+N(J9)*IFERROR(IF(VLOOKUP(I9,Materialen!$A$2:$I$39,9,0)="",0,VLOOKUP(I9,Materialen!$A$2:$I$39,9,0)),0)*(1+N(O9))+N(L9)*IFERROR(IF(VLOOKUP(K9,Materialen!$A$2:$I$39,9,0)="",0,VLOOKUP(K9,Materialen!$A$2:$I$39,9,0)),0)+N(N9)*IFERROR(IF(VLOOKUP(M9,Materialen!$A$2:$I$39,9,0)="",0,VLOOKUP(M9,Materialen!$A$2:$I$39,9,0)),0),2) | Q9: =IF(G9="",0,IF(IFERROR(VLOOKUP(G9,Materialen!$A$2:$I$39,5,0),"N")="J",ROUND(N(H9)*(1+N(O9))*Instellingen!$B$8,2),0)) | S9: =ROUND(N(R9)/60*Instellingen!$B$9,2) | U9: =P9+Q9+S9+N(T9) | V9: =IF(AC9<>"OK","",F9-U9) | W9: =IF(OR(F9=0,AC9<>"OK"),"",V9/F9) | X9: =IF(N(H9)>0,F9/H9,"") | Y9: =IF(N(H9)>0,IFERROR(IF(VLOOKUP(G9,Materialen!$A$2:$I$39,9,0)="",0,VLOOKUP(G9,Materialen!$A$2:$I$39,9,0)),0),"") | Z9: =ROUND(E9*F9,2) | AA9: =IF(AC9<>"OK","",ROUND(E9*U9,2)) | AB9: =IF(AC9<>"OK","",Z9-AA9) | AC9: =IF((IF(G9="",0,IF(IFERROR(IF(VLOOKUP(G9,Materialen!$A$2:$I$39,9,0)="",0,VLOOKUP(G9,Materialen!$A$2:$I$39,9,0)),0)=0,1,0))+IF(I9="",0,IF(IFERROR(IF(VLOOKUP(I9,Materialen!$A$2:$I$39,9,0)="",0,VLOOKUP(I9,Materialen!$A$2:$I$39,9,0)),0)=0,1,0))+IF(K9="",0,IF(IFERROR(IF(VLOOKUP(K9,Materialen!$A$2:$I$39,9,0)="",0,VLOOKUP(K9,Materialen!$A$2:$I$39,9,0)),0)=0,1,0))+IF(M9="",0,IF(IFERROR(IF(VLOOKUP(M9,Materialen!$A$2:$I$39,9,0)="",0,VLOOKUP(M9,Materialen!$A$2:$I$39,9,0)),0)=0,1,0)))>0,"aankoopprijs ontbreekt",IF(AND(G9="",K9="",N(T9)=0,N(R9)=0),"kost invullen (arbeid/overig)","OK")) | AD9: Grammage niet in bestek: frontlit 450 aangenomen
A10: 9 | B10: BÂCHE | C10: Bâche façade Warocqué: L380 x H230 cm, quadri recto UV - Support Frontlit 450 gr - Façonnage ourlets et œillets tous les 30 cm sur les 4 côtés | D10: pièce | E10: 10 | F10: 120 | G10: M02 | H10: 8.74 | K10: M25 | L10: 41 | O10: =IF(G10="","",IF(IFERROR(VLOOKUP(G10,Materialen!$A$2:$I$39,4,0),"")="plaat",Instellingen!$B$4,Instellingen!$B$3)) | P10: =ROUND(N(H10)*IFERROR(IF(VLOOKUP(G10,Materialen!$A$2:$I$39,9,0)="",0,VLOOKUP(G10,Materialen!$A$2:$I$39,9,0)),0)*(1+N(O10))+N(J10)*IFERROR(IF(VLOOKUP(I10,Materialen!$A$2:$I$39,9,0)="",0,VLOOKUP(I10,Materialen!$A$2:$I$39,9,0)),0)*(1+N(O10))+N(L10)*IFERROR(IF(VLOOKUP(K10,Materialen!$A$2:$I$39,9,0)="",0,VLOOKUP(K10,Materialen!$A$2:$I$39,9,0)),0)+N(N10)*IFERROR(IF(VLOOKUP(M10,Materialen!$A$2:$I$39,9,0)="",0,VLOOKUP(M10,Materialen!$A$2:$I$39,9,0)),0),2) | Q10: =IF(G10="",0,IF(IFERROR(VLOOKUP(G10,Materialen!$A$2:$I$39,5,0),"N")="J",ROUND(N(H10)*(1+N(O10))*Instellingen!$B$8,2),0)) | S10: =ROUND(N(R10)/60*Instellingen!$B$9,2) | U10: =P10+Q10+S10+N(T10) | V10: =IF(AC10<>"OK","",F10-U10) | W10: =IF(OR(F10=0,AC10<>"OK"),"",V10/F10) | X10: =IF(N(H10)>0,F10/H10,"") | Y10: =IF(N(H10)>0,IFERROR(IF(VLOOKUP(G10,Materialen!$A$2:$I$39,9,0)="",0,VLOOKUP(G10,Materialen!$A$2:$I$39,9,0)),0),"") | Z10: =ROUND(E10*F10,2) | AA10: =IF(AC10<>"OK","",ROUND(E10*U10,2)) | AB10: =IF(AC10<>"OK","",Z10-AA10) | AC10: =IF((IF(G10="",0,IF(IFERROR(IF(VLOOKUP(G10,Materialen!$A$2:$I$39,9,0)="",0,VLOOKUP(G10,Materialen!$A$2:$I$39,9,0)),0)=0,1,0))+IF(I10="",0,IF(IFERROR(IF(VLOOKUP(I10,Materialen!$A$2:$I$39,9,0)="",0,VLOOKUP(I10,Materialen!$A$2:$I$39,9,0)),0)=0,1,0))+IF(K10="",0,IF(IFERROR(IF(VLOOKUP(K10,Materialen!$A$2:$I$39,9,0)="",0,VLOOKUP(K10,Materialen!$A$2:$I$39,9,0)),0)=0,1,0))+IF(M10="",0,IF(IFERROR(IF(VLOOKUP(M10,Materialen!$A$2:$I$39,9,0)="",0,VLOOKUP(M10,Materialen!$A$2:$I$39,9,0)),0)=0,1,0)))>0,"aankoopprijs ontbreekt",IF(AND(G10="",K10="",N(T10)=0,N(R10)=0),"kost invullen (arbeid/overig)","OK")) | AD10: Oogjes om de 30 cm
A11: 10 | B11: BÂCHE | C11: Bâche pour CUBES: 180 x 180 cm - œillets tous les 30 cm - bâche 330 gr - 10 cm de marge sur chaque côté - 5 mm de bords perdus | D11: pièce | E11: 70 | F11: 42 | G11: M07 | H11: 3.24 | K11: M25 | L11: 24 | O11: =IF(G11="","",IF(IFERROR(VLOOKUP(G11,Materialen!$A$2:$I$39,4,0),"")="plaat",Instellingen!$B$4,Instellingen!$B$3)) | P11: =ROUND(N(H11)*IFERROR(IF(VLOOKUP(G11,Materialen!$A$2:$I$39,9,0)="",0,VLOOKUP(G11,Materialen!$A$2:$I$39,9,0)),0)*(1+N(O11))+N(J11)*IFERROR(IF(VLOOKUP(I11,Materialen!$A$2:$I$39,9,0)="",0,VLOOKUP(I11,Materialen!$A$2:$I$39,9,0)),0)*(1+N(O11))+N(L11)*IFERROR(IF(VLOOKUP(K11,Materialen!$A$2:$I$39,9,0)="",0,VLOOKUP(K11,Materialen!$A$2:$I$39,9,0)),0)+N(N11)*IFERROR(IF(VLOOKUP(M11,Materialen!$A$2:$I$39,9,0)="",0,VLOOKUP(M11,Materialen!$A$2:$I$39,9,0)),0),2) | Q11: =IF(G11="",0,IF(IFERROR(VLOOKUP(G11,Materialen!$A$2:$I$39,5,0),"N")="J",ROUND(N(H11)*(1+N(O11))*Instellingen!$B$8,2),0)) | S11: =ROUND(N(R11)/60*Instellingen!$B$9,2) | U11: =P11+Q11+S11+N(T11) | V11: =IF(AC11<>"OK","",F11-U11) | W11: =IF(OR(F11=0,AC11<>"OK"),"",V11/F11) | X11: =IF(N(H11)>0,F11/H11,"") | Y11: =IF(N(H11)>0,IFERROR(IF(VLOOKUP(G11,Materialen!$A$2:$I$39,9,0)="",0,VLOOKUP(G11,Materialen!$A$2:$I$39,9,0)),0),"") | Z11: =ROUND(E11*F11,2) | AA11: =IF(AC11<>"OK","",ROUND(E11*U11,2)) | AB11: =IF(AC11<>"OK","",Z11-AA11) | AC11: =IF((IF(G11="",0,IF(IFERROR(IF(VLOOKUP(G11,Materialen!$A$2:$I$39,9,0)="",0,VLOOKUP(G11,Materialen!$A$2:$I$39,9,0)),0)=0,1,0))+IF(I11="",0,IF(IFERROR(IF(VLOOKUP(I11,Materialen!$A$2:$I$39,9,0)="",0,VLOOKUP(I11,Materialen!$A$2:$I$39,9,0)),0)=0,1,0))+IF(K11="",0,IF(IFERROR(IF(VLOOKUP(K11,Materialen!$A$2:$I$39,9,0)="",0,VLOOKUP(K11,Materialen!$A$2:$I$39,9,0)),0)=0,1,0))+IF(M11="",0,IF(IFERROR(IF(VLOOKUP(M11,Materialen!$A$2:$I$39,9,0)="",0,VLOOKUP(M11,Materialen!$A$2:$I$39,9,0)),0)=0,1,0)))>0,"aankoopprijs ontbreekt",IF(AND(G11="",K11="",N(T11)=0,N(R11)=0),"kost invullen (arbeid/overig)","OK"))
A12: 11 | B12: BÂCHE | C12: Bâche « cube visitmons » o Format : L105 x H215 cm o Caractéristiques : Bâche Pro 550g, soudure du bord périmètre, œillets tous les 50cm périmètre o Couleurs : impression en quadrichromie | D12: pièce | E12: 90 | F12: 52 | G12: M03 | H12: 2.26 | K12: M25 | L12: 13 | O12: =IF(G12="","",IF(IFERROR(VLOOKUP(G12,Materialen!$A$2:$I$39,4,0),"")="plaat",Instellingen!$B$4,Instellingen!$B$3)) | P12: =ROUND(N(H12)*IFERROR(IF(VLOOKUP(G12,Materialen!$A$2:$I$39,9,0)="",0,VLOOKUP(G12,Materialen!$A$2:$I$39,9,0)),0)*(1+N(O12))+N(J12)*IFERROR(IF(VLOOKUP(I12,Materialen!$A$2:$I$39,9,0)="",0,VLOOKUP(I12,Materialen!$A$2:$I$39,9,0)),0)*(1+N(O12))+N(L12)*IFERROR(IF(VLOOKUP(K12,Materialen!$A$2:$I$39,9,0)="",0,VLOOKUP(K12,Materialen!$A$2:$I$39,9,0)),0)+N(N12)*IFERROR(IF(VLOOKUP(M12,Materialen!$A$2:$I$39,9,0)="",0,VLOOKUP(M12,Materialen!$A$2:$I$39,9,0)),0),2) | Q12: =IF(G12="",0,IF(IFERROR(VLOOKUP(G12,Materialen!$A$2:$I$39,5,0),"N")="J",ROUND(N(H12)*(1+N(O12))*Instellingen!$B$8,2),0)) | S12: =ROUND(N(R12)/60*Instellingen!$B$9,2) | U12: =P12+Q12+S12+N(T12) | V12: =IF(AC12<>"OK","",F12-U12) | W12: =IF(OR(F12=0,AC12<>"OK"),"",V12/F12) | X12: =IF(N(H12)>0,F12/H12,"") | Y12: =IF(N(H12)>0,IFERROR(IF(VLOOKUP(G12,Materialen!$A$2:$I$39,9,0)="",0,VLOOKUP(G12,Materialen!$A$2:$I$39,9,0)),0),"") | Z12: =ROUND(E12*F12,2) | AA12: =IF(AC12<>"OK","",ROUND(E12*U12,2)) | AB12: =IF(AC12<>"OK","",Z12-AA12) | AC12: =IF((IF(G12="",0,IF(IFERROR(IF(VLOOKUP(G12,Materialen!$A$2:$I$39,9,0)="",0,VLOOKUP(G12,Materialen!$A$2:$I$39,9,0)),0)=0,1,0))+IF(I12="",0,IF(IFERROR(IF(VLOOKUP(I12,Materialen!$A$2:$I$39,9,0)="",0,VLOOKUP(I12,Materialen!$A$2:$I$39,9,0)),0)=0,1,0))+IF(K12="",0,IF(IFERROR(IF(VLOOKUP(K12,Materialen!$A$2:$I$39,9,0)="",0,VLOOKUP(K12,Materialen!$A$2:$I$39,9,0)),0)=0,1,0))+IF(M12="",0,IF(IFERROR(IF(VLOOKUP(M12,Materialen!$A$2:$I$39,9,0)="",0,VLOOKUP(M12,Materialen!$A$2:$I$39,9,0)),0)=0,1,0)))>0,"aankoopprijs ontbreekt",IF(AND(G12="",K12="",N(T12)=0,N(R12)=0),"kost invullen (arbeid/overig)","OK"))
A13: 12 | B13: BÂCHE | C13: Bâche barrière « Nadar » o Format : L200xH110cm o Caractéristiques : bâche micro-perforée 290gr avec des œillets tous les 50cm, avec soudure du bord o Couleurs : impression en quadrichromie | D13: pièce | E13: 70 | F13: 38 | G13: M06 | H13: 2.2 | K13: M25 | L13: 13 | O13: =IF(G13="","",IF(IFERROR(VLOOKUP(G13,Materialen!$A$2:$I$39,4,0),"")="plaat",Instellingen!$B$4,Instellingen!$B$3)) | P13: =ROUND(N(H13)*IFERROR(IF(VLOOKUP(G13,Materialen!$A$2:$I$39,9,0)="",0,VLOOKUP(G13,Materialen!$A$2:$I$39,9,0)),0)*(1+N(O13))+N(J13)*IFERROR(IF(VLOOKUP(I13,Materialen!$A$2:$I$39,9,0)="",0,VLOOKUP(I13,Materialen!$A$2:$I$39,9,0)),0)*(1+N(O13))+N(L13)*IFERROR(IF(VLOOKUP(K13,Materialen!$A$2:$I$39,9,0)="",0,VLOOKUP(K13,Materialen!$A$2:$I$39,9,0)),0)+N(N13)*IFERROR(IF(VLOOKUP(M13,Materialen!$A$2:$I$39,9,0)="",0,VLOOKUP(M13,Materialen!$A$2:$I$39,9,0)),0),2) | Q13: =IF(G13="",0,IF(IFERROR(VLOOKUP(G13,Materialen!$A$2:$I$39,5,0),"N")="J",ROUND(N(H13)*(1+N(O13))*Instellingen!$B$8,2),0)) | S13: =ROUND(N(R13)/60*Instellingen!$B$9,2) | U13: =P13+Q13+S13+N(T13) | V13: =IF(AC13<>"OK","",F13-U13) | W13: =IF(OR(F13=0,AC13<>"OK"),"",V13/F13) | X13: =IF(N(H13)>0,F13/H13,"") | Y13: =IF(N(H13)>0,IFERROR(IF(VLOOKUP(G13,Materialen!$A$2:$I$39,9,0)="",0,VLOOKUP(G13,Materialen!$A$2:$I$39,9,0)),0),"") | Z13: =ROUND(E13*F13,2) | AA13: =IF(AC13<>"OK","",ROUND(E13*U13,2)) | AB13: =IF(AC13<>"OK","",Z13-AA13) | AC13: =IF((IF(G13="",0,IF(IFERROR(IF(VLOOKUP(G13,Materialen!$A$2:$I$39,9,0)="",0,VLOOKUP(G13,Materialen!$A$2:$I$39,9,0)),0)=0,1,0))+IF(I13="",0,IF(IFERROR(IF(VLOOKUP(I13,Materialen!$A$2:$I$39,9,0)="",0,VLOOKUP(I13,Materialen!$A$2:$I$39,9,0)),0)=0,1,0))+IF(K13="",0,IF(IFERROR(IF(VLOOKUP(K13,Materialen!$A$2:$I$39,9,0)="",0,VLOOKUP(K13,Materialen!$A$2:$I$39,9,0)),0)=0,1,0))+IF(M13="",0,IF(IFERROR(IF(VLOOKUP(M13,Materialen!$A$2:$I$39,9,0)="",0,VLOOKUP(M13,Materialen!$A$2:$I$39,9,0)),0)=0,1,0)))>0,"aankoopprijs ontbreekt",IF(AND(G13="",K13="",N(T13)=0,N(R13)=0),"kost invullen (arbeid/overig)","OK"))
A14: 13 | B14: ROLLS UP | C14: Rolls up : Format L 85x H 200 cm - Impression quadri recto - sac de transport inclus | D14: pièce | E14: 10 | F14: 78 | G14: M10 | H14: 1.7 | K14: M11 | L14: 1 | O14: =IF(G14="","",IF(IFERROR(VLOOKUP(G14,Materialen!$A$2:$I$39,4,0),"")="plaat",Instellingen!$B$4,Instellingen!$B$3)) | P14: =ROUND(N(H14)*IFERROR(IF(VLOOKUP(G14,Materialen!$A$2:$I$39,9,0)="",0,VLOOKUP(G14,Materialen!$A$2:$I$39,9,0)),0)*(1+N(O14))+N(J14)*IFERROR(IF(VLOOKUP(I14,Materialen!$A$2:$I$39,9,0)="",0,VLOOKUP(I14,Materialen!$A$2:$I$39,9,0)),0)*(1+N(O14))+N(L14)*IFERROR(IF(VLOOKUP(K14,Materialen!$A$2:$I$39,9,0)="",0,VLOOKUP(K14,Materialen!$A$2:$I$39,9,0)),0)+N(N14)*IFERROR(IF(VLOOKUP(M14,Materialen!$A$2:$I$39,9,0)="",0,VLOOKUP(M14,Materialen!$A$2:$I$39,9,0)),0),2) | Q14: =IF(G14="",0,IF(IFERROR(VLOOKUP(G14,Materialen!$A$2:$I$39,5,0),"N")="J",ROUND(N(H14)*(1+N(O14))*Instellingen!$B$8,2),0)) | S14: =ROUND(N(R14)/60*Instellingen!$B$9,2) | U14: =P14+Q14+S14+N(T14) | V14: =IF(AC14<>"OK","",F14-U14) | W14: =IF(OR(F14=0,AC14<>"OK"),"",V14/F14) | X14: =IF(N(H14)>0,F14/H14,"") | Y14: =IF(N(H14)>0,IFERROR(IF(VLOOKUP(G14,Materialen!$A$2:$I$39,9,0)="",0,VLOOKUP(G14,Materialen!$A$2:$I$39,9,0)),0),"") | Z14: =ROUND(E14*F14,2) | AA14: =IF(AC14<>"OK","",ROUND(E14*U14,2)) | AB14: =IF(AC14<>"OK","",Z14-AA14) | AC14: =IF((IF(G14="",0,IF(IFERROR(IF(VLOOKUP(G14,Materialen!$A$2:$I$39,9,0)="",0,VLOOKUP(G14,Materialen!$A$2:$I$39,9,0)),0)=0,1,0))+IF(I14="",0,IF(IFERROR(IF(VLOOKUP(I14,Materialen!$A$2:$I$39,9,0)="",0,VLOOKUP(I14,Materialen!$A$2:$I$39,9,0)),0)=0,1,0))+IF(K14="",0,IF(IFERROR(IF(VLOOKUP(K14,Materialen!$A$2:$I$39,9,0)="",0,VLOOKUP(K14,Materialen!$A$2:$I$39,9,0)),0)=0,1,0))+IF(M14="",0,IF(IFERROR(IF(VLOOKUP(M14,Materialen!$A$2:$I$39,9,0)="",0,VLOOKUP(M14,Materialen!$A$2:$I$39,9,0)),0)=0,1,0)))>0,"aankoopprijs ontbreekt",IF(AND(G14="",K14="",N(T14)=0,N(R14)=0),"kost invullen (arbeid/overig)","OK"))
A15: 14 | B15: ROLLS UP | C15: Rolls up: L60 x H160 cm - Impression quadri recto - Sac de transport inclus | D15: pièce | E15: 10 | F15: 65 | G15: M10 | H15: 0.96 | K15: M12 | L15: 1 | O15: =IF(G15="","",IF(IFERROR(VLOOKUP(G15,Materialen!$A$2:$I$39,4,0),"")="plaat",Instellingen!$B$4,Instellingen!$B$3)) | P15: =ROUND(N(H15)*IFERROR(IF(VLOOKUP(G15,Materialen!$A$2:$I$39,9,0)="",0,VLOOKUP(G15,Materialen!$A$2:$I$39,9,0)),0)*(1+N(O15))+N(J15)*IFERROR(IF(VLOOKUP(I15,Materialen!$A$2:$I$39,9,0)="",0,VLOOKUP(I15,Materialen!$A$2:$I$39,9,0)),0)*(1+N(O15))+N(L15)*IFERROR(IF(VLOOKUP(K15,Materialen!$A$2:$I$39,9,0)="",0,VLOOKUP(K15,Materialen!$A$2:$I$39,9,0)),0)+N(N15)*IFERROR(IF(VLOOKUP(M15,Materialen!$A$2:$I$39,9,0)="",0,VLOOKUP(M15,Materialen!$A$2:$I$39,9,0)),0),2) | Q15: =IF(G15="",0,IF(IFERROR(VLOOKUP(G15,Materialen!$A$2:$I$39,5,0),"N")="J",ROUND(N(H15)*(1+N(O15))*Instellingen!$B$8,2),0)) | S15: =ROUND(N(R15)/60*Instellingen!$B$9,2) | U15: =P15+Q15+S15+N(T15) | V15: =IF(AC15<>"OK","",F15-U15) | W15: =IF(OR(F15=0,AC15<>"OK"),"",V15/F15) | X15: =IF(N(H15)>0,F15/H15,"") | Y15: =IF(N(H15)>0,IFERROR(IF(VLOOKUP(G15,Materialen!$A$2:$I$39,9,0)="",0,VLOOKUP(G15,Materialen!$A$2:$I$39,9,0)),0),"") | Z15: =ROUND(E15*F15,2) | AA15: =IF(AC15<>"OK","",ROUND(E15*U15,2)) | AB15: =IF(AC15<>"OK","",Z15-AA15) | AC15: =IF((IF(G15="",0,IF(IFERROR(IF(VLOOKUP(G15,Materialen!$A$2:$I$39,9,0)="",0,VLOOKUP(G15,Materialen!$A$2:$I$39,9,0)),0)=0,1,0))+IF(I15="",0,IF(IFERROR(IF(VLOOKUP(I15,Materialen!$A$2:$I$39,9,0)="",0,VLOOKUP(I15,Materialen!$A$2:$I$39,9,0)),0)=0,1,0))+IF(K15="",0,IF(IFERROR(IF(VLOOKUP(K15,Materialen!$A$2:$I$39,9,0)="",0,VLOOKUP(K15,Materialen!$A$2:$I$39,9,0)),0)=0,1,0))+IF(M15="",0,IF(IFERROR(IF(VLOOKUP(M15,Materialen!$A$2:$I$39,9,0)="",0,VLOOKUP(M15,Materialen!$A$2:$I$39,9,0)),0)=0,1,0)))>0,"aankoopprijs ontbreekt",IF(AND(G15="",K15="",N(T15)=0,N(R15)=0),"kost invullen (arbeid/overig)","OK"))
A16: 15 | B16: BANNIERE ENTREE ABATTOIRS | C16: Largeur : 75cm (pas de fausse coupe) X Hauteur : 160cm (= format avec ourlet à plat) auxquels on rajoute 10 cm de fausse coupe en haut et en bas et 1,5cm de couture en haut et en bas. Hauteur totale : 183 cm. Impression en quadrichromie | D16: pièce | E16: 10 | F16: 38 | G16: M02 | H16: 1.3725 | O16: =IF(G16="","",IF(IFERROR(VLOOKUP(G16,Materialen!$A$2:$I$39,4,0),"")="plaat",Instellingen!$B$4,Instellingen!$B$3)) | P16: =ROUND(N(H16)*IFERROR(IF(VLOOKUP(G16,Materialen!$A$2:$I$39,9,0)="",0,VLOOKUP(G16,Materialen!$A$2:$I$39,9,0)),0)*(1+N(O16))+N(J16)*IFERROR(IF(VLOOKUP(I16,Materialen!$A$2:$I$39,9,0)="",0,VLOOKUP(I16,Materialen!$A$2:$I$39,9,0)),0)*(1+N(O16))+N(L16)*IFERROR(IF(VLOOKUP(K16,Materialen!$A$2:$I$39,9,0)="",0,VLOOKUP(K16,Materialen!$A$2:$I$39,9,0)),0)+N(N16)*IFERROR(IF(VLOOKUP(M16,Materialen!$A$2:$I$39,9,0)="",0,VLOOKUP(M16,Materialen!$A$2:$I$39,9,0)),0),2) | Q16: =IF(G16="",0,IF(IFERROR(VLOOKUP(G16,Materialen!$A$2:$I$39,5,0),"N")="J",ROUND(N(H16)*(1+N(O16))*Instellingen!$B$8,2),0)) | S16: =ROUND(N(R16)/60*Instellingen!$B$9,2) | U16: =P16+Q16+S16+N(T16) | V16: =IF(AC16<>"OK","",F16-U16) | W16: =IF(OR(F16=0,AC16<>"OK"),"",V16/F16) | X16: =IF(N(H16)>0,F16/H16,"") | Y16: =IF(N(H16)>0,IFERROR(IF(VLOOKUP(G16,Materialen!$A$2:$I$39,9,0)="",0,VLOOKUP(G16,Materialen!$A$2:$I$39,9,0)),0),"") | Z16: =ROUND(E16*F16,2) | AA16: =IF(AC16<>"OK","",ROUND(E16*U16,2)) | AB16: =IF(AC16<>"OK","",Z16-AA16) | AC16: =IF((IF(G16="",0,IF(IFERROR(IF(VLOOKUP(G16,Materialen!$A$2:$I$39,9,0)="",0,VLOOKUP(G16,Materialen!$A$2:$I$39,9,0)),0)=0,1,0))+IF(I16="",0,IF(IFERROR(IF(VLOOKUP(I16,Materialen!$A$2:$I$39,9,0)="",0,VLOOKUP(I16,Materialen!$A$2:$I$39,9,0)),0)=0,1,0))+IF(K16="",0,IF(IFERROR(IF(VLOOKUP(K16,Materialen!$A$2:$I$39,9,0)="",0,VLOOKUP(K16,Materialen!$A$2:$I$39,9,0)),0)=0,1,0))+IF(M16="",0,IF(IFERROR(IF(VLOOKUP(M16,Materialen!$A$2:$I$39,9,0)="",0,VLOOKUP(M16,Materialen!$A$2:$I$39,9,0)),0)=0,1,0)))>0,"aankoopprijs ontbreekt",IF(AND(G16="",K16="",N(T16)=0,N(R16)=0),"kost invullen (arbeid/overig)","OK")) | AD16: Grammage niet in bestek: frontlit 450 aangenomen
A17: 16 | B17: STICKERS | C17: Carré 30x30cm - découpe rectangle carré. Impression en quadrichromie | D17: pièce | E17: 20 | F17: 4.8 | G17: M15 | H17: 0.09 | O17: =IF(G17="","",IF(IFERROR(VLOOKUP(G17,Materialen!$A$2:$I$39,4,0),"")="plaat",Instellingen!$B$4,Instellingen!$B$3)) | P17: =ROUND(N(H17)*IFERROR(IF(VLOOKUP(G17,Materialen!$A$2:$I$39,9,0)="",0,VLOOKUP(G17,Materialen!$A$2:$I$39,9,0)),0)*(1+N(O17))+N(J17)*IFERROR(IF(VLOOKUP(I17,Materialen!$A$2:$I$39,9,0)="",0,VLOOKUP(I17,Materialen!$A$2:$I$39,9,0)),0)*(1+N(O17))+N(L17)*IFERROR(IF(VLOOKUP(K17,Materialen!$A$2:$I$39,9,0)="",0,VLOOKUP(K17,Materialen!$A$2:$I$39,9,0)),0)+N(N17)*IFERROR(IF(VLOOKUP(M17,Materialen!$A$2:$I$39,9,0)="",0,VLOOKUP(M17,Materialen!$A$2:$I$39,9,0)),0),2) | Q17: =IF(G17="",0,IF(IFERROR(VLOOKUP(G17,Materialen!$A$2:$I$39,5,0),"N")="J",ROUND(N(H17)*(1+N(O17))*Instellingen!$B$8,2),0)) | S17: =ROUND(N(R17)/60*Instellingen!$B$9,2) | U17: =P17+Q17+S17+N(T17) | V17: =IF(AC17<>"OK","",F17-U17) | W17: =IF(OR(F17=0,AC17<>"OK"),"",V17/F17) | X17: =IF(N(H17)>0,F17/H17,"") | Y17: =IF(N(H17)>0,IFERROR(IF(VLOOKUP(G17,Materialen!$A$2:$I$39,9,0)="",0,VLOOKUP(G17,Materialen!$A$2:$I$39,9,0)),0),"") | Z17: =ROUND(E17*F17,2) | AA17: =IF(AC17<>"OK","",ROUND(E17*U17,2)) | AB17: =IF(AC17<>"OK","",Z17-AA17) | AC17: =IF((IF(G17="",0,IF(IFERROR(IF(VLOOKUP(G17,Materialen!$A$2:$I$39,9,0)="",0,VLOOKUP(G17,Materialen!$A$2:$I$39,9,0)),0)=0,1,0))+IF(I17="",0,IF(IFERROR(IF(VLOOKUP(I17,Materialen!$A$2:$I$39,9,0)="",0,VLOOKUP(I17,Materialen!$A$2:$I$39,9,0)),0)=0,1,0))+IF(K17="",0,IF(IFERROR(IF(VLOOKUP(K17,Materialen!$A$2:$I$39,9,0)="",0,VLOOKUP(K17,Materialen!$A$2:$I$39,9,0)),0)=0,1,0))+IF(M17="",0,IF(IFERROR(IF(VLOOKUP(M17,Materialen!$A$2:$I$39,9,0)="",0,VLOOKUP(M17,Materialen!$A$2:$I$39,9,0)),0)=0,1,0)))>0,"aankoopprijs ontbreekt",IF(AND(G17="",K17="",N(T17)=0,N(R17)=0),"kost invullen (arbeid/overig)","OK"))
A18: 17 | B18: STICKERS | C18: eletrostatique 15x20cm - quadrichromie miroir et blanc - support sur Vinyle Yupo Taco Jelly | D18: quantité : par 10 | E18: 20 | F18: 18 | G18: M13 | H18: 0.3 | O18: =IF(G18="","",IF(IFERROR(VLOOKUP(G18,Materialen!$A$2:$I$39,4,0),"")="plaat",Instellingen!$B$4,Instellingen!$B$3)) | P18: =ROUND(N(H18)*IFERROR(IF(VLOOKUP(G18,Materialen!$A$2:$I$39,9,0)="",0,VLOOKUP(G18,Materialen!$A$2:$I$39,9,0)),0)*(1+N(O18))+N(J18)*IFERROR(IF(VLOOKUP(I18,Materialen!$A$2:$I$39,9,0)="",0,VLOOKUP(I18,Materialen!$A$2:$I$39,9,0)),0)*(1+N(O18))+N(L18)*IFERROR(IF(VLOOKUP(K18,Materialen!$A$2:$I$39,9,0)="",0,VLOOKUP(K18,Materialen!$A$2:$I$39,9,0)),0)+N(N18)*IFERROR(IF(VLOOKUP(M18,Materialen!$A$2:$I$39,9,0)="",0,VLOOKUP(M18,Materialen!$A$2:$I$39,9,0)),0),2) | Q18: =IF(G18="",0,IF(IFERROR(VLOOKUP(G18,Materialen!$A$2:$I$39,5,0),"N")="J",ROUND(N(H18)*(1+N(O18))*Instellingen!$B$8,2),0)) | S18: =ROUND(N(R18)/60*Instellingen!$B$9,2) | U18: =P18+Q18+S18+N(T18) | V18: =IF(AC18<>"OK","",F18-U18) | W18: =IF(OR(F18=0,AC18<>"OK"),"",V18/F18) | X18: =IF(N(H18)>0,F18/H18,"") | Y18: =IF(N(H18)>0,IFERROR(IF(VLOOKUP(G18,Materialen!$A$2:$I$39,9,0)="",0,VLOOKUP(G18,Materialen!$A$2:$I$39,9,0)),0),"") | Z18: =ROUND(E18*F18,2) | AA18: =IF(AC18<>"OK","",ROUND(E18*U18,2)) | AB18: =IF(AC18<>"OK","",Z18-AA18) | AC18: =IF((IF(G18="",0,IF(IFERROR(IF(VLOOKUP(G18,Materialen!$A$2:$I$39,9,0)="",0,VLOOKUP(G18,Materialen!$A$2:$I$39,9,0)),0)=0,1,0))+IF(I18="",0,IF(IFERROR(IF(VLOOKUP(I18,Materialen!$A$2:$I$39,9,0)="",0,VLOOKUP(I18,Materialen!$A$2:$I$39,9,0)),0)=0,1,0))+IF(K18="",0,IF(IFERROR(IF(VLOOKUP(K18,Materialen!$A$2:$I$39,9,0)="",0,VLOOKUP(K18,Materialen!$A$2:$I$39,9,0)),0)=0,1,0))+IF(M18="",0,IF(IFERROR(IF(VLOOKUP(M18,Materialen!$A$2:$I$39,9,0)="",0,VLOOKUP(M18,Materialen!$A$2:$I$39,9,0)),0)=0,1,0)))>0,"aankoopprijs ontbreekt",IF(AND(G18="",K18="",N(T18)=0,N(R18)=0),"kost invullen (arbeid/overig)","OK")) | AD18: Eenheid = 10 stuks
A19: 18 | B19: STICKERS | C19: 15cm diamètre - quadrichromie miroir + blanc - polymère transparent brillant | D19: quantité : par 10 | E19: 20 | F19: 16 | G19: M14 | H19: 0.177 | O19: =IF(G19="","",IF(IFERROR(VLOOKUP(G19,Materialen!$A$2:$I$39,4,0),"")="plaat",Instellingen!$B$4,Instellingen!$B$3)) | P19: =ROUND(N(H19)*IFERROR(IF(VLOOKUP(G19,Materialen!$A$2:$I$39,9,0)="",0,VLOOKUP(G19,Materialen!$A$2:$I$39,9,0)),0)*(1+N(O19))+N(J19)*IFERROR(IF(VLOOKUP(I19,Materialen!$A$2:$I$39,9,0)="",0,VLOOKUP(I19,Materialen!$A$2:$I$39,9,0)),0)*(1+N(O19))+N(L19)*IFERROR(IF(VLOOKUP(K19,Materialen!$A$2:$I$39,9,0)="",0,VLOOKUP(K19,Materialen!$A$2:$I$39,9,0)),0)+N(N19)*IFERROR(IF(VLOOKUP(M19,Materialen!$A$2:$I$39,9,0)="",0,VLOOKUP(M19,Materialen!$A$2:$I$39,9,0)),0),2) | Q19: =IF(G19="",0,IF(IFERROR(VLOOKUP(G19,Materialen!$A$2:$I$39,5,0),"N")="J",ROUND(N(H19)*(1+N(O19))*Instellingen!$B$8,2),0)) | S19: =ROUND(N(R19)/60*Instellingen!$B$9,2) | U19: =P19+Q19+S19+N(T19) | V19: =IF(AC19<>"OK","",F19-U19) | W19: =IF(OR(F19=0,AC19<>"OK"),"",V19/F19) | X19: =IF(N(H19)>0,F19/H19,"") | Y19: =IF(N(H19)>0,IFERROR(IF(VLOOKUP(G19,Materialen!$A$2:$I$39,9,0)="",0,VLOOKUP(G19,Materialen!$A$2:$I$39,9,0)),0),"") | Z19: =ROUND(E19*F19,2) | AA19: =IF(AC19<>"OK","",ROUND(E19*U19,2)) | AB19: =IF(AC19<>"OK","",Z19-AA19) | AC19: =IF((IF(G19="",0,IF(IFERROR(IF(VLOOKUP(G19,Materialen!$A$2:$I$39,9,0)="",0,VLOOKUP(G19,Materialen!$A$2:$I$39,9,0)),0)=0,1,0))+IF(I19="",0,IF(IFERROR(IF(VLOOKUP(I19,Materialen!$A$2:$I$39,9,0)="",0,VLOOKUP(I19,Materialen!$A$2:$I$39,9,0)),0)=0,1,0))+IF(K19="",0,IF(IFERROR(IF(VLOOKUP(K19,Materialen!$A$2:$I$39,9,0)="",0,VLOOKUP(K19,Materialen!$A$2:$I$39,9,0)),0)=0,1,0))+IF(M19="",0,IF(IFERROR(IF(VLOOKUP(M19,Materialen!$A$2:$I$39,9,0)="",0,VLOOKUP(M19,Materialen!$A$2:$I$39,9,0)),0)=0,1,0)))>0,"aankoopprijs ontbreekt",IF(AND(G19="",K19="",N(T19)=0,N(R19)=0),"kost invullen (arbeid/overig)","OK")) | AD19: Eenheid = 10 stuks; wit onderdruk = extra inkt
A20: 19 | B20: STICKERS | C20: Impression digitale quadri sur autocollant véhicule micro perforé pour vitre | D20: m² | E20: 20 | F20: 38 | G20: M16 | H20: 1 | O20: =IF(G20="","",IF(IFERROR(VLOOKUP(G20,Materialen!$A$2:$I$39,4,0),"")="plaat",Instellingen!$B$4,Instellingen!$B$3)) | P20: =ROUND(N(H20)*IFERROR(IF(VLOOKUP(G20,Materialen!$A$2:$I$39,9,0)="",0,VLOOKUP(G20,Materialen!$A$2:$I$39,9,0)),0)*(1+N(O20))+N(J20)*IFERROR(IF(VLOOKUP(I20,Materialen!$A$2:$I$39,9,0)="",0,VLOOKUP(I20,Materialen!$A$2:$I$39,9,0)),0)*(1+N(O20))+N(L20)*IFERROR(IF(VLOOKUP(K20,Materialen!$A$2:$I$39,9,0)="",0,VLOOKUP(K20,Materialen!$A$2:$I$39,9,0)),0)+N(N20)*IFERROR(IF(VLOOKUP(M20,Materialen!$A$2:$I$39,9,0)="",0,VLOOKUP(M20,Materialen!$A$2:$I$39,9,0)),0),2) | Q20: =IF(G20="",0,IF(IFERROR(VLOOKUP(G20,Materialen!$A$2:$I$39,5,0),"N")="J",ROUND(N(H20)*(1+N(O20))*Instellingen!$B$8,2),0)) | S20: =ROUND(N(R20)/60*Instellingen!$B$9,2) | U20: =P20+Q20+S20+N(T20) | V20: =IF(AC20<>"OK","",F20-U20) | W20: =IF(OR(F20=0,AC20<>"OK"),"",V20/F20) | X20: =IF(N(H20)>0,F20/H20,"") | Y20: =IF(N(H20)>0,IFERROR(IF(VLOOKUP(G20,Materialen!$A$2:$I$39,9,0)="",0,VLOOKUP(G20,Materialen!$A$2:$I$39,9,0)),0),"") | Z20: =ROUND(E20*F20,2) | AA20: =IF(AC20<>"OK","",ROUND(E20*U20,2)) | AB20: =IF(AC20<>"OK","",Z20-AA20) | AC20: =IF((IF(G20="",0,IF(IFERROR(IF(VLOOKUP(G20,Materialen!$A$2:$I$39,9,0)="",0,VLOOKUP(G20,Materialen!$A$2:$I$39,9,0)),0)=0,1,0))+IF(I20="",0,IF(IFERROR(IF(VLOOKUP(I20,Materialen!$A$2:$I$39,9,0)="",0,VLOOKUP(I20,Materialen!$A$2:$I$39,9,0)),0)=0,1,0))+IF(K20="",0,IF(IFERROR(IF(VLOOKUP(K20,Materialen!$A$2:$I$39,9,0)="",0,VLOOKUP(K20,Materialen!$A$2:$I$39,9,0)),0)=0,1,0))+IF(M20="",0,IF(IFERROR(IF(VLOOKUP(M20,Materialen!$A$2:$I$39,9,0)="",0,VLOOKUP(M20,Materialen!$A$2:$I$39,9,0)),0)=0,1,0)))>0,"aankoopprijs ontbreekt",IF(AND(G20="",K20="",N(T20)=0,N(R20)=0),"kost invullen (arbeid/overig)","OK"))
A21: 20 | B21: STICKERS | C21: Impression digitale quadri sur autocollant véhicule pour carrosserie | D21: m² | E21: 10 | F21: 36 | G21: M17 | H21: 1 | O21: =IF(G21="","",IF(IFERROR(VLOOKUP(G21,Materialen!$A$2:$I$39,4,0),"")="plaat",Instellingen!$B$4,Instellingen!$B$3)) | P21: =ROUND(N(H21)*IFERROR(IF(VLOOKUP(G21,Materialen!$A$2:$I$39,9,0)="",0,VLOOKUP(G21,Materialen!$A$2:$I$39,9,0)),0)*(1+N(O21))+N(J21)*IFERROR(IF(VLOOKUP(I21,Materialen!$A$2:$I$39,9,0)="",0,VLOOKUP(I21,Materialen!$A$2:$I$39,9,0)),0)*(1+N(O21))+N(L21)*IFERROR(IF(VLOOKUP(K21,Materialen!$A$2:$I$39,9,0)="",0,VLOOKUP(K21,Materialen!$A$2:$I$39,9,0)),0)+N(N21)*IFERROR(IF(VLOOKUP(M21,Materialen!$A$2:$I$39,9,0)="",0,VLOOKUP(M21,Materialen!$A$2:$I$39,9,0)),0),2) | Q21: =IF(G21="",0,IF(IFERROR(VLOOKUP(G21,Materialen!$A$2:$I$39,5,0),"N")="J",ROUND(N(H21)*(1+N(O21))*Instellingen!$B$8,2),0)) | S21: =ROUND(N(R21)/60*Instellingen!$B$9,2) | U21: =P21+Q21+S21+N(T21) | V21: =IF(AC21<>"OK","",F21-U21) | W21: =IF(OR(F21=0,AC21<>"OK"),"",V21/F21) | X21: =IF(N(H21)>0,F21/H21,"") | Y21: =IF(N(H21)>0,IFERROR(IF(VLOOKUP(G21,Materialen!$A$2:$I$39,9,0)="",0,VLOOKUP(G21,Materialen!$A$2:$I$39,9,0)),0),"") | Z21: =ROUND(E21*F21,2) | AA21: =IF(AC21<>"OK","",ROUND(E21*U21,2)) | AB21: =IF(AC21<>"OK","",Z21-AA21) | AC21: =IF((IF(G21="",0,IF(IFERROR(IF(VLOOKUP(G21,Materialen!$A$2:$I$39,9,0)="",0,VLOOKUP(G21,Materialen!$A$2:$I$39,9,0)),0)=0,1,0))+IF(I21="",0,IF(IFERROR(IF(VLOOKUP(I21,Materialen!$A$2:$I$39,9,0)="",0,VLOOKUP(I21,Materialen!$A$2:$I$39,9,0)),0)=0,1,0))+IF(K21="",0,IF(IFERROR(IF(VLOOKUP(K21,Materialen!$A$2:$I$39,9,0)="",0,VLOOKUP(K21,Materialen!$A$2:$I$39,9,0)),0)=0,1,0))+IF(M21="",0,IF(IFERROR(IF(VLOOKUP(M21,Materialen!$A$2:$I$39,9,0)="",0,VLOOKUP(M21,Materialen!$A$2:$I$39,9,0)),0)=0,1,0)))>0,"aankoopprijs ontbreekt",IF(AND(G21="",K21="",N(T21)=0,N(R21)=0),"kost invullen (arbeid/overig)","OK"))
A22: 21 | B22: STICKERS | C22: Impression digitale quadri sur vinyle autocollant polymère pour extérieur (y compris découpe rectangle) | D22: m² | E22: 30 | F22: 32 | G22: M18 | H22: 1 | O22: =IF(G22="","",IF(IFERROR(VLOOKUP(G22,Materialen!$A$2:$I$39,4,0),"")="plaat",Instellingen!$B$4,Instellingen!$B$3)) | P22: =ROUND(N(H22)*IFERROR(IF(VLOOKUP(G22,Materialen!$A$2:$I$39,9,0)="",0,VLOOKUP(G22,Materialen!$A$2:$I$39,9,0)),0)*(1+N(O22))+N(J22)*IFERROR(IF(VLOOKUP(I22,Materialen!$A$2:$I$39,9,0)="",0,VLOOKUP(I22,Materialen!$A$2:$I$39,9,0)),0)*(1+N(O22))+N(L22)*IFERROR(IF(VLOOKUP(K22,Materialen!$A$2:$I$39,9,0)="",0,VLOOKUP(K22,Materialen!$A$2:$I$39,9,0)),0)+N(N22)*IFERROR(IF(VLOOKUP(M22,Materialen!$A$2:$I$39,9,0)="",0,VLOOKUP(M22,Materialen!$A$2:$I$39,9,0)),0),2) | Q22: =IF(G22="",0,IF(IFERROR(VLOOKUP(G22,Materialen!$A$2:$I$39,5,0),"N")="J",ROUND(N(H22)*(1+N(O22))*Instellingen!$B$8,2),0)) | S22: =ROUND(N(R22)/60*Instellingen!$B$9,2) | U22: =P22+Q22+S22+N(T22) | V22: =IF(AC22<>"OK","",F22-U22) | W22: =IF(OR(F22=0,AC22<>"OK"),"",V22/F22) | X22: =IF(N(H22)>0,F22/H22,"") | Y22: =IF(N(H22)>0,IFERROR(IF(VLOOKUP(G22,Materialen!$A$2:$I$39,9,0)="",0,VLOOKUP(G22,Materialen!$A$2:$I$39,9,0)),0),"") | Z22: =ROUND(E22*F22,2) | AA22: =IF(AC22<>"OK","",ROUND(E22*U22,2)) | AB22: =IF(AC22<>"OK","",Z22-AA22) | AC22: =IF((IF(G22="",0,IF(IFERROR(IF(VLOOKUP(G22,Materialen!$A$2:$I$39,9,0)="",0,VLOOKUP(G22,Materialen!$A$2:$I$39,9,0)),0)=0,1,0))+IF(I22="",0,IF(IFERROR(IF(VLOOKUP(I22,Materialen!$A$2:$I$39,9,0)="",0,VLOOKUP(I22,Materialen!$A$2:$I$39,9,0)),0)=0,1,0))+IF(K22="",0,IF(IFERROR(IF(VLOOKUP(K22,Materialen!$A$2:$I$39,9,0)="",0,VLOOKUP(K22,Materialen!$A$2:$I$39,9,0)),0)=0,1,0))+IF(M22="",0,IF(IFERROR(IF(VLOOKUP(M22,Materialen!$A$2:$I$39,9,0)="",0,VLOOKUP(M22,Materialen!$A$2:$I$39,9,0)),0)=0,1,0)))>0,"aankoopprijs ontbreekt",IF(AND(G22="",K22="",N(T22)=0,N(R22)=0),"kost invullen (arbeid/overig)","OK"))
A23: 22 | B23: STICKERS | C23: Vinyle autocollant pour pose extérieure sur vitrine carré 30x30 cm ou rond 30 cm diamètre impression quadri Quantité : par 10 | D23: pièce | E23: 30 | F23: 48 | G23: M15 | H23: 0.9 | O23: =IF(G23="","",IF(IFERROR(VLOOKUP(G23,Materialen!$A$2:$I$39,4,0),"")="plaat",Instellingen!$B$4,Instellingen!$B$3)) | P23: =ROUND(N(H23)*IFERROR(IF(VLOOKUP(G23,Materialen!$A$2:$I$39,9,0)="",0,VLOOKUP(G23,Materialen!$A$2:$I$39,9,0)),0)*(1+N(O23))+N(J23)*IFERROR(IF(VLOOKUP(I23,Materialen!$A$2:$I$39,9,0)="",0,VLOOKUP(I23,Materialen!$A$2:$I$39,9,0)),0)*(1+N(O23))+N(L23)*IFERROR(IF(VLOOKUP(K23,Materialen!$A$2:$I$39,9,0)="",0,VLOOKUP(K23,Materialen!$A$2:$I$39,9,0)),0)+N(N23)*IFERROR(IF(VLOOKUP(M23,Materialen!$A$2:$I$39,9,0)="",0,VLOOKUP(M23,Materialen!$A$2:$I$39,9,0)),0),2) | Q23: =IF(G23="",0,IF(IFERROR(VLOOKUP(G23,Materialen!$A$2:$I$39,5,0),"N")="J",ROUND(N(H23)*(1+N(O23))*Instellingen!$B$8,2),0)) | S23: =ROUND(N(R23)/60*Instellingen!$B$9,2) | U23: =P23+Q23+S23+N(T23) | V23: =IF(AC23<>"OK","",F23-U23) | W23: =IF(OR(F23=0,AC23<>"OK"),"",V23/F23) | X23: =IF(N(H23)>0,F23/H23,"") | Y23: =IF(N(H23)>0,IFERROR(IF(VLOOKUP(G23,Materialen!$A$2:$I$39,9,0)="",0,VLOOKUP(G23,Materialen!$A$2:$I$39,9,0)),0),"") | Z23: =ROUND(E23*F23,2) | AA23: =IF(AC23<>"OK","",ROUND(E23*U23,2)) | AB23: =IF(AC23<>"OK","",Z23-AA23) | AC23: =IF((IF(G23="",0,IF(IFERROR(IF(VLOOKUP(G23,Materialen!$A$2:$I$39,9,0)="",0,VLOOKUP(G23,Materialen!$A$2:$I$39,9,0)),0)=0,1,0))+IF(I23="",0,IF(IFERROR(IF(VLOOKUP(I23,Materialen!$A$2:$I$39,9,0)="",0,VLOOKUP(I23,Materialen!$A$2:$I$39,9,0)),0)=0,1,0))+IF(K23="",0,IF(IFERROR(IF(VLOOKUP(K23,Materialen!$A$2:$I$39,9,0)="",0,VLOOKUP(K23,Materialen!$A$2:$I$39,9,0)),0)=0,1,0))+IF(M23="",0,IF(IFERROR(IF(VLOOKUP(M23,Materialen!$A$2:$I$39,9,0)="",0,VLOOKUP(M23,Materialen!$A$2:$I$39,9,0)),0)=0,1,0)))>0,"aankoopprijs ontbreekt",IF(AND(G23="",K23="",N(T23)=0,N(R23)=0),"kost invullen (arbeid/overig)","OK")) | AD23: Geprijsd per 10 stuks (zie offerte) – te bevestigen
A24: 23 | B24: STICKERS | C24: Stickers Totem : format 84x199cm - adhésif monomère mat pour le sol - quantité : par 10 | D24: pièce | E24: 45 | F24: 75 | G24: M15 | H24: 1.67 | I24: M19 | J24: 1.67 | O24: =IF(G24="","",IF(IFERROR(VLOOKUP(G24,Materialen!$A$2:$I$39,4,0),"")="plaat",Instellingen!$B$4,Instellingen!$B$3)) | P24: =ROUND(N(H24)*IFERROR(IF(VLOOKUP(G24,Materialen!$A$2:$I$39,9,0)="",0,VLOOKUP(G24,Materialen!$A$2:$I$39,9,0)),0)*(1+N(O24))+N(J24)*IFERROR(IF(VLOOKUP(I24,Materialen!$A$2:$I$39,9,0)="",0,VLOOKUP(I24,Materialen!$A$2:$I$39,9,0)),0)*(1+N(O24))+N(L24)*IFERROR(IF(VLOOKUP(K24,Materialen!$A$2:$I$39,9,0)="",0,VLOOKUP(K24,Materialen!$A$2:$I$39,9,0)),0)+N(N24)*IFERROR(IF(VLOOKUP(M24,Materialen!$A$2:$I$39,9,0)="",0,VLOOKUP(M24,Materialen!$A$2:$I$39,9,0)),0),2) | Q24: =IF(G24="",0,IF(IFERROR(VLOOKUP(G24,Materialen!$A$2:$I$39,5,0),"N")="J",ROUND(N(H24)*(1+N(O24))*Instellingen!$B$8,2),0)) | S24: =ROUND(N(R24)/60*Instellingen!$B$9,2) | U24: =P24+Q24+S24+N(T24) | V24: =IF(AC24<>"OK","",F24-U24) | W24: =IF(OR(F24=0,AC24<>"OK"),"",V24/F24) | X24: =IF(N(H24)>0,F24/H24,"") | Y24: =IF(N(H24)>0,IFERROR(IF(VLOOKUP(G24,Materialen!$A$2:$I$39,9,0)="",0,VLOOKUP(G24,Materialen!$A$2:$I$39,9,0)),0),"") | Z24: =ROUND(E24*F24,2) | AA24: =IF(AC24<>"OK","",ROUND(E24*U24,2)) | AB24: =IF(AC24<>"OK","",Z24-AA24) | AC24: =IF((IF(G24="",0,IF(IFERROR(IF(VLOOKUP(G24,Materialen!$A$2:$I$39,9,0)="",0,VLOOKUP(G24,Materialen!$A$2:$I$39,9,0)),0)=0,1,0))+IF(I24="",0,IF(IFERROR(IF(VLOOKUP(I24,Materialen!$A$2:$I$39,9,0)="",0,VLOOKUP(I24,Materialen!$A$2:$I$39,9,0)),0)=0,1,0))+IF(K24="",0,IF(IFERROR(IF(VLOOKUP(K24,Materialen!$A$2:$I$39,9,0)="",0,VLOOKUP(K24,Materialen!$A$2:$I$39,9,0)),0)=0,1,0))+IF(M24="",0,IF(IFERROR(IF(VLOOKUP(M24,Materialen!$A$2:$I$39,9,0)="",0,VLOOKUP(M24,Materialen!$A$2:$I$39,9,0)),0)=0,1,0)))>0,"aankoopprijs ontbreekt",IF(AND(G24="",K24="",N(T24)=0,N(R24)=0),"kost invullen (arbeid/overig)","OK")) | AD24: Geprijsd per stuk – te bevestigen
A25: 24 | B25: STICKERS | C25: Placement des stickers : prestation pour la pose | D25: pièce | E25: 1 | F25: 55 | O25: =IF(G25="","",IF(IFERROR(VLOOKUP(G25,Materialen!$A$2:$I$39,4,0),"")="plaat",Instellingen!$B$4,Instellingen!$B$3)) | P25: =ROUND(N(H25)*IFERROR(IF(VLOOKUP(G25,Materialen!$A$2:$I$39,9,0)="",0,VLOOKUP(G25,Materialen!$A$2:$I$39,9,0)),0)*(1+N(O25))+N(J25)*IFERROR(IF(VLOOKUP(I25,Materialen!$A$2:$I$39,9,0)="",0,VLOOKUP(I25,Materialen!$A$2:$I$39,9,0)),0)*(1+N(O25))+N(L25)*IFERROR(IF(VLOOKUP(K25,Materialen!$A$2:$I$39,9,0)="",0,VLOOKUP(K25,Materialen!$A$2:$I$39,9,0)),0)+N(N25)*IFERROR(IF(VLOOKUP(M25,Materialen!$A$2:$I$39,9,0)="",0,VLOOKUP(M25,Materialen!$A$2:$I$39,9,0)),0),2) | Q25: =IF(G25="",0,IF(IFERROR(VLOOKUP(G25,Materialen!$A$2:$I$39,5,0),"N")="J",ROUND(N(H25)*(1+N(O25))*Instellingen!$B$8,2),0)) | S25: =ROUND(N(R25)/60*Instellingen!$B$9,2) | U25: =P25+Q25+S25+N(T25) | V25: =IF(AC25<>"OK","",F25-U25) | W25: =IF(OR(F25=0,AC25<>"OK"),"",V25/F25) | X25: =IF(N(H25)>0,F25/H25,"") | Y25: =IF(N(H25)>0,IFERROR(IF(VLOOKUP(G25,Materialen!$A$2:$I$39,9,0)="",0,VLOOKUP(G25,Materialen!$A$2:$I$39,9,0)),0),"") | Z25: =ROUND(E25*F25,2) | AA25: =IF(AC25<>"OK","",ROUND(E25*U25,2)) | AB25: =IF(AC25<>"OK","",Z25-AA25) | AC25: =IF((IF(G25="",0,IF(IFERROR(IF(VLOOKUP(G25,Materialen!$A$2:$I$39,9,0)="",0,VLOOKUP(G25,Materialen!$A$2:$I$39,9,0)),0)=0,1,0))+IF(I25="",0,IF(IFERROR(IF(VLOOKUP(I25,Materialen!$A$2:$I$39,9,0)="",0,VLOOKUP(I25,Materialen!$A$2:$I$39,9,0)),0)=0,1,0))+IF(K25="",0,IF(IFERROR(IF(VLOOKUP(K25,Materialen!$A$2:$I$39,9,0)="",0,VLOOKUP(K25,Materialen!$A$2:$I$39,9,0)),0)=0,1,0))+IF(M25="",0,IF(IFERROR(IF(VLOOKUP(M25,Materialen!$A$2:$I$39,9,0)="",0,VLOOKUP(M25,Materialen!$A$2:$I$39,9,0)),0)=0,1,0)))>0,"aankoopprijs ontbreekt",IF(AND(G25="",K25="",N(T25)=0,N(R25)=0),"kost invullen (arbeid/overig)","OK")) | AD25: Arbeid
A26: 25 | B26: STICKERS | C26: Enlèvement des stickers : prestation de démontage | D26: pièce | E26: 1 | F26: 45 | O26: =IF(G26="","",IF(IFERROR(VLOOKUP(G26,Materialen!$A$2:$I$39,4,0),"")="plaat",Instellingen!$B$4,Instellingen!$B$3)) | P26: =ROUND(N(H26)*IFERROR(IF(VLOOKUP(G26,Materialen!$A$2:$I$39,9,0)="",0,VLOOKUP(G26,Materialen!$A$2:$I$39,9,0)),0)*(1+N(O26))+N(J26)*IFERROR(IF(VLOOKUP(I26,Materialen!$A$2:$I$39,9,0)="",0,VLOOKUP(I26,Materialen!$A$2:$I$39,9,0)),0)*(1+N(O26))+N(L26)*IFERROR(IF(VLOOKUP(K26,Materialen!$A$2:$I$39,9,0)="",0,VLOOKUP(K26,Materialen!$A$2:$I$39,9,0)),0)+N(N26)*IFERROR(IF(VLOOKUP(M26,Materialen!$A$2:$I$39,9,0)="",0,VLOOKUP(M26,Materialen!$A$2:$I$39,9,0)),0),2) | Q26: =IF(G26="",0,IF(IFERROR(VLOOKUP(G26,Materialen!$A$2:$I$39,5,0),"N")="J",ROUND(N(H26)*(1+N(O26))*Instellingen!$B$8,2),0)) | S26: =ROUND(N(R26)/60*Instellingen!$B$9,2) | U26: =P26+Q26+S26+N(T26) | V26: =IF(AC26<>"OK","",F26-U26) | W26: =IF(OR(F26=0,AC26<>"OK"),"",V26/F26) | X26: =IF(N(H26)>0,F26/H26,"") | Y26: =IF(N(H26)>0,IFERROR(IF(VLOOKUP(G26,Materialen!$A$2:$I$39,9,0)="",0,VLOOKUP(G26,Materialen!$A$2:$I$39,9,0)),0),"") | Z26: =ROUND(E26*F26,2) | AA26: =IF(AC26<>"OK","",ROUND(E26*U26,2)) | AB26: =IF(AC26<>"OK","",Z26-AA26) | AC26: =IF((IF(G26="",0,IF(IFERROR(IF(VLOOKUP(G26,Materialen!$A$2:$I$39,9,0)="",0,VLOOKUP(G26,Materialen!$A$2:$I$39,9,0)),0)=0,1,0))+IF(I26="",0,IF(IFERROR(IF(VLOOKUP(I26,Materialen!$A$2:$I$39,9,0)="",0,VLOOKUP(I26,Materialen!$A$2:$I$39,9,0)),0)=0,1,0))+IF(K26="",0,IF(IFERROR(IF(VLOOKUP(K26,Materialen!$A$2:$I$39,9,0)="",0,VLOOKUP(K26,Materialen!$A$2:$I$39,9,0)),0)=0,1,0))+IF(M26="",0,IF(IFERROR(IF(VLOOKUP(M26,Materialen!$A$2:$I$39,9,0)="",0,VLOOKUP(M26,Materialen!$A$2:$I$39,9,0)),0)=0,1,0)))>0,"aankoopprijs ontbreekt",IF(AND(G26="",K26="",N(T26)=0,N(R26)=0),"kost invullen (arbeid/overig)","OK")) | AD26: Arbeid
A27: 26 | B27: BEACH FLAG | C27: Drapeau L 85 x H 260 cm - Hauteur totale avec mât (tube en alu) : 350 cm - Potence horizontale - Toile cousue avec fourreaux vertical et horizontal - Pied en croix - Mousqueton en bas de l'ourlet - Sac de transport | D27: pièce | E27: 20 | F27: 75 | G27: M20 | H27: 2.21 | K27: M21 | L27: 1 | O27: =IF(G27="","",IF(IFERROR(VLOOKUP(G27,Materialen!$A$2:$I$39,4,0),"")="plaat",Instellingen!$B$4,Instellingen!$B$3)) | P27: =ROUND(N(H27)*IFERROR(IF(VLOOKUP(G27,Materialen!$A$2:$I$39,9,0)="",0,VLOOKUP(G27,Materialen!$A$2:$I$39,9,0)),0)*(1+N(O27))+N(J27)*IFERROR(IF(VLOOKUP(I27,Materialen!$A$2:$I$39,9,0)="",0,VLOOKUP(I27,Materialen!$A$2:$I$39,9,0)),0)*(1+N(O27))+N(L27)*IFERROR(IF(VLOOKUP(K27,Materialen!$A$2:$I$39,9,0)="",0,VLOOKUP(K27,Materialen!$A$2:$I$39,9,0)),0)+N(N27)*IFERROR(IF(VLOOKUP(M27,Materialen!$A$2:$I$39,9,0)="",0,VLOOKUP(M27,Materialen!$A$2:$I$39,9,0)),0),2) | Q27: =IF(G27="",0,IF(IFERROR(VLOOKUP(G27,Materialen!$A$2:$I$39,5,0),"N")="J",ROUND(N(H27)*(1+N(O27))*Instellingen!$B$8,2),0)) | S27: =ROUND(N(R27)/60*Instellingen!$B$9,2) | U27: =P27+Q27+S27+N(T27) | V27: =IF(AC27<>"OK","",F27-U27) | W27: =IF(OR(F27=0,AC27<>"OK"),"",V27/F27) | X27: =IF(N(H27)>0,F27/H27,"") | Y27: =IF(N(H27)>0,IFERROR(IF(VLOOKUP(G27,Materialen!$A$2:$I$39,9,0)="",0,VLOOKUP(G27,Materialen!$A$2:$I$39,9,0)),0),"") | Z27: =ROUND(E27*F27,2) | AA27: =IF(AC27<>"OK","",ROUND(E27*U27,2)) | AB27: =IF(AC27<>"OK","",Z27-AA27) | AC27: =IF((IF(G27="",0,IF(IFERROR(IF(VLOOKUP(G27,Materialen!$A$2:$I$39,9,0)="",0,VLOOKUP(G27,Materialen!$A$2:$I$39,9,0)),0)=0,1,0))+IF(I27="",0,IF(IFERROR(IF(VLOOKUP(I27,Materialen!$A$2:$I$39,9,0)="",0,VLOOKUP(I27,Materialen!$A$2:$I$39,9,0)),0)=0,1,0))+IF(K27="",0,IF(IFERROR(IF(VLOOKUP(K27,Materialen!$A$2:$I$39,9,0)="",0,VLOOKUP(K27,Materialen!$A$2:$I$39,9,0)),0)=0,1,0))+IF(M27="",0,IF(IFERROR(IF(VLOOKUP(M27,Materialen!$A$2:$I$39,9,0)="",0,VLOOKUP(M27,Materialen!$A$2:$I$39,9,0)),0)=0,1,0)))>0,"aankoopprijs ontbreekt",IF(AND(G27="",K27="",N(T27)=0,N(R27)=0),"kost invullen (arbeid/overig)","OK"))
A28: 27 | B28: PANNEAUX | C28: Biprint : L60 x H910cm - impression quadrichromie recto sur panneau biprint de 3 mm | D28: pièce | E28: 20 | F28: 22 | G28: M22 | H28: 0.54 | O28: =IF(G28="","",IF(IFERROR(VLOOKUP(G28,Materialen!$A$2:$I$39,4,0),"")="plaat",Instellingen!$B$4,Instellingen!$B$3)) | P28: =ROUND(N(H28)*IFERROR(IF(VLOOKUP(G28,Materialen!$A$2:$I$39,9,0)="",0,VLOOKUP(G28,Materialen!$A$2:$I$39,9,0)),0)*(1+N(O28))+N(J28)*IFERROR(IF(VLOOKUP(I28,Materialen!$A$2:$I$39,9,0)="",0,VLOOKUP(I28,Materialen!$A$2:$I$39,9,0)),0)*(1+N(O28))+N(L28)*IFERROR(IF(VLOOKUP(K28,Materialen!$A$2:$I$39,9,0)="",0,VLOOKUP(K28,Materialen!$A$2:$I$39,9,0)),0)+N(N28)*IFERROR(IF(VLOOKUP(M28,Materialen!$A$2:$I$39,9,0)="",0,VLOOKUP(M28,Materialen!$A$2:$I$39,9,0)),0),2) | Q28: =IF(G28="",0,IF(IFERROR(VLOOKUP(G28,Materialen!$A$2:$I$39,5,0),"N")="J",ROUND(N(H28)*(1+N(O28))*Instellingen!$B$8,2),0)) | S28: =ROUND(N(R28)/60*Instellingen!$B$9,2) | U28: =P28+Q28+S28+N(T28) | V28: =IF(AC28<>"OK","",F28-U28) | W28: =IF(OR(F28=0,AC28<>"OK"),"",V28/F28) | X28: =IF(N(H28)>0,F28/H28,"") | Y28: =IF(N(H28)>0,IFERROR(IF(VLOOKUP(G28,Materialen!$A$2:$I$39,9,0)="",0,VLOOKUP(G28,Materialen!$A$2:$I$39,9,0)),0),"") | Z28: =ROUND(E28*F28,2) | AA28: =IF(AC28<>"OK","",ROUND(E28*U28,2)) | AB28: =IF(AC28<>"OK","",Z28-AA28) | AC28: =IF((IF(G28="",0,IF(IFERROR(IF(VLOOKUP(G28,Materialen!$A$2:$I$39,9,0)="",0,VLOOKUP(G28,Materialen!$A$2:$I$39,9,0)),0)=0,1,0))+IF(I28="",0,IF(IFERROR(IF(VLOOKUP(I28,Materialen!$A$2:$I$39,9,0)="",0,VLOOKUP(I28,Materialen!$A$2:$I$39,9,0)),0)=0,1,0))+IF(K28="",0,IF(IFERROR(IF(VLOOKUP(K28,Materialen!$A$2:$I$39,9,0)="",0,VLOOKUP(K28,Materialen!$A$2:$I$39,9,0)),0)=0,1,0))+IF(M28="",0,IF(IFERROR(IF(VLOOKUP(M28,Materialen!$A$2:$I$39,9,0)="",0,VLOOKUP(M28,Materialen!$A$2:$I$39,9,0)),0)=0,1,0)))>0,"aankoopprijs ontbreekt",IF(AND(G28="",K28="",N(T28)=0,N(R28)=0),"kost invullen (arbeid/overig)","OK"))
A29: 28 | B29: PANNEAUX | C29: Ronds : 40x40cm - impression quadrichromie recto sur panneau biprint de 3 mm | D29: pièce | E29: 20 | F29: 14 | G29: M22 | H29: 0.16 | O29: =IF(G29="","",IF(IFERROR(VLOOKUP(G29,Materialen!$A$2:$I$39,4,0),"")="plaat",Instellingen!$B$4,Instellingen!$B$3)) | P29: =ROUND(N(H29)*IFERROR(IF(VLOOKUP(G29,Materialen!$A$2:$I$39,9,0)="",0,VLOOKUP(G29,Materialen!$A$2:$I$39,9,0)),0)*(1+N(O29))+N(J29)*IFERROR(IF(VLOOKUP(I29,Materialen!$A$2:$I$39,9,0)="",0,VLOOKUP(I29,Materialen!$A$2:$I$39,9,0)),0)*(1+N(O29))+N(L29)*IFERROR(IF(VLOOKUP(K29,Materialen!$A$2:$I$39,9,0)="",0,VLOOKUP(K29,Materialen!$A$2:$I$39,9,0)),0)+N(N29)*IFERROR(IF(VLOOKUP(M29,Materialen!$A$2:$I$39,9,0)="",0,VLOOKUP(M29,Materialen!$A$2:$I$39,9,0)),0),2) | Q29: =IF(G29="",0,IF(IFERROR(VLOOKUP(G29,Materialen!$A$2:$I$39,5,0),"N")="J",ROUND(N(H29)*(1+N(O29))*Instellingen!$B$8,2),0)) | S29: =ROUND(N(R29)/60*Instellingen!$B$9,2) | U29: =P29+Q29+S29+N(T29) | V29: =IF(AC29<>"OK","",F29-U29) | W29: =IF(OR(F29=0,AC29<>"OK"),"",V29/F29) | X29: =IF(N(H29)>0,F29/H29,"") | Y29: =IF(N(H29)>0,IFERROR(IF(VLOOKUP(G29,Materialen!$A$2:$I$39,9,0)="",0,VLOOKUP(G29,Materialen!$A$2:$I$39,9,0)),0),"") | Z29: =ROUND(E29*F29,2) | AA29: =IF(AC29<>"OK","",ROUND(E29*U29,2)) | AB29: =IF(AC29<>"OK","",Z29-AA29) | AC29: =IF((IF(G29="",0,IF(IFERROR(IF(VLOOKUP(G29,Materialen!$A$2:$I$39,9,0)="",0,VLOOKUP(G29,Materialen!$A$2:$I$39,9,0)),0)=0,1,0))+IF(I29="",0,IF(IFERROR(IF(VLOOKUP(I29,Materialen!$A$2:$I$39,9,0)="",0,VLOOKUP(I29,Materialen!$A$2:$I$39,9,0)),0)=0,1,0))+IF(K29="",0,IF(IFERROR(IF(VLOOKUP(K29,Materialen!$A$2:$I$39,9,0)="",0,VLOOKUP(K29,Materialen!$A$2:$I$39,9,0)),0)=0,1,0))+IF(M29="",0,IF(IFERROR(IF(VLOOKUP(M29,Materialen!$A$2:$I$39,9,0)="",0,VLOOKUP(M29,Materialen!$A$2:$I$39,9,0)),0)=0,1,0)))>0,"aankoopprijs ontbreekt",IF(AND(G29="",K29="",N(T29)=0,N(R29)=0),"kost invullen (arbeid/overig)","OK"))
A30: 29 | B30: PANNEAUX | C30: Panneaux alvéolaires 50x20cm - 3,5cm d'épaisseur - pas de système d'accrochage - 4 coins droits - impression satinée UV - façonnage - production sur mesure | D30: pièce | E30: 20 | F30: 9 | G30: M23 | H30: 0.1 | O30: =IF(G30="","",IF(IFERROR(VLOOKUP(G30,Materialen!$A$2:$I$39,4,0),"")="plaat",Instellingen!$B$4,Instellingen!$B$3)) | P30: =ROUND(N(H30)*IFERROR(IF(VLOOKUP(G30,Materialen!$A$2:$I$39,9,0)="",0,VLOOKUP(G30,Materialen!$A$2:$I$39,9,0)),0)*(1+N(O30))+N(J30)*IFERROR(IF(VLOOKUP(I30,Materialen!$A$2:$I$39,9,0)="",0,VLOOKUP(I30,Materialen!$A$2:$I$39,9,0)),0)*(1+N(O30))+N(L30)*IFERROR(IF(VLOOKUP(K30,Materialen!$A$2:$I$39,9,0)="",0,VLOOKUP(K30,Materialen!$A$2:$I$39,9,0)),0)+N(N30)*IFERROR(IF(VLOOKUP(M30,Materialen!$A$2:$I$39,9,0)="",0,VLOOKUP(M30,Materialen!$A$2:$I$39,9,0)),0),2) | Q30: =IF(G30="",0,IF(IFERROR(VLOOKUP(G30,Materialen!$A$2:$I$39,5,0),"N")="J",ROUND(N(H30)*(1+N(O30))*Instellingen!$B$8,2),0)) | S30: =ROUND(N(R30)/60*Instellingen!$B$9,2) | U30: =P30+Q30+S30+N(T30) | V30: =IF(AC30<>"OK","",F30-U30) | W30: =IF(OR(F30=0,AC30<>"OK"),"",V30/F30) | X30: =IF(N(H30)>0,F30/H30,"") | Y30: =IF(N(H30)>0,IFERROR(IF(VLOOKUP(G30,Materialen!$A$2:$I$39,9,0)="",0,VLOOKUP(G30,Materialen!$A$2:$I$39,9,0)),0),"") | Z30: =ROUND(E30*F30,2) | AA30: =IF(AC30<>"OK","",ROUND(E30*U30,2)) | AB30: =IF(AC30<>"OK","",Z30-AA30) | AC30: =IF((IF(G30="",0,IF(IFERROR(IF(VLOOKUP(G30,Materialen!$A$2:$I$39,9,0)="",0,VLOOKUP(G30,Materialen!$A$2:$I$39,9,0)),0)=0,1,0))+IF(I30="",0,IF(IFERROR(IF(VLOOKUP(I30,Materialen!$A$2:$I$39,9,0)="",0,VLOOKUP(I30,Materialen!$A$2:$I$39,9,0)),0)=0,1,0))+IF(K30="",0,IF(IFERROR(IF(VLOOKUP(K30,Materialen!$A$2:$I$39,9,0)="",0,VLOOKUP(K30,Materialen!$A$2:$I$39,9,0)),0)=0,1,0))+IF(M30="",0,IF(IFERROR(IF(VLOOKUP(M30,Materialen!$A$2:$I$39,9,0)="",0,VLOOKUP(M30,Materialen!$A$2:$I$39,9,0)),0)=0,1,0)))>0,"aankoopprijs ontbreekt",IF(AND(G30="",K30="",N(T30)=0,N(R30)=0),"kost invullen (arbeid/overig)","OK"))
A31: 30 | B31: PANNEAUX | C31: Panneaux alvéolaires 59,4x84,1cm - 3,5cm d'épaisseur - pas de système d'accrochage - 4 coins droits - impression satinée UV - façonnage - production sur mesure | D31: pièce | E31: 20 | F31: 24 | G31: M23 | H31: 0.5 | O31: =IF(G31="","",IF(IFERROR(VLOOKUP(G31,Materialen!$A$2:$I$39,4,0),"")="plaat",Instellingen!$B$4,Instellingen!$B$3)) | P31: =ROUND(N(H31)*IFERROR(IF(VLOOKUP(G31,Materialen!$A$2:$I$39,9,0)="",0,VLOOKUP(G31,Materialen!$A$2:$I$39,9,0)),0)*(1+N(O31))+N(J31)*IFERROR(IF(VLOOKUP(I31,Materialen!$A$2:$I$39,9,0)="",0,VLOOKUP(I31,Materialen!$A$2:$I$39,9,0)),0)*(1+N(O31))+N(L31)*IFERROR(IF(VLOOKUP(K31,Materialen!$A$2:$I$39,9,0)="",0,VLOOKUP(K31,Materialen!$A$2:$I$39,9,0)),0)+N(N31)*IFERROR(IF(VLOOKUP(M31,Materialen!$A$2:$I$39,9,0)="",0,VLOOKUP(M31,Materialen!$A$2:$I$39,9,0)),0),2) | Q31: =IF(G31="",0,IF(IFERROR(VLOOKUP(G31,Materialen!$A$2:$I$39,5,0),"N")="J",ROUND(N(H31)*(1+N(O31))*Instellingen!$B$8,2),0)) | S31: =ROUND(N(R31)/60*Instellingen!$B$9,2) | U31: =P31+Q31+S31+N(T31) | V31: =IF(AC31<>"OK","",F31-U31) | W31: =IF(OR(F31=0,AC31<>"OK"),"",V31/F31) | X31: =IF(N(H31)>0,F31/H31,"") | Y31: =IF(N(H31)>0,IFERROR(IF(VLOOKUP(G31,Materialen!$A$2:$I$39,9,0)="",0,VLOOKUP(G31,Materialen!$A$2:$I$39,9,0)),0),"") | Z31: =ROUND(E31*F31,2) | AA31: =IF(AC31<>"OK","",ROUND(E31*U31,2)) | AB31: =IF(AC31<>"OK","",Z31-AA31) | AC31: =IF((IF(G31="",0,IF(IFERROR(IF(VLOOKUP(G31,Materialen!$A$2:$I$39,9,0)="",0,VLOOKUP(G31,Materialen!$A$2:$I$39,9,0)),0)=0,1,0))+IF(I31="",0,IF(IFERROR(IF(VLOOKUP(I31,Materialen!$A$2:$I$39,9,0)="",0,VLOOKUP(I31,Materialen!$A$2:$I$39,9,0)),0)=0,1,0))+IF(K31="",0,IF(IFERROR(IF(VLOOKUP(K31,Materialen!$A$2:$I$39,9,0)="",0,VLOOKUP(K31,Materialen!$A$2:$I$39,9,0)),0)=0,1,0))+IF(M31="",0,IF(IFERROR(IF(VLOOKUP(M31,Materialen!$A$2:$I$39,9,0)="",0,VLOOKUP(M31,Materialen!$A$2:$I$39,9,0)),0)=0,1,0)))>0,"aankoopprijs ontbreekt",IF(AND(G31="",K31="",N(T31)=0,N(R31)=0),"kost invullen (arbeid/overig)","OK"))
A32: 31 | B32: PANNEAUX | C32: Élastiques à boule de 5mm de diamètre et de longueur hors boule 15cm | D32: pièce | E32: 50 | F32: 0.45 | K32: M24 | L32: 1 | O32: =IF(G32="","",IF(IFERROR(VLOOKUP(G32,Materialen!$A$2:$I$39,4,0),"")="plaat",Instellingen!$B$4,Instellingen!$B$3)) | P32: =ROUND(N(H32)*IFERROR(IF(VLOOKUP(G32,Materialen!$A$2:$I$39,9,0)="",0,VLOOKUP(G32,Materialen!$A$2:$I$39,9,0)),0)*(1+N(O32))+N(J32)*IFERROR(IF(VLOOKUP(I32,Materialen!$A$2:$I$39,9,0)="",0,VLOOKUP(I32,Materialen!$A$2:$I$39,9,0)),0)*(1+N(O32))+N(L32)*IFERROR(IF(VLOOKUP(K32,Materialen!$A$2:$I$39,9,0)="",0,VLOOKUP(K32,Materialen!$A$2:$I$39,9,0)),0)+N(N32)*IFERROR(IF(VLOOKUP(M32,Materialen!$A$2:$I$39,9,0)="",0,VLOOKUP(M32,Materialen!$A$2:$I$39,9,0)),0),2) | Q32: =IF(G32="",0,IF(IFERROR(VLOOKUP(G32,Materialen!$A$2:$I$39,5,0),"N")="J",ROUND(N(H32)*(1+N(O32))*Instellingen!$B$8,2),0)) | S32: =ROUND(N(R32)/60*Instellingen!$B$9,2) | U32: =P32+Q32+S32+N(T32) | V32: =IF(AC32<>"OK","",F32-U32) | W32: =IF(OR(F32=0,AC32<>"OK"),"",V32/F32) | X32: =IF(N(H32)>0,F32/H32,"") | Y32: =IF(N(H32)>0,IFERROR(IF(VLOOKUP(G32,Materialen!$A$2:$I$39,9,0)="",0,VLOOKUP(G32,Materialen!$A$2:$I$39,9,0)),0),"") | Z32: =ROUND(E32*F32,2) | AA32: =IF(AC32<>"OK","",ROUND(E32*U32,2)) | AB32: =IF(AC32<>"OK","",Z32-AA32) | AC32: =IF((IF(G32="",0,IF(IFERROR(IF(VLOOKUP(G32,Materialen!$A$2:$I$39,9,0)="",0,VLOOKUP(G32,Materialen!$A$2:$I$39,9,0)),0)=0,1,0))+IF(I32="",0,IF(IFERROR(IF(VLOOKUP(I32,Materialen!$A$2:$I$39,9,0)="",0,VLOOKUP(I32,Materialen!$A$2:$I$39,9,0)),0)=0,1,0))+IF(K32="",0,IF(IFERROR(IF(VLOOKUP(K32,Materialen!$A$2:$I$39,9,0)="",0,VLOOKUP(K32,Materialen!$A$2:$I$39,9,0)),0)=0,1,0))+IF(M32="",0,IF(IFERROR(IF(VLOOKUP(M32,Materialen!$A$2:$I$39,9,0)="",0,VLOOKUP(M32,Materialen!$A$2:$I$39,9,0)),0)=0,1,0)))>0,"aankoopprijs ontbreekt",IF(AND(G32="",K32="",N(T32)=0,N(R32)=0),"kost invullen (arbeid/overig)","OK"))
A33: 32 | B33: PLACEMENT EVENTUEL | C33: Frais de déplacement aller- retour | D33: forfait | E33: 1 | F33: 45 | O33: =IF(G33="","",IF(IFERROR(VLOOKUP(G33,Materialen!$A$2:$I$39,4,0),"")="plaat",Instellingen!$B$4,Instellingen!$B$3)) | P33: =ROUND(N(H33)*IFERROR(IF(VLOOKUP(G33,Materialen!$A$2:$I$39,9,0)="",0,VLOOKUP(G33,Materialen!$A$2:$I$39,9,0)),0)*(1+N(O33))+N(J33)*IFERROR(IF(VLOOKUP(I33,Materialen!$A$2:$I$39,9,0)="",0,VLOOKUP(I33,Materialen!$A$2:$I$39,9,0)),0)*(1+N(O33))+N(L33)*IFERROR(IF(VLOOKUP(K33,Materialen!$A$2:$I$39,9,0)="",0,VLOOKUP(K33,Materialen!$A$2:$I$39,9,0)),0)+N(N33)*IFERROR(IF(VLOOKUP(M33,Materialen!$A$2:$I$39,9,0)="",0,VLOOKUP(M33,Materialen!$A$2:$I$39,9,0)),0),2) | Q33: =IF(G33="",0,IF(IFERROR(VLOOKUP(G33,Materialen!$A$2:$I$39,5,0),"N")="J",ROUND(N(H33)*(1+N(O33))*Instellingen!$B$8,2),0)) | S33: =ROUND(N(R33)/60*Instellingen!$B$9,2) | U33: =P33+Q33+S33+N(T33) | V33: =IF(AC33<>"OK","",F33-U33) | W33: =IF(OR(F33=0,AC33<>"OK"),"",V33/F33) | X33: =IF(N(H33)>0,F33/H33,"") | Y33: =IF(N(H33)>0,IFERROR(IF(VLOOKUP(G33,Materialen!$A$2:$I$39,9,0)="",0,VLOOKUP(G33,Materialen!$A$2:$I$39,9,0)),0),"") | Z33: =ROUND(E33*F33,2) | AA33: =IF(AC33<>"OK","",ROUND(E33*U33,2)) | AB33: =IF(AC33<>"OK","",Z33-AA33) | AC33: =IF((IF(G33="",0,IF(IFERROR(IF(VLOOKUP(G33,Materialen!$A$2:$I$39,9,0)="",0,VLOOKUP(G33,Materialen!$A$2:$I$39,9,0)),0)=0,1,0))+IF(I33="",0,IF(IFERROR(IF(VLOOKUP(I33,Materialen!$A$2:$I$39,9,0)="",0,VLOOKUP(I33,Materialen!$A$2:$I$39,9,0)),0)=0,1,0))+IF(K33="",0,IF(IFERROR(IF(VLOOKUP(K33,Materialen!$A$2:$I$39,9,0)="",0,VLOOKUP(K33,Materialen!$A$2:$I$39,9,0)),0)=0,1,0))+IF(M33="",0,IF(IFERROR(IF(VLOOKUP(M33,Materialen!$A$2:$I$39,9,0)="",0,VLOOKUP(M33,Materialen!$A$2:$I$39,9,0)),0)=0,1,0)))>0,"aankoopprijs ontbreekt",IF(AND(G33="",K33="",N(T33)=0,N(R33)=0),"kost invullen (arbeid/overig)","OK")) | AD33: Verplaatsing → overige kost
A34: 33 | B34: PLACEMENT EVENTUEL | C34: Tarif horaire | D34: heure | E34: 1 | F34: 48 | O34: =IF(G34="","",IF(IFERROR(VLOOKUP(G34,Materialen!$A$2:$I$39,4,0),"")="plaat",Instellingen!$B$4,Instellingen!$B$3)) | P34: =ROUND(N(H34)*IFERROR(IF(VLOOKUP(G34,Materialen!$A$2:$I$39,9,0)="",0,VLOOKUP(G34,Materialen!$A$2:$I$39,9,0)),0)*(1+N(O34))+N(J34)*IFERROR(IF(VLOOKUP(I34,Materialen!$A$2:$I$39,9,0)="",0,VLOOKUP(I34,Materialen!$A$2:$I$39,9,0)),0)*(1+N(O34))+N(L34)*IFERROR(IF(VLOOKUP(K34,Materialen!$A$2:$I$39,9,0)="",0,VLOOKUP(K34,Materialen!$A$2:$I$39,9,0)),0)+N(N34)*IFERROR(IF(VLOOKUP(M34,Materialen!$A$2:$I$39,9,0)="",0,VLOOKUP(M34,Materialen!$A$2:$I$39,9,0)),0),2) | Q34: =IF(G34="",0,IF(IFERROR(VLOOKUP(G34,Materialen!$A$2:$I$39,5,0),"N")="J",ROUND(N(H34)*(1+N(O34))*Instellingen!$B$8,2),0)) | S34: =ROUND(N(R34)/60*Instellingen!$B$9,2) | U34: =P34+Q34+S34+N(T34) | V34: =IF(AC34<>"OK","",F34-U34) | W34: =IF(OR(F34=0,AC34<>"OK"),"",V34/F34) | X34: =IF(N(H34)>0,F34/H34,"") | Y34: =IF(N(H34)>0,IFERROR(IF(VLOOKUP(G34,Materialen!$A$2:$I$39,9,0)="",0,VLOOKUP(G34,Materialen!$A$2:$I$39,9,0)),0),"") | Z34: =ROUND(E34*F34,2) | AA34: =IF(AC34<>"OK","",ROUND(E34*U34,2)) | AB34: =IF(AC34<>"OK","",Z34-AA34) | AC34: =IF((IF(G34="",0,IF(IFERROR(IF(VLOOKUP(G34,Materialen!$A$2:$I$39,9,0)="",0,VLOOKUP(G34,Materialen!$A$2:$I$39,9,0)),0)=0,1,0))+IF(I34="",0,IF(IFERROR(IF(VLOOKUP(I34,Materialen!$A$2:$I$39,9,0)="",0,VLOOKUP(I34,Materialen!$A$2:$I$39,9,0)),0)=0,1,0))+IF(K34="",0,IF(IFERROR(IF(VLOOKUP(K34,Materialen!$A$2:$I$39,9,0)="",0,VLOOKUP(K34,Materialen!$A$2:$I$39,9,0)),0)=0,1,0))+IF(M34="",0,IF(IFERROR(IF(VLOOKUP(M34,Materialen!$A$2:$I$39,9,0)="",0,VLOOKUP(M34,Materialen!$A$2:$I$39,9,0)),0)=0,1,0)))>0,"aankoopprijs ontbreekt",IF(AND(G34="",K34="",N(T34)=0,N(R34)=0),"kost invullen (arbeid/overig)","OK")) | AD34: Arbeid
W35: Marge % (volledige posten) | Y35: Verkoop posten met volledige kost
C36: TOTAAL | W36: =IF(Y36=0,"",AB36/Y36) | Y36: =SUMIF(AC2:AC34,"OK",Z2:Z34) | Z36: =SUM(Z2:Z34) | AA36: =SUM(AA2:AA34) | AB36: =SUM(AB2:AB34)
C37: Posten met ontbrekende aankoopprijs | AC37: =COUNTIF(AC2:AC34,"aankoopprijs ontbreekt")
C38: Let op: de totale marge is pas betrouwbaar als 'Controle' overal OK toont.

Sheet Lot 2
A1: N° | B1: Rubriek | C1: Omschrijving | D1: Eenheid | E1: Q | F1: Verkoop PU excl. btw | G1: Materiaal 1 | H1: m² mat. 1 / eenheid | I1: Materiaal 2 | J1: m² mat. 2 / eenheid | K1: Acc. 1 | L1: Aantal acc. 1 | M1: Acc. 2 | N1: Aantal acc. 2 | O1: Afval % | P1: Materiaalkost / eenheid | Q1: Inktkost / eenheid | R1: Arbeid min / eenheid | S1: Arbeid € / eenheid | T1: Overige kost / eenheid (huur, transport) | U1: Kostprijs / eenheid | V1: Marge € / eenheid | W1: Marge % | X1: Verkoop / m² | Y1: Aankoop mat. / m² | Z1: Totaal verkoop | AA1: Totaal kost | AB1: Totaal marge | AC1: Controle | AD1: Opmerking
A2: 1 | B2: Impression quadrichromie sur toile 100% polyester - 300g/m² - white - M1 à coller sur mur (intérieur) | C2: >= A2 et <= 1 m² | D2: m² | E2: 5 | F2: 48 | G2: M30 | H2: 1 | O2: =IF(G2="","",IF(IFERROR(VLOOKUP(G2,Materialen!$A$2:$I$39,4,0),"")="plaat",Instellingen!$B$4,Instellingen!$B$3)) | P2: =ROUND(N(H2)*IFERROR(IF(VLOOKUP(G2,Materialen!$A$2:$I$39,9,0)="",0,VLOOKUP(G2,Materialen!$A$2:$I$39,9,0)),0)*(1+N(O2))+N(J2)*IFERROR(IF(VLOOKUP(I2,Materialen!$A$2:$I$39,9,0)="",0,VLOOKUP(I2,Materialen!$A$2:$I$39,9,0)),0)*(1+N(O2))+N(L2)*IFERROR(IF(VLOOKUP(K2,Materialen!$A$2:$I$39,9,0)="",0,VLOOKUP(K2,Materialen!$A$2:$I$39,9,0)),0)+N(N2)*IFERROR(IF(VLOOKUP(M2,Materialen!$A$2:$I$39,9,0)="",0,VLOOKUP(M2,Materialen!$A$2:$I$39,9,0)),0),2) | Q2: =IF(G2="",0,IF(IFERROR(VLOOKUP(G2,Materialen!$A$2:$I$39,5,0),"N")="J",ROUND(N(H2)*(1+N(O2))*Instellingen!$B$8,2),0)) | S2: =ROUND(N(R2)/60*Instellingen!$B$9,2) | U2: =P2+Q2+S2+N(T2) | V2: =IF(AC2<>"OK","",F2-U2) | W2: =IF(OR(F2=0,AC2<>"OK"),"",V2/F2) | X2: =IF(N(H2)>0,F2/H2,"") | Y2: =IF(N(H2)>0,IFERROR(IF(VLOOKUP(G2,Materialen!$A$2:$I$39,9,0)="",0,VLOOKUP(G2,Materialen!$A$2:$I$39,9,0)),0),"") | Z2: =ROUND(E2*F2,2) | AA2: =IF(AC2<>"OK","",ROUND(E2*U2,2)) | AB2: =IF(AC2<>"OK","",Z2-AA2) | AC2: =IF((IF(G2="",0,IF(IFERROR(IF(VLOOKUP(G2,Materialen!$A$2:$I$39,9,0)="",0,VLOOKUP(G2,Materialen!$A$2:$I$39,9,0)),0)=0,1,0))+IF(I2="",0,IF(IFERROR(IF(VLOOKUP(I2,Materialen!$A$2:$I$39,9,0)="",0,VLOOKUP(I2,Materialen!$A$2:$I$39,9,0)),0)=0,1,0))+IF(K2="",0,IF(IFERROR(IF(VLOOKUP(K2,Materialen!$A$2:$I$39,9,0)="",0,VLOOKUP(K2,Materialen!$A$2:$I$39,9,0)),0)=0,1,0))+IF(M2="",0,IF(IFERROR(IF(VLOOKUP(M2,Materialen!$A$2:$I$39,9,0)="",0,VLOOKUP(M2,Materialen!$A$2:$I$39,9,0)),0)=0,1,0)))>0,"aankoopprijs ontbreekt",IF(AND(G2="",K2="",N(T2)=0,N(R2)=0),"kost invullen (arbeid/overig)","OK"))
A3: 2 | B3: Impression quadrichromie sur toile 100% polyester - 300g/m² - white - M1 à coller sur mur (intérieur) | C3: > 1 m² et <= 2 m² | D3: m² | E3: 5 | F3: 42 | G3: M30 | H3: 1 | O3: =IF(G3="","",IF(IFERROR(VLOOKUP(G3,Materialen!$A$2:$I$39,4,0),"")="plaat",Instellingen!$B$4,Instellingen!$B$3)) | P3: =ROUND(N(H3)*IFERROR(IF(VLOOKUP(G3,Materialen!$A$2:$I$39,9,0)="",0,VLOOKUP(G3,Materialen!$A$2:$I$39,9,0)),0)*(1+N(O3))+N(J3)*IFERROR(IF(VLOOKUP(I3,Materialen!$A$2:$I$39,9,0)="",0,VLOOKUP(I3,Materialen!$A$2:$I$39,9,0)),0)*(1+N(O3))+N(L3)*IFERROR(IF(VLOOKUP(K3,Materialen!$A$2:$I$39,9,0)="",0,VLOOKUP(K3,Materialen!$A$2:$I$39,9,0)),0)+N(N3)*IFERROR(IF(VLOOKUP(M3,Materialen!$A$2:$I$39,9,0)="",0,VLOOKUP(M3,Materialen!$A$2:$I$39,9,0)),0),2) | Q3: =IF(G3="",0,IF(IFERROR(VLOOKUP(G3,Materialen!$A$2:$I$39,5,0),"N")="J",ROUND(N(H3)*(1+N(O3))*Instellingen!$B$8,2),0)) | S3: =ROUND(N(R3)/60*Instellingen!$B$9,2) | U3: =P3+Q3+S3+N(T3) | V3: =IF(AC3<>"OK","",F3-U3) | W3: =IF(OR(F3=0,AC3<>"OK"),"",V3/F3) | X3: =IF(N(H3)>0,F3/H3,"") | Y3: =IF(N(H3)>0,IFERROR(IF(VLOOKUP(G3,Materialen!$A$2:$I$39,9,0)="",0,VLOOKUP(G3,Materialen!$A$2:$I$39,9,0)),0),"") | Z3: =ROUND(E3*F3,2) | AA3: =IF(AC3<>"OK","",ROUND(E3*U3,2)) | AB3: =IF(AC3<>"OK","",Z3-AA3) | AC3: =IF((IF(G3="",0,IF(IFERROR(IF(VLOOKUP(G3,Materialen!$A$2:$I$39,9,0)="",0,VLOOKUP(G3,Materialen!$A$2:$I$39,9,0)),0)=0,1,0))+IF(I3="",0,IF(IFERROR(IF(VLOOKUP(I3,Materialen!$A$2:$I$39,9,0)="",0,VLOOKUP(I3,Materialen!$A$2:$I$39,9,0)),0)=0,1,0))+IF(K3="",0,IF(IFERROR(IF(VLOOKUP(K3,Materialen!$A$2:$I$39,9,0)="",0,VLOOKUP(K3,Materialen!$A$2:$I$39,9,0)),0)=0,1,0))+IF(M3="",0,IF(IFERROR(IF(VLOOKUP(M3,Materialen!$A$2:$I$39,9,0)="",0,VLOOKUP(M3,Materialen!$A$2:$I$39,9,0)),0)=0,1,0)))>0,"aankoopprijs ontbreekt",IF(AND(G3="",K3="",N(T3)=0,N(R3)=0),"kost invullen (arbeid/overig)","OK"))
A4: 3 | B4: Impression quadrichromie sur toile 100% polyester - 300g/m² - white - M1 à coller sur mur (intérieur) | C4: > 2 m² et <= 5 m² | D4: m² | E4: 5 | F4: 38 | G4: M30 | H4: 1 | O4: =IF(G4="","",IF(IFERROR(VLOOKUP(G4,Materialen!$A$2:$I$39,4,0),"")="plaat",Instellingen!$B$4,Instellingen!$B$3)) | P4: =ROUND(N(H4)*IFERROR(IF(VLOOKUP(G4,Materialen!$A$2:$I$39,9,0)="",0,VLOOKUP(G4,Materialen!$A$2:$I$39,9,0)),0)*(1+N(O4))+N(J4)*IFERROR(IF(VLOOKUP(I4,Materialen!$A$2:$I$39,9,0)="",0,VLOOKUP(I4,Materialen!$A$2:$I$39,9,0)),0)*(1+N(O4))+N(L4)*IFERROR(IF(VLOOKUP(K4,Materialen!$A$2:$I$39,9,0)="",0,VLOOKUP(K4,Materialen!$A$2:$I$39,9,0)),0)+N(N4)*IFERROR(IF(VLOOKUP(M4,Materialen!$A$2:$I$39,9,0)="",0,VLOOKUP(M4,Materialen!$A$2:$I$39,9,0)),0),2) | Q4: =IF(G4="",0,IF(IFERROR(VLOOKUP(G4,Materialen!$A$2:$I$39,5,0),"N")="J",ROUND(N(H4)*(1+N(O4))*Instellingen!$B$8,2),0)) | S4: =ROUND(N(R4)/60*Instellingen!$B$9,2) | U4: =P4+Q4+S4+N(T4) | V4: =IF(AC4<>"OK","",F4-U4) | W4: =IF(OR(F4=0,AC4<>"OK"),"",V4/F4) | X4: =IF(N(H4)>0,F4/H4,"") | Y4: =IF(N(H4)>0,IFERROR(IF(VLOOKUP(G4,Materialen!$A$2:$I$39,9,0)="",0,VLOOKUP(G4,Materialen!$A$2:$I$39,9,0)),0),"") | Z4: =ROUND(E4*F4,2) | AA4: =IF(AC4<>"OK","",ROUND(E4*U4,2)) | AB4: =IF(AC4<>"OK","",Z4-AA4) | AC4: =IF((IF(G4="",0,IF(IFERROR(IF(VLOOKUP(G4,Materialen!$A$2:$I$39,9,0)="",0,VLOOKUP(G4,Materialen!$A$2:$I$39,9,0)),0)=0,1,0))+IF(I4="",0,IF(IFERROR(IF(VLOOKUP(I4,Materialen!$A$2:$I$39,9,0)="",0,VLOOKUP(I4,Materialen!$A$2:$I$39,9,0)),0)=0,1,0))+IF(K4="",0,IF(IFERROR(IF(VLOOKUP(K4,Materialen!$A$2:$I$39,9,0)="",0,VLOOKUP(K4,Materialen!$A$2:$I$39,9,0)),0)=0,1,0))+IF(M4="",0,IF(IFERROR(IF(VLOOKUP(M4,Materialen!$A$2:$I$39,9,0)="",0,VLOOKUP(M4,Materialen!$A$2:$I$39,9,0)),0)=0,1,0)))>0,"aankoopprijs ontbreekt",IF(AND(G4="",K4="",N(T4)=0,N(R4)=0),"kost invullen (arbeid/overig)","OK"))
A5: 4 | B5: Impression quadrichromie sur toile 100% polyester - 300g/m² - white - M1 à coller sur mur (intérieur) | C5: > 5 m² et <= 10 m² | D5: m² | E5: 5 | F5: 34 | G5: M30 | H5: 1 | O5: =IF(G5="","",IF(IFERROR(VLOOKUP(G5,Materialen!$A$2:$I$39,4,0),"")="plaat",Instellingen!$B$4,Instellingen!$B$3)) | P5: =ROUND(N(H5)*IFERROR(IF(VLOOKUP(G5,Materialen!$A$2:$I$39,9,0)="",0,VLOOKUP(G5,Materialen!$A$2:$I$39,9,0)),0)*(1+N(O5))+N(J5)*IFERROR(IF(VLOOKUP(I5,Materialen!$A$2:$I$39,9,0)="",0,VLOOKUP(I5,Materialen!$A$2:$I$39,9,0)),0)*(1+N(O5))+N(L5)*IFERROR(IF(VLOOKUP(K5,Materialen!$A$2:$I$39,9,0)="",0,VLOOKUP(K5,Materialen!$A$2:$I$39,9,0)),0)+N(N5)*IFERROR(IF(VLOOKUP(M5,Materialen!$A$2:$I$39,9,0)="",0,VLOOKUP(M5,Materialen!$A$2:$I$39,9,0)),0),2) | Q5: =IF(G5="",0,IF(IFERROR(VLOOKUP(G5,Materialen!$A$2:$I$39,5,0),"N")="J",ROUND(N(H5)*(1+N(O5))*Instellingen!$B$8,2),0)) | S5: =ROUND(N(R5)/60*Instellingen!$B$9,2) | U5: =P5+Q5+S5+N(T5) | V5: =IF(AC5<>"OK","",F5-U5) | W5: =IF(OR(F5=0,AC5<>"OK"),"",V5/F5) | X5: =IF(N(H5)>0,F5/H5,"") | Y5: =IF(N(H5)>0,IFERROR(IF(VLOOKUP(G5,Materialen!$A$2:$I$39,9,0)="",0,VLOOKUP(G5,Materialen!$A$2:$I$39,9,0)),0),"") | Z5: =ROUND(E5*F5,2) | AA5: =IF(AC5<>"OK","",ROUND(E5*U5,2)) | AB5: =IF(AC5<>"OK","",Z5-AA5) | AC5: =IF((IF(G5="",0,IF(IFERROR(IF(VLOOKUP(G5,Materialen!$A$2:$I$39,9,0)="",0,VLOOKUP(G5,Materialen!$A$2:$I$39,9,0)),0)=0,1,0))+IF(I5="",0,IF(IFERROR(IF(VLOOKUP(I5,Materialen!$A$2:$I$39,9,0)="",0,VLOOKUP(I5,Materialen!$A$2:$I$39,9,0)),0)=0,1,0))+IF(K5="",0,IF(IFERROR(IF(VLOOKUP(K5,Materialen!$A$2:$I$39,9,0)="",0,VLOOKUP(K5,Materialen!$A$2:$I$39,9,0)),0)=0,1,0))+IF(M5="",0,IF(IFERROR(IF(VLOOKUP(M5,Materialen!$A$2:$I$39,9,0)="",0,VLOOKUP(M5,Materialen!$A$2:$I$39,9,0)),0)=0,1,0)))>0,"aankoopprijs ontbreekt",IF(AND(G5="",K5="",N(T5)=0,N(R5)=0),"kost invullen (arbeid/overig)","OK"))
A6: 5 | B6: Impression quadrichromie sur toile 100% polyester - 300g/m² - white - M1 à coller sur mur (intérieur) | C6: > 10 m² et <= 25 m² | D6: m² | E6: 5 | F6: 30 | G6: M30 | H6: 1 | O6: =IF(G6="","",IF(IFERROR(VLOOKUP(G6,Materialen!$A$2:$I$39,4,0),"")="plaat",Instellingen!$B$4,Instellingen!$B$3)) | P6: =ROUND(N(H6)*IFERROR(IF(VLOOKUP(G6,Materialen!$A$2:$I$39,9,0)="",0,VLOOKUP(G6,Materialen!$A$2:$I$39,9,0)),0)*(1+N(O6))+N(J6)*IFERROR(IF(VLOOKUP(I6,Materialen!$A$2:$I$39,9,0)="",0,VLOOKUP(I6,Materialen!$A$2:$I$39,9,0)),0)*(1+N(O6))+N(L6)*IFERROR(IF(VLOOKUP(K6,Materialen!$A$2:$I$39,9,0)="",0,VLOOKUP(K6,Materialen!$A$2:$I$39,9,0)),0)+N(N6)*IFERROR(IF(VLOOKUP(M6,Materialen!$A$2:$I$39,9,0)="",0,VLOOKUP(M6,Materialen!$A$2:$I$39,9,0)),0),2) | Q6: =IF(G6="",0,IF(IFERROR(VLOOKUP(G6,Materialen!$A$2:$I$39,5,0),"N")="J",ROUND(N(H6)*(1+N(O6))*Instellingen!$B$8,2),0)) | S6: =ROUND(N(R6)/60*Instellingen!$B$9,2) | U6: =P6+Q6+S6+N(T6) | V6: =IF(AC6<>"OK","",F6-U6) | W6: =IF(OR(F6=0,AC6<>"OK"),"",V6/F6) | X6: =IF(N(H6)>0,F6/H6,"") | Y6: =IF(N(H6)>0,IFERROR(IF(VLOOKUP(G6,Materialen!$A$2:$I$39,9,0)="",0,VLOOKUP(G6,Materialen!$A$2:$I$39,9,0)),0),"") | Z6: =ROUND(E6*F6,2) | AA6: =IF(AC6<>"OK","",ROUND(E6*U6,2)) | AB6: =IF(AC6<>"OK","",Z6-AA6) | AC6: =IF((IF(G6="",0,IF(IFERROR(IF(VLOOKUP(G6,Materialen!$A$2:$I$39,9,0)="",0,VLOOKUP(G6,Materialen!$A$2:$I$39,9,0)),0)=0,1,0))+IF(I6="",0,IF(IFERROR(IF(VLOOKUP(I6,Materialen!$A$2:$I$39,9,0)="",0,VLOOKUP(I6,Materialen!$A$2:$I$39,9,0)),0)=0,1,0))+IF(K6="",0,IF(IFERROR(IF(VLOOKUP(K6,Materialen!$A$2:$I$39,9,0)="",0,VLOOKUP(K6,Materialen!$A$2:$I$39,9,0)),0)=0,1,0))+IF(M6="",0,IF(IFERROR(IF(VLOOKUP(M6,Materialen!$A$2:$I$39,9,0)="",0,VLOOKUP(M6,Materialen!$A$2:$I$39,9,0)),0)=0,1,0)))>0,"aankoopprijs ontbreekt",IF(AND(G6="",K6="",N(T6)=0,N(R6)=0),"kost invullen (arbeid/overig)","OK"))
A7: 6 | B7: Impression quadrichromie sur toile 100% polyester - 300g/m² - white - M1 à coller sur mur (intérieur) | C7: > 25 m² | D7: m² | E7: 5 | F7: 28 | G7: M30 | H7: 1 | O7: =IF(G7="","",IF(IFERROR(VLOOKUP(G7,Materialen!$A$2:$I$39,4,0),"")="plaat",Instellingen!$B$4,Instellingen!$B$3)) | P7: =ROUND(N(H7)*IFERROR(IF(VLOOKUP(G7,Materialen!$A$2:$I$39,9,0)="",0,VLOOKUP(G7,Materialen!$A$2:$I$39,9,0)),0)*(1+N(O7))+N(J7)*IFERROR(IF(VLOOKUP(I7,Materialen!$A$2:$I$39,9,0)="",0,VLOOKUP(I7,Materialen!$A$2:$I$39,9,0)),0)*(1+N(O7))+N(L7)*IFERROR(IF(VLOOKUP(K7,Materialen!$A$2:$I$39,9,0)="",0,VLOOKUP(K7,Materialen!$A$2:$I$39,9,0)),0)+N(N7)*IFERROR(IF(VLOOKUP(M7,Materialen!$A$2:$I$39,9,0)="",0,VLOOKUP(M7,Materialen!$A$2:$I$39,9,0)),0),2) | Q7: =IF(G7="",0,IF(IFERROR(VLOOKUP(G7,Materialen!$A$2:$I$39,5,0),"N")="J",ROUND(N(H7)*(1+N(O7))*Instellingen!$B$8,2),0)) | S7: =ROUND(N(R7)/60*Instellingen!$B$9,2) | U7: =P7+Q7+S7+N(T7) | V7: =IF(AC7<>"OK","",F7-U7) | W7: =IF(OR(F7=0,AC7<>"OK"),"",V7/F7) | X7: =IF(N(H7)>0,F7/H7,"") | Y7: =IF(N(H7)>0,IFERROR(IF(VLOOKUP(G7,Materialen!$A$2:$I$39,9,0)="",0,VLOOKUP(G7,Materialen!$A$2:$I$39,9,0)),0),"") | Z7: =ROUND(E7*F7,2) | AA7: =IF(AC7<>"OK","",ROUND(E7*U7,2)) | AB7: =IF(AC7<>"OK","",Z7-AA7) | AC7: =IF((IF(G7="",0,IF(IFERROR(IF(VLOOKUP(G7,Materialen!$A$2:$I$39,9,0)="",0,VLOOKUP(G7,Materialen!$A$2:$I$39,9,0)),0)=0,1,0))+IF(I7="",0,IF(IFERROR(IF(VLOOKUP(I7,Materialen!$A$2:$I$39,9,0)="",0,VLOOKUP(I7,Materialen!$A$2:$I$39,9,0)),0)=0,1,0))+IF(K7="",0,IF(IFERROR(IF(VLOOKUP(K7,Materialen!$A$2:$I$39,9,0)="",0,VLOOKUP(K7,Materialen!$A$2:$I$39,9,0)),0)=0,1,0))+IF(M7="",0,IF(IFERROR(IF(VLOOKUP(M7,Materialen!$A$2:$I$39,9,0)="",0,VLOOKUP(M7,Materialen!$A$2:$I$39,9,0)),0)=0,1,0)))>0,"aankoopprijs ontbreekt",IF(AND(G7="",K7="",N(T7)=0,N(R7)=0),"kost invullen (arbeid/overig)","OK"))
A8: 7 | B8: Impression sur panneaux FOREX de 2mm | C8: >= A2 et <= 1 m² | D8: m² | E8: 5 | F8: 62 | G8: M31 | H8: 1 | O8: =IF(G8="","",IF(IFERROR(VLOOKUP(G8,Materialen!$A$2:$I$39,4,0),"")="plaat",Instellingen!$B$4,Instellingen!$B$3)) | P8: =ROUND(N(H8)*IFERROR(IF(VLOOKUP(G8,Materialen!$A$2:$I$39,9,0)="",0,VLOOKUP(G8,Materialen!$A$2:$I$39,9,0)),0)*(1+N(O8))+N(J8)*IFERROR(IF(VLOOKUP(I8,Materialen!$A$2:$I$39,9,0)="",0,VLOOKUP(I8,Materialen!$A$2:$I$39,9,0)),0)*(1+N(O8))+N(L8)*IFERROR(IF(VLOOKUP(K8,Materialen!$A$2:$I$39,9,0)="",0,VLOOKUP(K8,Materialen!$A$2:$I$39,9,0)),0)+N(N8)*IFERROR(IF(VLOOKUP(M8,Materialen!$A$2:$I$39,9,0)="",0,VLOOKUP(M8,Materialen!$A$2:$I$39,9,0)),0),2) | Q8: =IF(G8="",0,IF(IFERROR(VLOOKUP(G8,Materialen!$A$2:$I$39,5,0),"N")="J",ROUND(N(H8)*(1+N(O8))*Instellingen!$B$8,2),0)) | S8: =ROUND(N(R8)/60*Instellingen!$B$9,2) | U8: =P8+Q8+S8+N(T8) | V8: =IF(AC8<>"OK","",F8-U8) | W8: =IF(OR(F8=0,AC8<>"OK"),"",V8/F8) | X8: =IF(N(H8)>0,F8/H8,"") | Y8: =IF(N(H8)>0,IFERROR(IF(VLOOKUP(G8,Materialen!$A$2:$I$39,9,0)="",0,VLOOKUP(G8,Materialen!$A$2:$I$39,9,0)),0),"") | Z8: =ROUND(E8*F8,2) | AA8: =IF(AC8<>"OK","",ROUND(E8*U8,2)) | AB8: =IF(AC8<>"OK","",Z8-AA8) | AC8: =IF((IF(G8="",0,IF(IFERROR(IF(VLOOKUP(G8,Materialen!$A$2:$I$39,9,0)="",0,VLOOKUP(G8,Materialen!$A$2:$I$39,9,0)),0)=0,1,0))+IF(I8="",0,IF(IFERROR(IF(VLOOKUP(I8,Materialen!$A$2:$I$39,9,0)="",0,VLOOKUP(I8,Materialen!$A$2:$I$39,9,0)),0)=0,1,0))+IF(K8="",0,IF(IFERROR(IF(VLOOKUP(K8,Materialen!$A$2:$I$39,9,0)="",0,VLOOKUP(K8,Materialen!$A$2:$I$39,9,0)),0)=0,1,0))+IF(M8="",0,IF(IFERROR(IF(VLOOKUP(M8,Materialen!$A$2:$I$39,9,0)="",0,VLOOKUP(M8,Materialen!$A$2:$I$39,9,0)),0)=0,1,0)))>0,"aankoopprijs ontbreekt",IF(AND(G8="",K8="",N(T8)=0,N(R8)=0),"kost invullen (arbeid/overig)","OK"))
A9: 8 | B9: Impression sur panneaux FOREX de 2mm | C9: > 1 m² et <= 2 m² | D9: m² | E9: 5 | F9: 52 | G9: M31 | H9: 1 | O9: =IF(G9="","",IF(IFERROR(VLOOKUP(G9,Materialen!$A$2:$I$39,4,0),"")="plaat",Instellingen!$B$4,Instellingen!$B$3)) | P9: =ROUND(N(H9)*IFERROR(IF(VLOOKUP(G9,Materialen!$A$2:$I$39,9,0)="",0,VLOOKUP(G9,Materialen!$A$2:$I$39,9,0)),0)*(1+N(O9))+N(J9)*IFERROR(IF(VLOOKUP(I9,Materialen!$A$2:$I$39,9,0)="",0,VLOOKUP(I9,Materialen!$A$2:$I$39,9,0)),0)*(1+N(O9))+N(L9)*IFERROR(IF(VLOOKUP(K9,Materialen!$A$2:$I$39,9,0)="",0,VLOOKUP(K9,Materialen!$A$2:$I$39,9,0)),0)+N(N9)*IFERROR(IF(VLOOKUP(M9,Materialen!$A$2:$I$39,9,0)="",0,VLOOKUP(M9,Materialen!$A$2:$I$39,9,0)),0),2) | Q9: =IF(G9="",0,IF(IFERROR(VLOOKUP(G9,Materialen!$A$2:$I$39,5,0),"N")="J",ROUND(N(H9)*(1+N(O9))*Instellingen!$B$8,2),0)) | S9: =ROUND(N(R9)/60*Instellingen!$B$9,2) | U9: =P9+Q9+S9+N(T9) | V9: =IF(AC9<>"OK","",F9-U9) | W9: =IF(OR(F9=0,AC9<>"OK"),"",V9/F9) | X9: =IF(N(H9)>0,F9/H9,"") | Y9: =IF(N(H9)>0,IFERROR(IF(VLOOKUP(G9,Materialen!$A$2:$I$39,9,0)="",0,VLOOKUP(G9,Materialen!$A$2:$I$39,9,0)),0),"") | Z9: =ROUND(E9*F9,2) | AA9: =IF(AC9<>"OK","",ROUND(E9*U9,2)) | AB9: =IF(AC9<>"OK","",Z9-AA9) | AC9: =IF((IF(G9="",0,IF(IFERROR(IF(VLOOKUP(G9,Materialen!$A$2:$I$39,9,0)="",0,VLOOKUP(G9,Materialen!$A$2:$I$39,9,0)),0)=0,1,0))+IF(I9="",0,IF(IFERROR(IF(VLOOKUP(I9,Materialen!$A$2:$I$39,9,0)="",0,VLOOKUP(I9,Materialen!$A$2:$I$39,9,0)),0)=0,1,0))+IF(K9="",0,IF(IFERROR(IF(VLOOKUP(K9,Materialen!$A$2:$I$39,9,0)="",0,VLOOKUP(K9,Materialen!$A$2:$I$39,9,0)),0)=0,1,0))+IF(M9="",0,IF(IFERROR(IF(VLOOKUP(M9,Materialen!$A$2:$I$39,9,0)="",0,VLOOKUP(M9,Materialen!$A$2:$I$39,9,0)),0)=0,1,0)))>0,"aankoopprijs ontbreekt",IF(AND(G9="",K9="",N(T9)=0,N(R9)=0),"kost invullen (arbeid/overig)","OK"))
A10: 9 | B10: Impression sur panneaux FOREX de 2mm | C10: > 2 m² et <= 5 m² | D10: m² | E10: 5 | F10: 46 | G10: M31 | H10: 1 | O10: =IF(G10="","",IF(IFERROR(VLOOKUP(G10,Materialen!$A$2:$I$39,4,0),"")="plaat",Instellingen!$B$4,Instellingen!$B$3)) | P10: =ROUND(N(H10)*IFERROR(IF(VLOOKUP(G10,Materialen!$A$2:$I$39,9,0)="",0,VLOOKUP(G10,Materialen!$A$2:$I$39,9,0)),0)*(1+N(O10))+N(J10)*IFERROR(IF(VLOOKUP(I10,Materialen!$A$2:$I$39,9,0)="",0,VLOOKUP(I10,Materialen!$A$2:$I$39,9,0)),0)*(1+N(O10))+N(L10)*IFERROR(IF(VLOOKUP(K10,Materialen!$A$2:$I$39,9,0)="",0,VLOOKUP(K10,Materialen!$A$2:$I$39,9,0)),0)+N(N10)*IFERROR(IF(VLOOKUP(M10,Materialen!$A$2:$I$39,9,0)="",0,VLOOKUP(M10,Materialen!$A$2:$I$39,9,0)),0),2) | Q10: =IF(G10="",0,IF(IFERROR(VLOOKUP(G10,Materialen!$A$2:$I$39,5,0),"N")="J",ROUND(N(H10)*(1+N(O10))*Instellingen!$B$8,2),0)) | S10: =ROUND(N(R10)/60*Instellingen!$B$9,2) | U10: =P10+Q10+S10+N(T10) | V10: =IF(AC10<>"OK","",F10-U10) | W10: =IF(OR(F10=0,AC10<>"OK"),"",V10/F10) | X10: =IF(N(H10)>0,F10/H10,"") | Y10: =IF(N(H10)>0,IFERROR(IF(VLOOKUP(G10,Materialen!$A$2:$I$39,9,0)="",0,VLOOKUP(G10,Materialen!$A$2:$I$39,9,0)),0),"") | Z10: =ROUND(E10*F10,2) | AA10: =IF(AC10<>"OK","",ROUND(E10*U10,2)) | AB10: =IF(AC10<>"OK","",Z10-AA10) | AC10: =IF((IF(G10="",0,IF(IFERROR(IF(VLOOKUP(G10,Materialen!$A$2:$I$39,9,0)="",0,VLOOKUP(G10,Materialen!$A$2:$I$39,9,0)),0)=0,1,0))+IF(I10="",0,IF(IFERROR(IF(VLOOKUP(I10,Materialen!$A$2:$I$39,9,0)="",0,VLOOKUP(I10,Materialen!$A$2:$I$39,9,0)),0)=0,1,0))+IF(K10="",0,IF(IFERROR(IF(VLOOKUP(K10,Materialen!$A$2:$I$39,9,0)="",0,VLOOKUP(K10,Materialen!$A$2:$I$39,9,0)),0)=0,1,0))+IF(M10="",0,IF(IFERROR(IF(VLOOKUP(M10,Materialen!$A$2:$I$39,9,0)="",0,VLOOKUP(M10,Materialen!$A$2:$I$39,9,0)),0)=0,1,0)))>0,"aankoopprijs ontbreekt",IF(AND(G10="",K10="",N(T10)=0,N(R10)=0),"kost invullen (arbeid/overig)","OK"))
A11: 10 | B11: Impression sur panneaux FOREX de 2mm | C11: > 5 m² et <= 10 m² | D11: m² | E11: 5 | F11: 40 | G11: M31 | H11: 1 | O11: =IF(G11="","",IF(IFERROR(VLOOKUP(G11,Materialen!$A$2:$I$39,4,0),"")="plaat",Instellingen!$B$4,Instellingen!$B$3)) | P11: =ROUND(N(H11)*IFERROR(IF(VLOOKUP(G11,Materialen!$A$2:$I$39,9,0)="",0,VLOOKUP(G11,Materialen!$A$2:$I$39,9,0)),0)*(1+N(O11))+N(J11)*IFERROR(IF(VLOOKUP(I11,Materialen!$A$2:$I$39,9,0)="",0,VLOOKUP(I11,Materialen!$A$2:$I$39,9,0)),0)*(1+N(O11))+N(L11)*IFERROR(IF(VLOOKUP(K11,Materialen!$A$2:$I$39,9,0)="",0,VLOOKUP(K11,Materialen!$A$2:$I$39,9,0)),0)+N(N11)*IFERROR(IF(VLOOKUP(M11,Materialen!$A$2:$I$39,9,0)="",0,VLOOKUP(M11,Materialen!$A$2:$I$39,9,0)),0),2) | Q11: =IF(G11="",0,IF(IFERROR(VLOOKUP(G11,Materialen!$A$2:$I$39,5,0),"N")="J",ROUND(N(H11)*(1+N(O11))*Instellingen!$B$8,2),0)) | S11: =ROUND(N(R11)/60*Instellingen!$B$9,2) | U11: =P11+Q11+S11+N(T11) | V11: =IF(AC11<>"OK","",F11-U11) | W11: =IF(OR(F11=0,AC11<>"OK"),"",V11/F11) | X11: =IF(N(H11)>0,F11/H11,"") | Y11: =IF(N(H11)>0,IFERROR(IF(VLOOKUP(G11,Materialen!$A$2:$I$39,9,0)="",0,VLOOKUP(G11,Materialen!$A$2:$I$39,9,0)),0),"") | Z11: =ROUND(E11*F11,2) | AA11: =IF(AC11<>"OK","",ROUND(E11*U11,2)) | AB11: =IF(AC11<>"OK","",Z11-AA11) | AC11: =IF((IF(G11="",0,IF(IFERROR(IF(VLOOKUP(G11,Materialen!$A$2:$I$39,9,0)="",0,VLOOKUP(G11,Materialen!$A$2:$I$39,9,0)),0)=0,1,0))+IF(I11="",0,IF(IFERROR(IF(VLOOKUP(I11,Materialen!$A$2:$I$39,9,0)="",0,VLOOKUP(I11,Materialen!$A$2:$I$39,9,0)),0)=0,1,0))+IF(K11="",0,IF(IFERROR(IF(VLOOKUP(K11,Materialen!$A$2:$I$39,9,0)="",0,VLOOKUP(K11,Materialen!$A$2:$I$39,9,0)),0)=0,1,0))+IF(M11="",0,IF(IFERROR(IF(VLOOKUP(M11,Materialen!$A$2:$I$39,9,0)="",0,VLOOKUP(M11,Materialen!$A$2:$I$39,9,0)),0)=0,1,0)))>0,"aankoopprijs ontbreekt",IF(AND(G11="",K11="",N(T11)=0,N(R11)=0),"kost invullen (arbeid/overig)","OK"))
A12: 11 | B12: Impression sur panneaux FOREX de 2mm | C12: > 10 m² et <= 25 m² | D12: m² | E12: 5 | F12: 36 | G12: M31 | H12: 1 | O12: =IF(G12="","",IF(IFERROR(VLOOKUP(G12,Materialen!$A$2:$I$39,4,0),"")="plaat",Instellingen!$B$4,Instellingen!$B$3)) | P12: =ROUND(N(H12)*IFERROR(IF(VLOOKUP(G12,Materialen!$A$2:$I$39,9,0)="",0,VLOOKUP(G12,Materialen!$A$2:$I$39,9,0)),0)*(1+N(O12))+N(J12)*IFERROR(IF(VLOOKUP(I12,Materialen!$A$2:$I$39,9,0)="",0,VLOOKUP(I12,Materialen!$A$2:$I$39,9,0)),0)*(1+N(O12))+N(L12)*IFERROR(IF(VLOOKUP(K12,Materialen!$A$2:$I$39,9,0)="",0,VLOOKUP(K12,Materialen!$A$2:$I$39,9,0)),0)+N(N12)*IFERROR(IF(VLOOKUP(M12,Materialen!$A$2:$I$39,9,0)="",0,VLOOKUP(M12,Materialen!$A$2:$I$39,9,0)),0),2) | Q12: =IF(G12="",0,IF(IFERROR(VLOOKUP(G12,Materialen!$A$2:$I$39,5,0),"N")="J",ROUND(N(H12)*(1+N(O12))*Instellingen!$B$8,2),0)) | S12: =ROUND(N(R12)/60*Instellingen!$B$9,2) | U12: =P12+Q12+S12+N(T12) | V12: =IF(AC12<>"OK","",F12-U12) | W12: =IF(OR(F12=0,AC12<>"OK"),"",V12/F12) | X12: =IF(N(H12)>0,F12/H12,"") | Y12: =IF(N(H12)>0,IFERROR(IF(VLOOKUP(G12,Materialen!$A$2:$I$39,9,0)="",0,VLOOKUP(G12,Materialen!$A$2:$I$39,9,0)),0),"") | Z12: =ROUND(E12*F12,2) | AA12: =IF(AC12<>"OK","",ROUND(E12*U12,2)) | AB12: =IF(AC12<>"OK","",Z12-AA12) | AC12: =IF((IF(G12="",0,IF(IFERROR(IF(VLOOKUP(G12,Materialen!$A$2:$I$39,9,0)="",0,VLOOKUP(G12,Materialen!$A$2:$I$39,9,0)),0)=0,1,0))+IF(I12="",0,IF(IFERROR(IF(VLOOKUP(I12,Materialen!$A$2:$I$39,9,0)="",0,VLOOKUP(I12,Materialen!$A$2:$I$39,9,0)),0)=0,1,0))+IF(K12="",0,IF(IFERROR(IF(VLOOKUP(K12,Materialen!$A$2:$I$39,9,0)="",0,VLOOKUP(K12,Materialen!$A$2:$I$39,9,0)),0)=0,1,0))+IF(M12="",0,IF(IFERROR(IF(VLOOKUP(M12,Materialen!$A$2:$I$39,9,0)="",0,VLOOKUP(M12,Materialen!$A$2:$I$39,9,0)),0)=0,1,0)))>0,"aankoopprijs ontbreekt",IF(AND(G12="",K12="",N(T12)=0,N(R12)=0),"kost invullen (arbeid/overig)","OK"))
A13: 12 | B13: Impression sur panneaux FOREX de 2mm | C13: > 25 m² | D13: m² | E13: 5 | F13: 33 | G13: M31 | H13: 1 | O13: =IF(G13="","",IF(IFERROR(VLOOKUP(G13,Materialen!$A$2:$I$39,4,0),"")="plaat",Instellingen!$B$4,Instellingen!$B$3)) | P13: =ROUND(N(H13)*IFERROR(IF(VLOOKUP(G13,Materialen!$A$2:$I$39,9,0)="",0,VLOOKUP(G13,Materialen!$A$2:$I$39,9,0)),0)*(1+N(O13))+N(J13)*IFERROR(IF(VLOOKUP(I13,Materialen!$A$2:$I$39,9,0)="",0,VLOOKUP(I13,Materialen!$A$2:$I$39,9,0)),0)*(1+N(O13))+N(L13)*IFERROR(IF(VLOOKUP(K13,Materialen!$A$2:$I$39,9,0)="",0,VLOOKUP(K13,Materialen!$A$2:$I$39,9,0)),0)+N(N13)*IFERROR(IF(VLOOKUP(M13,Materialen!$A$2:$I$39,9,0)="",0,VLOOKUP(M13,Materialen!$A$2:$I$39,9,0)),0),2) | Q13: =IF(G13="",0,IF(IFERROR(VLOOKUP(G13,Materialen!$A$2:$I$39,5,0),"N")="J",ROUND(N(H13)*(1+N(O13))*Instellingen!$B$8,2),0)) | S13: =ROUND(N(R13)/60*Instellingen!$B$9,2) | U13: =P13+Q13+S13+N(T13) | V13: =IF(AC13<>"OK","",F13-U13) | W13: =IF(OR(F13=0,AC13<>"OK"),"",V13/F13) | X13: =IF(N(H13)>0,F13/H13,"") | Y13: =IF(N(H13)>0,IFERROR(IF(VLOOKUP(G13,Materialen!$A$2:$I$39,9,0)="",0,VLOOKUP(G13,Materialen!$A$2:$I$39,9,0)),0),"") | Z13: =ROUND(E13*F13,2) | AA13: =IF(AC13<>"OK","",ROUND(E13*U13,2)) | AB13: =IF(AC13<>"OK","",Z13-AA13) | AC13: =IF((IF(G13="",0,IF(IFERROR(IF(VLOOKUP(G13,Materialen!$A$2:$I$39,9,0)="",0,VLOOKUP(G13,Materialen!$A$2:$I$39,9,0)),0)=0,1,0))+IF(I13="",0,IF(IFERROR(IF(VLOOKUP(I13,Materialen!$A$2:$I$39,9,0)="",0,VLOOKUP(I13,Materialen!$A$2:$I$39,9,0)),0)=0,1,0))+IF(K13="",0,IF(IFERROR(IF(VLOOKUP(K13,Materialen!$A$2:$I$39,9,0)="",0,VLOOKUP(K13,Materialen!$A$2:$I$39,9,0)),0)=0,1,0))+IF(M13="",0,IF(IFERROR(IF(VLOOKUP(M13,Materialen!$A$2:$I$39,9,0)="",0,VLOOKUP(M13,Materialen!$A$2:$I$39,9,0)),0)=0,1,0)))>0,"aankoopprijs ontbreekt",IF(AND(G13="",K13="",N(T13)=0,N(R13)=0),"kost invullen (arbeid/overig)","OK"))
... A25: 24 | B25: Impression sur panneau FOREX de 5mm | C25: > 25 m² | D25: m² | E25: 5 | F25: 43 | G25: M33 | H25: 1 | O25: =IF(G25="","",IF(IFERROR(VLOOKUP(G25,Materialen!$A$2:$I$39,4,0),"")="plaat",Instellingen!$B$4,Instellingen!$B$3)) | P25: =ROUND(N(H25)*IFERROR(IF(VLOOKUP(G25,Materialen!$A$2:$I$39,9,0)="",0,VLOOKUP(G25,Materialen!$A$2:$I$39,9,0)),0)*(1+N(O25))+N(J25)*IFERROR(IF(VLOOKUP(I25,Materialen!$A$2:$I$39,9,0)="",0,VLOOKUP(I25,Materialen!$A$2:$I$39,9,0)),0)*(1+N(O25))+N(L25)*IFERROR(IF(VLOOKUP(K25,Materialen!$A$2:$I$39,9,0)="",0,VLOOKUP(K25,Materialen!$A$2:$I$39,9,0)),0)+N(N25)*IFERROR(IF(VLOOKUP(M25,Materialen!$A$2:$I$39,9,0)="",0,VLOOKUP(M25,Materialen!$A$2:$I$39,9,0)),0),2) | Q25: =IF(G25="",0,IF(IFERROR(VLOOKUP(G25,Materialen!$A$2:$I$39,5,0),"N")="J",ROUND(N(H25)*(1+N(O25))*Instellingen!$B$8,2),0)) | S25: =ROUND(N(R25)/60*Instellingen!$B$9,2) | U25: =P25+Q25+S25+N(T25) | V25: =IF(AC25<>"OK","",F25-U25) | W25: =IF(OR(F25=0,AC25<>"OK"),"",V25/F25) | X25: =IF(N(H25)>0,F25/H25,"") | Y25: =IF(N(H25)>0,IFERROR(IF(VLOOKUP(G25,Materialen!$A$2:$I$39,9,0)="",0,VLOOKUP(G25,Materialen!$A$2:$I$39,9,0)),0),"") | Z25: =ROUND(E25*F25,2) | AA25: =IF(AC25<>"OK","",ROUND(E25*U25,2)) | AB25: =IF(AC25<>"OK","",Z25-AA25) | AC25: =IF((IF(G25="",0,IF(IFERROR(IF(VLOOKUP(G25,Materialen!$A$2:$I$39,9,0)="",0,VLOOKUP(G25,Materialen!$A$2:$I$39,9,0)),0)=0,1,0))+IF(I25="",0,IF(IFERROR(IF(VLOOKUP(I25,Materialen!$A$2:$I$39,9,0)="",0,VLOOKUP(I25,Materialen!$A$2:$I$39,9,0)),0)=0,1,0))+IF(K25="",0,IF(IFERROR(IF(VLOOKUP(K25,Materialen!$A$2:$I$39,9,0)="",0,VLOOKUP(K25,Materialen!$A$2:$I$39,9,0)),0)=0,1,0))+IF(M25="",0,IF(IFERROR(IF(VLOOKUP(M25,Materialen!$A$2:$I$39,9,0)="",0,VLOOKUP(M25,Materialen!$A$2:$I$39,9,0)),0)=0,1,0)))>0,"aankoopprijs ontbreekt",IF(AND(G25="",K25="",N(T25)=0,N(R25)=0),"kost invullen (arbeid/overig)","OK"))
A26: 25 | B26: Impression sur panneaux FOREX de 2mm | C26: 10 cartels | D26: 10 cartels | E26: 5 | F26: 35 | G26: M31 | H26: 0.3108 | O26: =IF(G26="","",IF(IFERROR(VLOOKUP(G26,Materialen!$A$2:$I$39,4,0),"")="plaat",Instellingen!$B$4,Instellingen!$B$3)) | P26: =ROUND(N(H26)*IFERROR(IF(VLOOKUP(G26,Materialen!$A$2:$I$39,9,0)="",0,VLOOKUP(G26,Materialen!$A$2:$I$39,9,0)),0)*(1+N(O26))+N(J26)*IFERROR(IF(VLOOKUP(I26,Materialen!$A$2:$I$39,9,0)="",0,VLOOKUP(I26,Materialen!$A$2:$I$39,9,0)),0)*(1+N(O26))+N(L26)*IFERROR(IF(VLOOKUP(K26,Materialen!$A$2:$I$39,9,0)="",0,VLOOKUP(K26,Materialen!$A$2:$I$39,9,0)),0)+N(N26)*IFERROR(IF(VLOOKUP(M26,Materialen!$A$2:$I$39,9,0)="",0,VLOOKUP(M26,Materialen!$A$2:$I$39,9,0)),0),2) | Q26: =IF(G26="",0,IF(IFERROR(VLOOKUP(G26,Materialen!$A$2:$I$39,5,0),"N")="J",ROUND(N(H26)*(1+N(O26))*Instellingen!$B$8,2),0)) | S26: =ROUND(N(R26)/60*Instellingen!$B$9,2) | U26: =P26+Q26+S26+N(T26) | V26: =IF(AC26<>"OK","",F26-U26) | W26: =IF(OR(F26=0,AC26<>"OK"),"",V26/F26) | X26: =IF(N(H26)>0,F26/H26,"") | Y26: =IF(N(H26)>0,IFERROR(IF(VLOOKUP(G26,Materialen!$A$2:$I$39,9,0)="",0,VLOOKUP(G26,Materialen!$A$2:$I$39,9,0)),0),"") | Z26: =ROUND(E26*F26,2) | AA26: =IF(AC26<>"OK","",ROUND(E26*U26,2)) | AB26: =IF(AC26<>"OK","",Z26-AA26) | AC26: =IF((IF(G26="",0,IF(IFERROR(IF(VLOOKUP(G26,Materialen!$A$2:$I$39,9,0)="",0,VLOOKUP(G26,Materialen!$A$2:$I$39,9,0)),0)=0,1,0))+IF(I26="",0,IF(IFERROR(IF(VLOOKUP(I26,Materialen!$A$2:$I$39,9,0)="",0,VLOOKUP(I26,Materialen!$A$2:$I$39,9,0)),0)=0,1,0))+IF(K26="",0,IF(IFERROR(IF(VLOOKUP(K26,Materialen!$A$2:$I$39,9,0)="",0,VLOOKUP(K26,Materialen!$A$2:$I$39,9,0)),0)=0,1,0))+IF(M26="",0,IF(IFERROR(IF(VLOOKUP(M26,Materialen!$A$2:$I$39,9,0)="",0,VLOOKUP(M26,Materialen!$A$2:$I$39,9,0)),0)=0,1,0)))>0,"aankoopprijs ontbreekt",IF(AND(G26="",K26="",N(T26)=0,N(R26)=0),"kost invullen (arbeid/overig)","OK")) | AD26: 10 x A5
A27: 26 | B27: Impression sur panneaux FOREX de 2mm | C27: 25 cartels | D27: 25 cartels | E27: 5 | F27: 70 | G27: M31 | H27: 0.777 | O27: =IF(G27="","",IF(IFERROR(VLOOKUP(G27,Materialen!$A$2:$I$39,4,0),"")="plaat",Instellingen!$B$4,Instellingen!$B$3)) | P27: =ROUND(N(H27)*IFERROR(IF(VLOOKUP(G27,Materialen!$A$2:$I$39,9,0)="",0,VLOOKUP(G27,Materialen!$A$2:$I$39,9,0)),0)*(1+N(O27))+N(J27)*IFERROR(IF(VLOOKUP(I27,Materialen!$A$2:$I$39,9,0)="",0,VLOOKUP(I27,Materialen!$A$2:$I$39,9,0)),0)*(1+N(O27))+N(L27)*IFERROR(IF(VLOOKUP(K27,Materialen!$A$2:$I$39,9,0)="",0,VLOOKUP(K27,Materialen!$A$2:$I$39,9,0)),0)+N(N27)*IFERROR(IF(VLOOKUP(M27,Materialen!$A$2:$I$39,9,0)="",0,VLOOKUP(M27,Materialen!$A$2:$I$39,9,0)),0),2) | Q27: =IF(G27="",0,IF(IFERROR(VLOOKUP(G27,Materialen!$A$2:$I$39,5,0),"N")="J",ROUND(N(H27)*(1+N(O27))*Instellingen!$B$8,2),0)) | S27: =ROUND(N(R27)/60*Instellingen!$B$9,2) | U27: =P27+Q27+S27+N(T27) | V27: =IF(AC27<>"OK","",F27-U27) | W27: =IF(OR(F27=0,AC27<>"OK"),"",V27/F27) | X27: =IF(N(H27)>0,F27/H27,"") | Y27: =IF(N(H27)>0,IFERROR(IF(VLOOKUP(G27,Materialen!$A$2:$I$39,9,0)="",0,VLOOKUP(G27,Materialen!$A$2:$I$39,9,0)),0),"") | Z27: =ROUND(E27*F27,2) | AA27: =IF(AC27<>"OK","",ROUND(E27*U27,2)) | AB27: =IF(AC27<>"OK","",Z27-AA27) | AC27: =IF((IF(G27="",0,IF(IFERROR(IF(VLOOKUP(G27,Materialen!$A$2:$I$39,9,0)="",0,VLOOKUP(G27,Materialen!$A$2:$I$39,9,0)),0)=0,1,0))+IF(I27="",0,IF(IFERROR(IF(VLOOKUP(I27,Materialen!$A$2:$I$39,9,0)="",0,VLOOKUP(I27,Materialen!$A$2:$I$39,9,0)),0)=0,1,0))+IF(K27="",0,IF(IFERROR(IF(VLOOKUP(K27,Materialen!$A$2:$I$39,9,0)="",0,VLOOKUP(K27,Materialen!$A$2:$I$39,9,0)),0)=0,1,0))+IF(M27="",0,IF(IFERROR(IF(VLOOKUP(M27,Materialen!$A$2:$I$39,9,0)="",0,VLOOKUP(M27,Materialen!$A$2:$I$39,9,0)),0)=0,1,0)))>0,"aankoopprijs ontbreekt",IF(AND(G27="",K27="",N(T27)=0,N(R27)=0),"kost invullen (arbeid/overig)","OK")) | AD27: 25 x A5
A28: 27 | B28: Impression sur panneaux FOREX de 2mm | C28: 50 cartels | D28: 50 cartels | E28: 5 | F28: 120 | G28: M31 | H28: 1.554 | O28: =IF(G28="","",IF(IFERROR(VLOOKUP(G28,Materialen!$A$2:$I$39,4,0),"")="plaat",Instellingen!$B$4,Instellingen!$B$3)) | P28: =ROUND(N(H28)*IFERROR(IF(VLOOKUP(G28,Materialen!$A$2:$I$39,9,0)="",0,VLOOKUP(G28,Materialen!$A$2:$I$39,9,0)),0)*(1+N(O28))+N(J28)*IFERROR(IF(VLOOKUP(I28,Materialen!$A$2:$I$39,9,0)="",0,VLOOKUP(I28,Materialen!$A$2:$I$39,9,0)),0)*(1+N(O28))+N(L28)*IFERROR(IF(VLOOKUP(K28,Materialen!$A$2:$I$39,9,0)="",0,VLOOKUP(K28,Materialen!$A$2:$I$39,9,0)),0)+N(N28)*IFERROR(IF(VLOOKUP(M28,Materialen!$A$2:$I$39,9,0)="",0,VLOOKUP(M28,Materialen!$A$2:$I$39,9,0)),0),2) | Q28: =IF(G28="",0,IF(IFERROR(VLOOKUP(G28,Materialen!$A$2:$I$39,5,0),"N")="J",ROUND(N(H28)*(1+N(O28))*Instellingen!$B$8,2),0)) | S28: =ROUND(N(R28)/60*Instellingen!$B$9,2) | U28: =P28+Q28+S28+N(T28) | V28: =IF(AC28<>"OK","",F28-U28) | W28: =IF(OR(F28=0,AC28<>"OK"),"",V28/F28) | X28: =IF(N(H28)>0,F28/H28,"") | Y28: =IF(N(H28)>0,IFERROR(IF(VLOOKUP(G28,Materialen!$A$2:$I$39,9,0)="",0,VLOOKUP(G28,Materialen!$A$2:$I$39,9,0)),0),"") | Z28: =ROUND(E28*F28,2) | AA28: =IF(AC28<>"OK","",ROUND(E28*U28,2)) | AB28: =IF(AC28<>"OK","",Z28-AA28) | AC28: =IF((IF(G28="",0,IF(IFERROR(IF(VLOOKUP(G28,Materialen!$A$2:$I$39,9,0)="",0,VLOOKUP(G28,Materialen!$A$2:$I$39,9,0)),0)=0,1,0))+IF(I28="",0,IF(IFERROR(IF(VLOOKUP(I28,Materialen!$A$2:$I$39,9,0)="",0,VLOOKUP(I28,Materialen!$A$2:$I$39,9,0)),0)=0,1,0))+IF(K28="",0,IF(IFERROR(IF(VLOOKUP(K28,Materialen!$A$2:$I$39,9,0)="",0,VLOOKUP(K28,Materialen!$A$2:$I$39,9,0)),0)=0,1,0))+IF(M28="",0,IF(IFERROR(IF(VLOOKUP(M28,Materialen!$A$2:$I$39,9,0)="",0,VLOOKUP(M28,Materialen!$A$2:$I$39,9,0)),0)=0,1,0)))>0,"aankoopprijs ontbreekt",IF(AND(G28="",K28="",N(T28)=0,N(R28)=0),"kost invullen (arbeid/overig)","OK")) | AD28: 50 x A5
A29: 28 | B29: Impression sur panneaux FOREX de 2mm | C29: 100 cartels | D29: 100 cartels | E29: 5 | F29: 210 | G29: M31 | H29: 3.108 | O29: =IF(G29="","",IF(IFERROR(VLOOKUP(G29,Materialen!$A$2:$I$39,4,0),"")="plaat",Instellingen!$B$4,Instellingen!$B$3)) | P29: =ROUND(N(H29)*IFERROR(IF(VLOOKUP(G29,Materialen!$A$2:$I$39,9,0)="",0,VLOOKUP(G29,Materialen!$A$2:$I$39,9,0)),0)*(1+N(O29))+N(J29)*IFERROR(IF(VLOOKUP(I29,Materialen!$A$2:$I$39,9,0)="",0,VLOOKUP(I29,Materialen!$A$2:$I$39,9,0)),0)*(1+N(O29))+N(L29)*IFERROR(IF(VLOOKUP(K29,Materialen!$A$2:$I$39,9,0)="",0,VLOOKUP(K29,Materialen!$A$2:$I$39,9,0)),0)+N(N29)*IFERROR(IF(VLOOKUP(M29,Materialen!$A$2:$I$39,9,0)="",0,VLOOKUP(M29,Materialen!$A$2:$I$39,9,0)),0),2) | Q29: =IF(G29="",0,IF(IFERROR(VLOOKUP(G29,Materialen!$A$2:$I$39,5,0),"N")="J",ROUND(N(H29)*(1+N(O29))*Instellingen!$B$8,2),0)) | S29: =ROUND(N(R29)/60*Instellingen!$B$9,2) | U29: =P29+Q29+S29+N(T29) | V29: =IF(AC29<>"OK","",F29-U29) | W29: =IF(OR(F29=0,AC29<>"OK"),"",V29/F29) | X29: =IF(N(H29)>0,F29/H29,"") | Y29: =IF(N(H29)>0,IFERROR(IF(VLOOKUP(G29,Materialen!$A$2:$I$39,9,0)="",0,VLOOKUP(G29,Materialen!$A$2:$I$39,9,0)),0),"") | Z29: =ROUND(E29*F29,2) | AA29: =IF(AC29<>"OK","",ROUND(E29*U29,2)) | AB29: =IF(AC29<>"OK","",Z29-AA29) | AC29: =IF((IF(G29="",0,IF(IFERROR(IF(VLOOKUP(G29,Materialen!$A$2:$I$39,9,0)="",0,VLOOKUP(G29,Materialen!$A$2:$I$39,9,0)),0)=0,1,0))+IF(I29="",0,IF(IFERROR(IF(VLOOKUP(I29,Materialen!$A$2:$I$39,9,0)="",0,VLOOKUP(I29,Materialen!$A$2:$I$39,9,0)),0)=0,1,0))+IF(K29="",0,IF(IFERROR(IF(VLOOKUP(K29,Materialen!$A$2:$I$39,9,0)="",0,VLOOKUP(K29,Materialen!$A$2:$I$39,9,0)),0)=0,1,0))+IF(M29="",0,IF(IFERROR(IF(VLOOKUP(M29,Materialen!$A$2:$I$39,9,0)="",0,VLOOKUP(M29,Materialen!$A$2:$I$39,9,0)),0)=0,1,0)))>0,"aankoopprijs ontbreekt",IF(AND(G29="",K29="",N(T29)=0,N(R29)=0),"kost invullen (arbeid/overig)","OK")) | AD29: 100 x A5
A30: 29 | B30: Impression sur panneaux FOREX de 2mm | C30: 150 cartels | D30: 150 cartels | E30: 5 | F30: 290 | G30: M31 | H30: 4.662 | O30: =IF(G30="","",IF(IFERROR(VLOOKUP(G30,Materialen!$A$2:$I$39,4,0),"")="plaat",Instellingen!$B$4,Instellingen!$B$3)) | P30: =ROUND(N(H30)*IFERROR(IF(VLOOKUP(G30,Materialen!$A$2:$I$39,9,0)="",0,VLOOKUP(G30,Materialen!$A$2:$I$39,9,0)),0)*(1+N(O30))+N(J30)*IFERROR(IF(VLOOKUP(I30,Materialen!$A$2:$I$39,9,0)="",0,VLOOKUP(I30,Materialen!$A$2:$I$39,9,0)),0)*(1+N(O30))+N(L30)*IFERROR(IF(VLOOKUP(K30,Materialen!$A$2:$I$39,9,0)="",0,VLOOKUP(K30,Materialen!$A$2:$I$39,9,0)),0)+N(N30)*IFERROR(IF(VLOOKUP(M30,Materialen!$A$2:$I$39,9,0)="",0,VLOOKUP(M30,Materialen!$A$2:$I$39,9,0)),0),2) | Q30: =IF(G30="",0,IF(IFERROR(VLOOKUP(G30,Materialen!$A$2:$I$39,5,0),"N")="J",ROUND(N(H30)*(1+N(O30))*Instellingen!$B$8,2),0)) | S30: =ROUND(N(R30)/60*Instellingen!$B$9,2) | U30: =P30+Q30+S30+N(T30) | V30: =IF(AC30<>"OK","",F30-U30) | W30: =IF(OR(F30=0,AC30<>"OK"),"",V30/F30) | X30: =IF(N(H30)>0,F30/H30,"") | Y30: =IF(N(H30)>0,IFERROR(IF(VLOOKUP(G30,Materialen!$A$2:$I$39,9,0)="",0,VLOOKUP(G30,Materialen!$A$2:$I$39,9,0)),0),"") | Z30: =ROUND(E30*F30,2) | AA30: =IF(AC30<>"OK","",ROUND(E30*U30,2)) | AB30: =IF(AC30<>"OK","",Z30-AA30) | AC30: =IF((IF(G30="",0,IF(IFERROR(IF(VLOOKUP(G30,Materialen!$A$2:$I$39,9,0)="",0,VLOOKUP(G30,Materialen!$A$2:$I$39,9,0)),0)=0,1,0))+IF(I30="",0,IF(IFERROR(IF(VLOOKUP(I30,Materialen!$A$2:$I$39,9,0)="",0,VLOOKUP(I30,Materialen!$A$2:$I$39,9,0)),0)=0,1,0))+IF(K30="",0,IF(IFERROR(IF(VLOOKUP(K30,Materialen!$A$2:$I$39,9,0)="",0,VLOOKUP(K30,Materialen!$A$2:$I$39,9,0)),0)=0,1,0))+IF(M30="",0,IF(IFERROR(IF(VLOOKUP(M30,Materialen!$A$2:$I$39,9,0)="",0,VLOOKUP(M30,Materialen!$A$2:$I$39,9,0)),0)=0,1,0)))>0,"aankoopprijs ontbreekt",IF(AND(G30="",K30="",N(T30)=0,N(R30)=0),"kost invullen (arbeid/overig)","OK")) | AD30: 150 x A5
A31: 30 | B31: Impression sur panneaux FOREX de 2mm | C31: 200 cartels | D31: 200 cartels | E31: 5 | F31: 360 | G31: M31 | H31: 6.216 | O31: =IF(G31="","",IF(IFERROR(VLOOKUP(G31,Materialen!$A$2:$I$39,4,0),"")="plaat",Instellingen!$B$4,Instellingen!$B$3)) | P31: =ROUND(N(H31)*IFERROR(IF(VLOOKUP(G31,Materialen!$A$2:$I$39,9,0)="",0,VLOOKUP(G31,Materialen!$A$2:$I$39,9,0)),0)*(1+N(O31))+N(J31)*IFERROR(IF(VLOOKUP(I31,Materialen!$A$2:$I$39,9,0)="",0,VLOOKUP(I31,Materialen!$A$2:$I$39,9,0)),0)*(1+N(O31))+N(L31)*IFERROR(IF(VLOOKUP(K31,Materialen!$A$2:$I$39,9,0)="",0,VLOOKUP(K31,Materialen!$A$2:$I$39,9,0)),0)+N(N31)*IFERROR(IF(VLOOKUP(M31,Materialen!$A$2:$I$39,9,0)="",0,VLOOKUP(M31,Materialen!$A$2:$I$39,9,0)),0),2) | Q31: =IF(G31="",0,IF(IFERROR(VLOOKUP(G31,Materialen!$A$2:$I$39,5,0),"N")="J",ROUND(N(H31)*(1+N(O31))*Instellingen!$B$8,2),0)) | S31: =ROUND(N(R31)/60*Instellingen!$B$9,2) | U31: =P31+Q31+S31+N(T31) | V31: =IF(AC31<>"OK","",F31-U31) | W31: =IF(OR(F31=0,AC31<>"OK"),"",V31/F31) | X31: =IF(N(H31)>0,F31/H31,"") | Y31: =IF(N(H31)>0,IFERROR(IF(VLOOKUP(G31,Materialen!$A$2:$I$39,9,0)="",0,VLOOKUP(G31,Materialen!$A$2:$I$39,9,0)),0),"") | Z31: =ROUND(E31*F31,2) | AA31: =IF(AC31<>"OK","",ROUND(E31*U31,2)) | AB31: =IF(AC31<>"OK","",Z31-AA31) | AC31: =IF((IF(G31="",0,IF(IFERROR(IF(VLOOKUP(G31,Materialen!$A$2:$I$39,9,0)="",0,VLOOKUP(G31,Materialen!$A$2:$I$39,9,0)),0)=0,1,0))+IF(I31="",0,IF(IFERROR(IF(VLOOKUP(I31,Materialen!$A$2:$I$39,9,0)="",0,VLOOKUP(I31,Materialen!$A$2:$I$39,9,0)),0)=0,1,0))+IF(K31="",0,IF(IFERROR(IF(VLOOKUP(K31,Materialen!$A$2:$I$39,9,0)="",0,VLOOKUP(K31,Materialen!$A$2:$I$39,9,0)),0)=0,1,0))+IF(M31="",0,IF(IFERROR(IF(VLOOKUP(M31,Materialen!$A$2:$I$39,9,0)="",0,VLOOKUP(M31,Materialen!$A$2:$I$39,9,0)),0)=0,1,0)))>0,"aankoopprijs ontbreekt",IF(AND(G31="",K31="",N(T31)=0,N(R31)=0),"kost invullen (arbeid/overig)","OK")) | AD31: 200 x A5
A32: 31 | B32: Impression sur panneaux FOREX de 2mm | C32: 10 quantités supplémentaires | D32: 10 quantités supplémentaires | E32: 5 | F32: 15 | G32: M31 | H32: 0.3108 | O32: =IF(G32="","",IF(IFERROR(VLOOKUP(G32,Materialen!$A$2:$I$39,4,0),"")="plaat",Instellingen!$B$4,Instellingen!$B$3)) | P32: =ROUND(N(H32)*IFERROR(IF(VLOOKUP(G32,Materialen!$A$2:$I$39,9,0)="",0,VLOOKUP(G32,Materialen!$A$2:$I$39,9,0)),0)*(1+N(O32))+N(J32)*IFERROR(IF(VLOOKUP(I32,Materialen!$A$2:$I$39,9,0)="",0,VLOOKUP(I32,Materialen!$A$2:$I$39,9,0)),0)*(1+N(O32))+N(L32)*IFERROR(IF(VLOOKUP(K32,Materialen!$A$2:$I$39,9,0)="",0,VLOOKUP(K32,Materialen!$A$2:$I$39,9,0)),0)+N(N32)*IFERROR(IF(VLOOKUP(M32,Materialen!$A$2:$I$39,9,0)="",0,VLOOKUP(M32,Materialen!$A$2:$I$39,9,0)),0),2) | Q32: =IF(G32="",0,IF(IFERROR(VLOOKUP(G32,Materialen!$A$2:$I$39,5,0),"N")="J",ROUND(N(H32)*(1+N(O32))*Instellingen!$B$8,2),0)) | S32: =ROUND(N(R32)/60*Instellingen!$B$9,2) | U32: =P32+Q32+S32+N(T32) | V32: =IF(AC32<>"OK","",F32-U32) | W32: =IF(OR(F32=0,AC32<>"OK"),"",V32/F32) | X32: =IF(N(H32)>0,F32/H32,"") | Y32: =IF(N(H32)>0,IFERROR(IF(VLOOKUP(G32,Materialen!$A$2:$I$39,9,0)="",0,VLOOKUP(G32,Materialen!$A$2:$I$39,9,0)),0),"") | Z32: =ROUND(E32*F32,2) | AA32: =IF(AC32<>"OK","",ROUND(E32*U32,2)) | AB32: =IF(AC32<>"OK","",Z32-AA32) | AC32: =IF((IF(G32="",0,IF(IFERROR(IF(VLOOKUP(G32,Materialen!$A$2:$I$39,9,0)="",0,VLOOKUP(G32,Materialen!$A$2:$I$39,9,0)),0)=0,1,0))+IF(I32="",0,IF(IFERROR(IF(VLOOKUP(I32,Materialen!$A$2:$I$39,9,0)="",0,VLOOKUP(I32,Materialen!$A$2:$I$39,9,0)),0)=0,1,0))+IF(K32="",0,IF(IFERROR(IF(VLOOKUP(K32,Materialen!$A$2:$I$39,9,0)="",0,VLOOKUP(K32,Materialen!$A$2:$I$39,9,0)),0)=0,1,0))+IF(M32="",0,IF(IFERROR(IF(VLOOKUP(M32,Materialen!$A$2:$I$39,9,0)="",0,VLOOKUP(M32,Materialen!$A$2:$I$39,9,0)),0)=0,1,0)))>0,"aankoopprijs ontbreekt",IF(AND(G32="",K32="",N(T32)=0,N(R32)=0),"kost invullen (arbeid/overig)","OK")) | AD32: 10 x A5
A33: 32 | B33: Impression sur panneau FOREX de 3mm | C33: 10 cartels | D33: 10 cartels | E33: 5 | F33: 40 | G33: M32 | H33: 0.3108 | O33: =IF(G33="","",IF(IFERROR(VLOOKUP(G33,Materialen!$A$2:$I$39,4,0),"")="plaat",Instellingen!$B$4,Instellingen!$B$3)) | P33: =ROUND(N(H33)*IFERROR(IF(VLOOKUP(G33,Materialen!$A$2:$I$39,9,0)="",0,VLOOKUP(G33,Materialen!$A$2:$I$39,9,0)),0)*(1+N(O33))+N(J33)*IFERROR(IF(VLOOKUP(I33,Materialen!$A$2:$I$39,9,0)="",0,VLOOKUP(I33,Materialen!$A$2:$I$39,9,0)),0)*(1+N(O33))+N(L33)*IFERROR(IF(VLOOKUP(K33,Materialen!$A$2:$I$39,9,0)="",0,VLOOKUP(K33,Materialen!$A$2:$I$39,9,0)),0)+N(N33)*IFERROR(IF(VLOOKUP(M33,Materialen!$A$2:$I$39,9,0)="",0,VLOOKUP(M33,Materialen!$A$2:$I$39,9,0)),0),2) | Q33: =IF(G33="",0,IF(IFERROR(VLOOKUP(G33,Materialen!$A$2:$I$39,5,0),"N")="J",ROUND(N(H33)*(1+N(O33))*Instellingen!$B$8,2),0)) | S33: =ROUND(N(R33)/60*Instellingen!$B$9,2) | U33: =P33+Q33+S33+N(T33) | V33: =IF(AC33<>"OK","",F33-U33) | W33: =IF(OR(F33=0,AC33<>"OK"),"",V33/F33) | X33: =IF(N(H33)>0,F33/H33,"") | Y33: =IF(N(H33)>0,IFERROR(IF(VLOOKUP(G33,Materialen!$A$2:$I$39,9,0)="",0,VLOOKUP(G33,Materialen!$A$2:$I$39,9,0)),0),"") | Z33: =ROUND(E33*F33,2) | AA33: =IF(AC33<>"OK","",ROUND(E33*U33,2)) | AB33: =IF(AC33<>"OK","",Z33-AA33) | AC33: =IF((IF(G33="",0,IF(IFERROR(IF(VLOOKUP(G33,Materialen!$A$2:$I$39,9,0)="",0,VLOOKUP(G33,Materialen!$A$2:$I$39,9,0)),0)=0,1,0))+IF(I33="",0,IF(IFERROR(IF(VLOOKUP(I33,Materialen!$A$2:$I$39,9,0)="",0,VLOOKUP(I33,Materialen!$A$2:$I$39,9,0)),0)=0,1,0))+IF(K33="",0,IF(IFERROR(IF(VLOOKUP(K33,Materialen!$A$2:$I$39,9,0)="",0,VLOOKUP(K33,Materialen!$A$2:$I$39,9,0)),0)=0,1,0))+IF(M33="",0,IF(IFERROR(IF(VLOOKUP(M33,Materialen!$A$2:$I$39,9,0)="",0,VLOOKUP(M33,Materialen!$A$2:$I$39,9,0)),0)=0,1,0)))>0,"aankoopprijs ontbreekt",IF(AND(G33="",K33="",N(T33)=0,N(R33)=0),"kost invullen (arbeid/overig)","OK")) | AD33: 10 x A5
A34: 33 | B34: Impression sur panneau FOREX de 3mm | C34: 25 cartels | D34: 25 cartels | E34: 5 | F34: 80 | G34: M32 | H34: 0.777 | O34: =IF(G34="","",IF(IFERROR(VLOOKUP(G34,Materialen!$A$2:$I$39,4,0),"")="plaat",Instellingen!$B$4,Instellingen!$B$3)) | P34: =ROUND(N(H34)*IFERROR(IF(VLOOKUP(G34,Materialen!$A$2:$I$39,9,0)="",0,VLOOKUP(G34,Materialen!$A$2:$I$39,9,0)),0)*(1+N(O34))+N(J34)*IFERROR(IF(VLOOKUP(I34,Materialen!$A$2:$I$39,9,0)="",0,VLOOKUP(I34,Materialen!$A$2:$I$39,9,0)),0)*(1+N(O34))+N(L34)*IFERROR(IF(VLOOKUP(K34,Materialen!$A$2:$I$39,9,0)="",0,VLOOKUP(K34,Materialen!$A$2:$I$39,9,0)),0)+N(N34)*IFERROR(IF(VLOOKUP(M34,Materialen!$A$2:$I$39,9,0)="",0,VLOOKUP(M34,Materialen!$A$2:$I$39,9,0)),0),2) | Q34: =IF(G34="",0,IF(IFERROR(VLOOKUP(G34,Materialen!$A$2:$I$39,5,0),"N")="J",ROUND(N(H34)*(1+N(O34))*Instellingen!$B$8,2),0)) | S34: =ROUND(N(R34)/60*Instellingen!$B$9,2) | U34: =P34+Q34+S34+N(T34) | V34: =IF(AC34<>"OK","",F34-U34) | W34: =IF(OR(F34=0,AC34<>"OK"),"",V34/F34) | X34: =IF(N(H34)>0,F34/H34,"") | Y34: =IF(N(H34)>0,IFERROR(IF(VLOOKUP(G34,Materialen!$A$2:$I$39,9,0)="",0,VLOOKUP(G34,Materialen!$A$2:$I$39,9,0)),0),"") | Z34: =ROUND(E34*F34,2) | AA34: =IF(AC34<>"OK","",ROUND(E34*U34,2)) | AB34: =IF(AC34<>"OK","",Z34-AA34) | AC34: =IF((IF(G34="",0,IF(IFERROR(IF(VLOOKUP(G34,Materialen!$A$2:$I$39,9,0)="",0,VLOOKUP(G34,Materialen!$A$2:$I$39,9,0)),0)=0,1,0))+IF(I34="",0,IF(IFERROR(IF(VLOOKUP(I34,Materialen!$A$2:$I$39,9,0)="",0,VLOOKUP(I34,Materialen!$A$2:$I$39,9,0)),0)=0,1,0))+IF(K34="",0,IF(IFERROR(IF(VLOOKUP(K34,Materialen!$A$2:$I$39,9,0)="",0,VLOOKUP(K34,Materialen!$A$2:$I$39,9,0)),0)=0,1,0))+IF(M34="",0,IF(IFERROR(IF(VLOOKUP(M34,Materialen!$A$2:$I$39,9,0)="",0,VLOOKUP(M34,Materialen!$A$2:$I$39,9,0)),0)=0,1,0)))>0,"aankoopprijs ontbreekt",IF(AND(G34="",K34="",N(T34)=0,N(R34)=0),"kost invullen (arbeid/overig)","OK")) | AD34: 25 x A5
A35: 34 | B35: Impression sur panneau FOREX de 3mm | C35: 50 cartels | D35: 50 cartels | E35: 5 | F35: 135 | G35: M32 | H35: 1.554 | O35: =IF(G35="","",IF(IFERROR(VLOOKUP(G35,Materialen!$A$2:$I$39,4,0),"")="plaat",Instellingen!$B$4,Instellingen!$B$3)) | P35: =ROUND(N(H35)*IFERROR(IF(VLOOKUP(G35,Materialen!$A$2:$I$39,9,0)="",0,VLOOKUP(G35,Materialen!$A$2:$I$39,9,0)),0)*(1+N(O35))+N(J35)*IFERROR(IF(VLOOKUP(I35,Materialen!$A$2:$I$39,9,0)="",0,VLOOKUP(I35,Materialen!$A$2:$I$39,9,0)),0)*(1+N(O35))+N(L35)*IFERROR(IF(VLOOKUP(K35,Materialen!$A$2:$I$39,9,0)="",0,VLOOKUP(K35,Materialen!$A$2:$I$39,9,0)),0)+N(N35)*IFERROR(IF(VLOOKUP(M35,Materialen!$A$2:$I$39,9,0)="",0,VLOOKUP(M35,Materialen!$A$2:$I$39,9,0)),0),2) | Q35: =IF(G35="",0,IF(IFERROR(VLOOKUP(G35,Materialen!$A$2:$I$39,5,0),"N")="J",ROUND(N(H35)*(1+N(O35))*Instellingen!$B$8,2),0)) | S35: =ROUND(N(R35)/60*Instellingen!$B$9,2) | U35: =P35+Q35+S35+N(T35) | V35: =IF(AC35<>"OK","",F35-U35) | W35: =IF(OR(F35=0,AC35<>"OK"),"",V35/F35) | X35: =IF(N(H35)>0,F35/H35,"") | Y35: =IF(N(H35)>0,IFERROR(IF(VLOOKUP(G35,Materialen!$A$2:$I$39,9,0)="",0,VLOOKUP(G35,Materialen!$A$2:$I$39,9,0)),0),"") | Z35: =ROUND(E35*F35,2) | AA35: =IF(AC35<>"OK","",ROUND(E35*U35,2)) | AB35: =IF(AC35<>"OK","",Z35-AA35) | AC35: =IF((IF(G35="",0,IF(IFERROR(IF(VLOOKUP(G35,Materialen!$A$2:$I$39,9,0)="",0,VLOOKUP(G35,Materialen!$A$2:$I$39,9,0)),0)=0,1,0))+IF(I35="",0,IF(IFERROR(IF(VLOOKUP(I35,Materialen!$A$2:$I$39,9,0)="",0,VLOOKUP(I35,Materialen!$A$2:$I$39,9,0)),0)=0,1,0))+IF(K35="",0,IF(IFERROR(IF(VLOOKUP(K35,Materialen!$A$2:$I$39,9,0)="",0,VLOOKUP(K35,Materialen!$A$2:$I$39,9,0)),0)=0,1,0))+IF(M35="",0,IF(IFERROR(IF(VLOOKUP(M35,Materialen!$A$2:$I$39,9,0)="",0,VLOOKUP(M35,Materialen!$A$2:$I$39,9,0)),0)=0,1,0)))>0,"aankoopprijs ontbreekt",IF(AND(G35="",K35="",N(T35)=0,N(R35)=0),"kost invullen (arbeid/overig)","OK")) | AD35: 50 x A5
A36: 35 | B36: Impression sur panneau FOREX de 3mm | C36: 100 cartels | D36: 100 cartels | E36: 5 | F36: 240 | G36: M32 | H36: 3.108 | O36: =IF(G36="","",IF(IFERROR(VLOOKUP(G36,Materialen!$A$2:$I$39,4,0),"")="plaat",Instellingen!$B$4,Instellingen!$B$3)) | P36: =ROUND(N(H36)*IFERROR(IF(VLOOKUP(G36,Materialen!$A$2:$I$39,9,0)="",0,VLOOKUP(G36,Materialen!$A$2:$I$39,9,0)),0)*(1+N(O36))+N(J36)*IFERROR(IF(VLOOKUP(I36,Materialen!$A$2:$I$39,9,0)="",0,VLOOKUP(I36,Materialen!$A$2:$I$39,9,0)),0)*(1+N(O36))+N(L36)*IFERROR(IF(VLOOKUP(K36,Materialen!$A$2:$I$39,9,0)="",0,VLOOKUP(K36,Materialen!$A$2:$I$39,9,0)),0)+N(N36)*IFERROR(IF(VLOOKUP(M36,Materialen!$A$2:$I$39,9,0)="",0,VLOOKUP(M36,Materialen!$A$2:$I$39,9,0)),0),2) | Q36: =IF(G36="",0,IF(IFERROR(VLOOKUP(G36,Materialen!$A$2:$I$39,5,0),"N")="J",ROUND(N(H36)*(1+N(O36))*Instellingen!$B$8,2),0)) | S36: =ROUND(N(R36)/60*Instellingen!$B$9,2) | U36: =P36+Q36+S36+N(T36) | V36: =IF(AC36<>"OK","",F36-U36) | W36: =IF(OR(F36=0,AC36<>"OK"),"",V36/F36) | X36: =IF(N(H36)>0,F36/H36,"") | Y36: =IF(N(H36)>0,IFERROR(IF(VLOOKUP(G36,Materialen!$A$2:$I$39,9,0)="",0,VLOOKUP(G36,Materialen!$A$2:$I$39,9,0)),0),"") | Z36: =ROUND(E36*F36,2) | AA36: =IF(AC36<>"OK","",ROUND(E36*U36,2)) | AB36: =IF(AC36<>"OK","",Z36-AA36) | AC36: =IF((IF(G36="",0,IF(IFERROR(IF(VLOOKUP(G36,Materialen!$A$2:$I$39,9,0)="",0,VLOOKUP(G36,Materialen!$A$2:$I$39,9,0)),0)=0,1,0))+IF(I36="",0,IF(IFERROR(IF(VLOOKUP(I36,Materialen!$A$2:$I$39,9,0)="",0,VLOOKUP(I36,Materialen!$A$2:$I$39,9,0)),0)=0,1,0))+IF(K36="",0,IF(IFERROR(IF(VLOOKUP(K36,Materialen!$A$2:$I$39,9,0)="",0,VLOOKUP(K36,Materialen!$A$2:$I$39,9,0)),0)=0,1,0))+IF(M36="",0,IF(IFERROR(IF(VLOOKUP(M36,Materialen!$A$2:$I$39,9,0)="",0,VLOOKUP(M36,Materialen!$A$2:$I$39,9,0)),0)=0,1,0)))>0,"aankoopprijs ontbreekt",IF(AND(G36="",K36="",N(T36)=0,N(R36)=0),"kost invullen (arbeid/overig)","OK")) | AD36: 100 x A5
A37: 36 | B37: Impression sur panneau FOREX de 3mm | C37: 150 cartels | D37: 150 cartels | E37: 5 | F37: 330 | G37: M32 | H37: 4.662 | O37: =IF(G37="","",IF(IFERROR(VLOOKUP(G37,Materialen!$A$2:$I$39,4,0),"")="plaat",Instellingen!$B$4,Instellingen!$B$3)) | P37: =ROUND(N(H37)*IFERROR(IF(VLOOKUP(G37,Materialen!$A$2:$I$39,9,0)="",0,VLOOKUP(G37,Materialen!$A$2:$I$39,9,0)),0)*(1+N(O37))+N(J37)*IFERROR(IF(VLOOKUP(I37,Materialen!$A$2:$I$39,9,0)="",0,VLOOKUP(I37,Materialen!$A$2:$I$39,9,0)),0)*(1+N(O37))+N(L37)*IFERROR(IF(VLOOKUP(K37,Materialen!$A$2:$I$39,9,0)="",0,VLOOKUP(K37,Materialen!$A$2:$I$39,9,0)),0)+N(N37)*IFERROR(IF(VLOOKUP(M37,Materialen!$A$2:$I$39,9,0)="",0,VLOOKUP(M37,Materialen!$A$2:$I$39,9,0)),0),2) | Q37: =IF(G37="",0,IF(IFERROR(VLOOKUP(G37,Materialen!$A$2:$I$39,5,0),"N")="J",ROUND(N(H37)*(1+N(O37))*Instellingen!$B$8,2),0)) | S37: =ROUND(N(R37)/60*Instellingen!$B$9,2) | U37: =P37+Q37+S37+N(T37) | V37: =IF(AC37<>"OK","",F37-U37) | W37: =IF(OR(F37=0,AC37<>"OK"),"",V37/F37) | X37: =IF(N(H37)>0,F37/H37,"") | Y37: =IF(N(H37)>0,IFERROR(IF(VLOOKUP(G37,Materialen!$A$2:$I$39,9,0)="",0,VLOOKUP(G37,Materialen!$A$2:$I$39,9,0)),0),"") | Z37: =ROUND(E37*F37,2) | AA37: =IF(AC37<>"OK","",ROUND(E37*U37,2)) | AB37: =IF(AC37<>"OK","",Z37-AA37) | AC37: =IF((IF(G37="",0,IF(IFERROR(IF(VLOOKUP(G37,Materialen!$A$2:$I$39,9,0)="",0,VLOOKUP(G37,Materialen!$A$2:$I$39,9,0)),0)=0,1,0))+IF(I37="",0,IF(IFERROR(IF(VLOOKUP(I37,Materialen!$A$2:$I$39,9,0)="",0,VLOOKUP(I37,Materialen!$A$2:$I$39,9,0)),0)=0,1,0))+IF(K37="",0,IF(IFERROR(IF(VLOOKUP(K37,Materialen!$A$2:$I$39,9,0)="",0,VLOOKUP(K37,Materialen!$A$2:$I$39,9,0)),0)=0,1,0))+IF(M37="",0,IF(IFERROR(IF(VLOOKUP(M37,Materialen!$A$2:$I$39,9,0)="",0,VLOOKUP(M37,Materialen!$A$2:$I$39,9,0)),0)=0,1,0)))>0,"aankoopprijs ontbreekt",IF(AND(G37="",K37="",N(T37)=0,N(R37)=0),"kost invullen (arbeid/overig)","OK")) | AD37: 150 x A5
... A46: 45 | B46: Impression sur panneau FOREX de 5mm | C46: 10 quantités supplémentaires | D46: 10 quantités supplémentaires | E46: 5 | F46: 21 | G46: M33 | H46: 0.3108 | O46: =IF(G46="","",IF(IFERROR(VLOOKUP(G46,Materialen!$A$2:$I$39,4,0),"")="plaat",Instellingen!$B$4,Instellingen!$B$3)) | P46: =ROUND(N(H46)*IFERROR(IF(VLOOKUP(G46,Materialen!$A$2:$I$39,9,0)="",0,VLOOKUP(G46,Materialen!$A$2:$I$39,9,0)),0)*(1+N(O46))+N(J46)*IFERROR(IF(VLOOKUP(I46,Materialen!$A$2:$I$39,9,0)="",0,VLOOKUP(I46,Materialen!$A$2:$I$39,9,0)),0)*(1+N(O46))+N(L46)*IFERROR(IF(VLOOKUP(K46,Materialen!$A$2:$I$39,9,0)="",0,VLOOKUP(K46,Materialen!$A$2:$I$39,9,0)),0)+N(N46)*IFERROR(IF(VLOOKUP(M46,Materialen!$A$2:$I$39,9,0)="",0,VLOOKUP(M46,Materialen!$A$2:$I$39,9,0)),0),2) | Q46: =IF(G46="",0,IF(IFERROR(VLOOKUP(G46,Materialen!$A$2:$I$39,5,0),"N")="J",ROUND(N(H46)*(1+N(O46))*Instellingen!$B$8,2),0)) | S46: =ROUND(N(R46)/60*Instellingen!$B$9,2) | U46: =P46+Q46+S46+N(T46) | V46: =IF(AC46<>"OK","",F46-U46) | W46: =IF(OR(F46=0,AC46<>"OK"),"",V46/F46) | X46: =IF(N(H46)>0,F46/H46,"") | Y46: =IF(N(H46)>0,IFERROR(IF(VLOOKUP(G46,Materialen!$A$2:$I$39,9,0)="",0,VLOOKUP(G46,Materialen!$A$2:$I$39,9,0)),0),"") | Z46: =ROUND(E46*F46,2) | AA46: =IF(AC46<>"OK","",ROUND(E46*U46,2)) | AB46: =IF(AC46<>"OK","",Z46-AA46) | AC46: =IF((IF(G46="",0,IF(IFERROR(IF(VLOOKUP(G46,Materialen!$A$2:$I$39,9,0)="",0,VLOOKUP(G46,Materialen!$A$2:$I$39,9,0)),0)=0,1,0))+IF(I46="",0,IF(IFERROR(IF(VLOOKUP(I46,Materialen!$A$2:$I$39,9,0)="",0,VLOOKUP(I46,Materialen!$A$2:$I$39,9,0)),0)=0,1,0))+IF(K46="",0,IF(IFERROR(IF(VLOOKUP(K46,Materialen!$A$2:$I$39,9,0)="",0,VLOOKUP(K46,Materialen!$A$2:$I$39,9,0)),0)=0,1,0))+IF(M46="",0,IF(IFERROR(IF(VLOOKUP(M46,Materialen!$A$2:$I$39,9,0)="",0,VLOOKUP(M46,Materialen!$A$2:$I$39,9,0)),0)=0,1,0)))>0,"aankoopprijs ontbreekt",IF(AND(G46="",K46="",N(T46)=0,N(R46)=0),"kost invullen (arbeid/overig)","OK")) | AD46: 10 x A5
A47: 46 | B47: Impression quadrichromie sur PLEXI mat opalin 2mm | C47: >= A2 et <= 1 m² | D47: m² | E47: 5 | F47: 140 | G47: M34 | H47: 1 | O47: =IF(G47="","",IF(IFERROR(VLOOKUP(G47,Materialen!$A$2:$I$39,4,0),"")="plaat",Instellingen!$B$4,Instellingen!$B$3)) | P47: =ROUND(N(H47)*IFERROR(IF(VLOOKUP(G47,Materialen!$A$2:$I$39,9,0)="",0,VLOOKUP(G47,Materialen!$A$2:$I$39,9,0)),0)*(1+N(O47))+N(J47)*IFERROR(IF(VLOOKUP(I47,Materialen!$A$2:$I$39,9,0)="",0,VLOOKUP(I47,Materialen!$A$2:$I$39,9,0)),0)*(1+N(O47))+N(L47)*IFERROR(IF(VLOOKUP(K47,Materialen!$A$2:$I$39,9,0)="",0,VLOOKUP(K47,Materialen!$A$2:$I$39,9,0)),0)+N(N47)*IFERROR(IF(VLOOKUP(M47,Materialen!$A$2:$I$39,9,0)="",0,VLOOKUP(M47,Materialen!$A$2:$I$39,9,0)),0),2) | Q47: =IF(G47="",0,IF(IFERROR(VLOOKUP(G47,Materialen!$A$2:$I$39,5,0),"N")="J",ROUND(N(H47)*(1+N(O47))*Instellingen!$B$8,2),0)) | S47: =ROUND(N(R47)/60*Instellingen!$B$9,2) | U47: =P47+Q47+S47+N(T47) | V47: =IF(AC47<>"OK","",F47-U47) | W47: =IF(OR(F47=0,AC47<>"OK"),"",V47/F47) | X47: =IF(N(H47)>0,F47/H47,"") | Y47: =IF(N(H47)>0,IFERROR(IF(VLOOKUP(G47,Materialen!$A$2:$I$39,9,0)="",0,VLOOKUP(G47,Materialen!$A$2:$I$39,9,0)),0),"") | Z47: =ROUND(E47*F47,2) | AA47: =IF(AC47<>"OK","",ROUND(E47*U47,2)) | AB47: =IF(AC47<>"OK","",Z47-AA47) | AC47: =IF((IF(G47="",0,IF(IFERROR(IF(VLOOKUP(G47,Materialen!$A$2:$I$39,9,0)="",0,VLOOKUP(G47,Materialen!$A$2:$I$39,9,0)),0)=0,1,0))+IF(I47="",0,IF(IFERROR(IF(VLOOKUP(I47,Materialen!$A$2:$I$39,9,0)="",0,VLOOKUP(I47,Materialen!$A$2:$I$39,9,0)),0)=0,1,0))+IF(K47="",0,IF(IFERROR(IF(VLOOKUP(K47,Materialen!$A$2:$I$39,9,0)="",0,VLOOKUP(K47,Materialen!$A$2:$I$39,9,0)),0)=0,1,0))+IF(M47="",0,IF(IFERROR(IF(VLOOKUP(M47,Materialen!$A$2:$I$39,9,0)="",0,VLOOKUP(M47,Materialen!$A$2:$I$39,9,0)),0)=0,1,0)))>0,"aankoopprijs ontbreekt",IF(AND(G47="",K47="",N(T47)=0,N(R47)=0),"kost invullen (arbeid/overig)","OK"))
A48: 47 | B48: Impression quadrichromie sur PLEXI mat opalin 2mm | C48: > 1 m² et <= 2 m² | D48: m² | E48: 5 | F48: 125 | G48: M34 | H48: 1 | O48: =IF(G48="","",IF(IFERROR(VLOOKUP(G48,Materialen!$A$2:$I$39,4,0),"")="plaat",Instellingen!$B$4,Instellingen!$B$3)) | P48: =ROUND(N(H48)*IFERROR(IF(VLOOKUP(G48,Materialen!$A$2:$I$39,9,0)="",0,VLOOKUP(G48,Materialen!$A$2:$I$39,9,0)),0)*(1+N(O48))+N(J48)*IFERROR(IF(VLOOKUP(I48,Materialen!$A$2:$I$39,9,0)="",0,VLOOKUP(I48,Materialen!$A$2:$I$39,9,0)),0)*(1+N(O48))+N(L48)*IFERROR(IF(VLOOKUP(K48,Materialen!$A$2:$I$39,9,0)="",0,VLOOKUP(K48,Materialen!$A$2:$I$39,9,0)),0)+N(N48)*IFERROR(IF(VLOOKUP(M48,Materialen!$A$2:$I$39,9,0)="",0,VLOOKUP(M48,Materialen!$A$2:$I$39,9,0)),0),2) | Q48: =IF(G48="",0,IF(IFERROR(VLOOKUP(G48,Materialen!$A$2:$I$39,5,0),"N")="J",ROUND(N(H48)*(1+N(O48))*Instellingen!$B$8,2),0)) | S48: =ROUND(N(R48)/60*Instellingen!$B$9,2) | U48: =P48+Q48+S48+N(T48) | V48: =IF(AC48<>"OK","",F48-U48) | W48: =IF(OR(F48=0,AC48<>"OK"),"",V48/F48) | X48: =IF(N(H48)>0,F48/H48,"") | Y48: =IF(N(H48)>0,IFERROR(IF(VLOOKUP(G48,Materialen!$A$2:$I$39,9,0)="",0,VLOOKUP(G48,Materialen!$A$2:$I$39,9,0)),0),"") | Z48: =ROUND(E48*F48,2) | AA48: =IF(AC48<>"OK","",ROUND(E48*U48,2)) | AB48: =IF(AC48<>"OK","",Z48-AA48) | AC48: =IF((IF(G48="",0,IF(IFERROR(IF(VLOOKUP(G48,Materialen!$A$2:$I$39,9,0)="",0,VLOOKUP(G48,Materialen!$A$2:$I$39,9,0)),0)=0,1,0))+IF(I48="",0,IF(IFERROR(IF(VLOOKUP(I48,Materialen!$A$2:$I$39,9,0)="",0,VLOOKUP(I48,Materialen!$A$2:$I$39,9,0)),0)=0,1,0))+IF(K48="",0,IF(IFERROR(IF(VLOOKUP(K48,Materialen!$A$2:$I$39,9,0)="",0,VLOOKUP(K48,Materialen!$A$2:$I$39,9,0)),0)=0,1,0))+IF(M48="",0,IF(IFERROR(IF(VLOOKUP(M48,Materialen!$A$2:$I$39,9,0)="",0,VLOOKUP(M48,Materialen!$A$2:$I$39,9,0)),0)=0,1,0)))>0,"aankoopprijs ontbreekt",IF(AND(G48="",K48="",N(T48)=0,N(R48)=0),"kost invullen (arbeid/overig)","OK"))
A49: 48 | B49: Impression quadrichromie sur PLEXI mat opalin 2mm | C49: > 2 m² et <= 5 m² | D49: m² | E49: 5 | F49: 115 | G49: M34 | H49: 1 | O49: =IF(G49="","",IF(IFERROR(VLOOKUP(G49,Materialen!$A$2:$I$39,4,0),"")="plaat",Instellingen!$B$4,Instellingen!$B$3)) | P49: =ROUND(N(H49)*IFERROR(IF(VLOOKUP(G49,Materialen!$A$2:$I$39,9,0)="",0,VLOOKUP(G49,Materialen!$A$2:$I$39,9,0)),0)*(1+N(O49))+N(J49)*IFERROR(IF(VLOOKUP(I49,Materialen!$A$2:$I$39,9,0)="",0,VLOOKUP(I49,Materialen!$A$2:$I$39,9,0)),0)*(1+N(O49))+N(L49)*IFERROR(IF(VLOOKUP(K49,Materialen!$A$2:$I$39,9,0)="",0,VLOOKUP(K49,Materialen!$A$2:$I$39,9,0)),0)+N(N49)*IFERROR(IF(VLOOKUP(M49,Materialen!$A$2:$I$39,9,0)="",0,VLOOKUP(M49,Materialen!$A$2:$I$39,9,0)),0),2) | Q49: =IF(G49="",0,IF(IFERROR(VLOOKUP(G49,Materialen!$A$2:$I$39,5,0),"N")="J",ROUND(N(H49)*(1+N(O49))*Instellingen!$B$8,2),0)) | S49: =ROUND(N(R49)/60*Instellingen!$B$9,2) | U49: =P49+Q49+S49+N(T49) | V49: =IF(AC49<>"OK","",F49-U49) | W49: =IF(OR(F49=0,AC49<>"OK"),"",V49/F49) | X49: =IF(N(H49)>0,F49/H49,"") | Y49: =IF(N(H49)>0,IFERROR(IF(VLOOKUP(G49,Materialen!$A$2:$I$39,9,0)="",0,VLOOKUP(G49,Materialen!$A$2:$I$39,9,0)),0),"") | Z49: =ROUND(E49*F49,2) | AA49: =IF(AC49<>"OK","",ROUND(E49*U49,2)) | AB49: =IF(AC49<>"OK","",Z49-AA49) | AC49: =IF((IF(G49="",0,IF(IFERROR(IF(VLOOKUP(G49,Materialen!$A$2:$I$39,9,0)="",0,VLOOKUP(G49,Materialen!$A$2:$I$39,9,0)),0)=0,1,0))+IF(I49="",0,IF(IFERROR(IF(VLOOKUP(I49,Materialen!$A$2:$I$39,9,0)="",0,VLOOKUP(I49,Materialen!$A$2:$I$39,9,0)),0)=0,1,0))+IF(K49="",0,IF(IFERROR(IF(VLOOKUP(K49,Materialen!$A$2:$I$39,9,0)="",0,VLOOKUP(K49,Materialen!$A$2:$I$39,9,0)),0)=0,1,0))+IF(M49="",0,IF(IFERROR(IF(VLOOKUP(M49,Materialen!$A$2:$I$39,9,0)="",0,VLOOKUP(M49,Materialen!$A$2:$I$39,9,0)),0)=0,1,0)))>0,"aankoopprijs ontbreekt",IF(AND(G49="",K49="",N(T49)=0,N(R49)=0),"kost invullen (arbeid/overig)","OK"))
A50: 49 | B50: Impression quadrichromie sur PLEXI mat opalin 2mm | C50: > 5 m² et <= 10 m² | D50: m² | E50: 5 | F50: 105 | G50: M34 | H50: 1 | O50: =IF(G50="","",IF(IFERROR(VLOOKUP(G50,Materialen!$A$2:$I$39,4,0),"")="plaat",Instellingen!$B$4,Instellingen!$B$3)) | P50: =ROUND(N(H50)*IFERROR(IF(VLOOKUP(G50,Materialen!$A$2:$I$39,9,0)="",0,VLOOKUP(G50,Materialen!$A$2:$I$39,9,0)),0)*(1+N(O50))+N(J50)*IFERROR(IF(VLOOKUP(I50,Materialen!$A$2:$I$39,9,0)="",0,VLOOKUP(I50,Materialen!$A$2:$I$39,9,0)),0)*(1+N(O50))+N(L50)*IFERROR(IF(VLOOKUP(K50,Materialen!$A$2:$I$39,9,0)="",0,VLOOKUP(K50,Materialen!$A$2:$I$39,9,0)),0)+N(N50)*IFERROR(IF(VLOOKUP(M50,Materialen!$A$2:$I$39,9,0)="",0,VLOOKUP(M50,Materialen!$A$2:$I$39,9,0)),0),2) | Q50: =IF(G50="",0,IF(IFERROR(VLOOKUP(G50,Materialen!$A$2:$I$39,5,0),"N")="J",ROUND(N(H50)*(1+N(O50))*Instellingen!$B$8,2),0)) | S50: =ROUND(N(R50)/60*Instellingen!$B$9,2) | U50: =P50+Q50+S50+N(T50) | V50: =IF(AC50<>"OK","",F50-U50) | W50: =IF(OR(F50=0,AC50<>"OK"),"",V50/F50) | X50: =IF(N(H50)>0,F50/H50,"") | Y50: =IF(N(H50)>0,IFERROR(IF(VLOOKUP(G50,Materialen!$A$2:$I$39,9,0)="",0,VLOOKUP(G50,Materialen!$A$2:$I$39,9,0)),0),"") | Z50: =ROUND(E50*F50,2) | AA50: =IF(AC50<>"OK","",ROUND(E50*U50,2)) | AB50: =IF(AC50<>"OK","",Z50-AA50) | AC50: =IF((IF(G50="",0,IF(IFERROR(IF(VLOOKUP(G50,Materialen!$A$2:$I$39,9,0)="",0,VLOOKUP(G50,Materialen!$A$2:$I$39,9,0)),0)=0,1,0))+IF(I50="",0,IF(IFERROR(IF(VLOOKUP(I50,Materialen!$A$2:$I$39,9,0)="",0,VLOOKUP(I50,Materialen!$A$2:$I$39,9,0)),0)=0,1,0))+IF(K50="",0,IF(IFERROR(IF(VLOOKUP(K50,Materialen!$A$2:$I$39,9,0)="",0,VLOOKUP(K50,Materialen!$A$2:$I$39,9,0)),0)=0,1,0))+IF(M50="",0,IF(IFERROR(IF(VLOOKUP(M50,Materialen!$A$2:$I$39,9,0)="",0,VLOOKUP(M50,Materialen!$A$2:$I$39,9,0)),0)=0,1,0)))>0,"aankoopprijs ontbreekt",IF(AND(G50="",K50="",N(T50)=0,N(R50)=0),"kost invullen (arbeid/overig)","OK"))
A51: 50 | B51: Impression quadrichromie sur PLEXI mat opalin 2mm | C51: > 10 m² et <= 25 m² | D51: m² | E51: 5 | F51: 95 | G51: M34 | H51: 1 | O51: =IF(G51="","",IF(IFERROR(VLOOKUP(G51,Materialen!$A$2:$I$39,4,0),"")="plaat",Instellingen!$B$4,Instellingen!$B$3)) | P51: =ROUND(N(H51)*IFERROR(IF(VLOOKUP(G51,Materialen!$A$2:$I$39,9,0)="",0,VLOOKUP(G51,Materialen!$A$2:$I$39,9,0)),0)*(1+N(O51))+N(J51)*IFERROR(IF(VLOOKUP(I51,Materialen!$A$2:$I$39,9,0)="",0,VLOOKUP(I51,Materialen!$A$2:$I$39,9,0)),0)*(1+N(O51))+N(L51)*IFERROR(IF(VLOOKUP(K51,Materialen!$A$2:$I$39,9,0)="",0,VLOOKUP(K51,Materialen!$A$2:$I$39,9,0)),0)+N(N51)*IFERROR(IF(VLOOKUP(M51,Materialen!$A$2:$I$39,9,0)="",0,VLOOKUP(M51,Materialen!$A$2:$I$39,9,0)),0),2) | Q51: =IF(G51="",0,IF(IFERROR(VLOOKUP(G51,Materialen!$A$2:$I$39,5,0),"N")="J",ROUND(N(H51)*(1+N(O51))*Instellingen!$B$8,2),0)) | S51: =ROUND(N(R51)/60*Instellingen!$B$9,2) | U51: =P51+Q51+S51+N(T51) | V51: =IF(AC51<>"OK","",F51-U51) | W51: =IF(OR(F51=0,AC51<>"OK"),"",V51/F51) | X51: =IF(N(H51)>0,F51/H51,"") | Y51: =IF(N(H51)>0,IFERROR(IF(VLOOKUP(G51,Materialen!$A$2:$I$39,9,0)="",0,VLOOKUP(G51,Materialen!$A$2:$I$39,9,0)),0),"") | Z51: =ROUND(E51*F51,2) | AA51: =IF(AC51<>"OK","",ROUND(E51*U51,2)) | AB51: =IF(AC51<>"OK","",Z51-AA51) | AC51: =IF((IF(G51="",0,IF(IFERROR(IF(VLOOKUP(G51,Materialen!$A$2:$I$39,9,0)="",0,VLOOKUP(G51,Materialen!$A$2:$I$39,9,0)),0)=0,1,0))+IF(I51="",0,IF(IFERROR(IF(VLOOKUP(I51,Materialen!$A$2:$I$39,9,0)="",0,VLOOKUP(I51,Materialen!$A$2:$I$39,9,0)),0)=0,1,0))+IF(K51="",0,IF(IFERROR(IF(VLOOKUP(K51,Materialen!$A$2:$I$39,9,0)="",0,VLOOKUP(K51,Materialen!$A$2:$I$39,9,0)),0)=0,1,0))+IF(M51="",0,IF(IFERROR(IF(VLOOKUP(M51,Materialen!$A$2:$I$39,9,0)="",0,VLOOKUP(M51,Materialen!$A$2:$I$39,9,0)),0)=0,1,0)))>0,"aankoopprijs ontbreekt",IF(AND(G51="",K51="",N(T51)=0,N(R51)=0),"kost invullen (arbeid/overig)","OK"))
A52: 51 | B52: Impression quadrichromie sur PLEXI mat opalin 2mm | C52: > 25 m² | D52: m² | E52: 5 | F52: 90 | G52: M34 | H52: 1 | O52: =IF(G52="","",IF(IFERROR(VLOOKUP(G52,Materialen!$A$2:$I$39,4,0),"")="plaat",Instellingen!$B$4,Instellingen!$B$3)) | P52: =ROUND(N(H52)*IFERROR(IF(VLOOKUP(G52,Materialen!$A$2:$I$39,9,0)="",0,VLOOKUP(G52,Materialen!$A$2:$I$39,9,0)),0)*(1+N(O52))+N(J52)*IFERROR(IF(VLOOKUP(I52,Materialen!$A$2:$I$39,9,0)="",0,VLOOKUP(I52,Materialen!$A$2:$I$39,9,0)),0)*(1+N(O52))+N(L52)*IFERROR(IF(VLOOKUP(K52,Materialen!$A$2:$I$39,9,0)="",0,VLOOKUP(K52,Materialen!$A$2:$I$39,9,0)),0)+N(N52)*IFERROR(IF(VLOOKUP(M52,Materialen!$A$2:$I$39,9,0)="",0,VLOOKUP(M52,Materialen!$A$2:$I$39,9,0)),0),2) | Q52: =IF(G52="",0,IF(IFERROR(VLOOKUP(G52,Materialen!$A$2:$I$39,5,0),"N")="J",ROUND(N(H52)*(1+N(O52))*Instellingen!$B$8,2),0)) | S52: =ROUND(N(R52)/60*Instellingen!$B$9,2) | U52: =P52+Q52+S52+N(T52) | V52: =IF(AC52<>"OK","",F52-U52) | W52: =IF(OR(F52=0,AC52<>"OK"),"",V52/F52) | X52: =IF(N(H52)>0,F52/H52,"") | Y52: =IF(N(H52)>0,IFERROR(IF(VLOOKUP(G52,Materialen!$A$2:$I$39,9,0)="",0,VLOOKUP(G52,Materialen!$A$2:$I$39,9,0)),0),"") | Z52: =ROUND(E52*F52,2) | AA52: =IF(AC52<>"OK","",ROUND(E52*U52,2)) | AB52: =IF(AC52<>"OK","",Z52-AA52) | AC52: =IF((IF(G52="",0,IF(IFERROR(IF(VLOOKUP(G52,Materialen!$A$2:$I$39,9,0)="",0,VLOOKUP(G52,Materialen!$A$2:$I$39,9,0)),0)=0,1,0))+IF(I52="",0,IF(IFERROR(IF(VLOOKUP(I52,Materialen!$A$2:$I$39,9,0)="",0,VLOOKUP(I52,Materialen!$A$2:$I$39,9,0)),0)=0,1,0))+IF(K52="",0,IF(IFERROR(IF(VLOOKUP(K52,Materialen!$A$2:$I$39,9,0)="",0,VLOOKUP(K52,Materialen!$A$2:$I$39,9,0)),0)=0,1,0))+IF(M52="",0,IF(IFERROR(IF(VLOOKUP(M52,Materialen!$A$2:$I$39,9,0)="",0,VLOOKUP(M52,Materialen!$A$2:$I$39,9,0)),0)=0,1,0)))>0,"aankoopprijs ontbreekt",IF(AND(G52="",K52="",N(T52)=0,N(R52)=0),"kost invullen (arbeid/overig)","OK"))
A53: 52 | B53: Impression quadrichromie sur PLEXI mat opalin 3mm | C53: >= A2 et <= 1 m² | D53: m² | E53: 5 | F53: 155 | G53: M35 | H53: 1 | O53: =IF(G53="","",IF(IFERROR(VLOOKUP(G53,Materialen!$A$2:$I$39,4,0),"")="plaat",Instellingen!$B$4,Instellingen!$B$3)) | P53: =ROUND(N(H53)*IFERROR(IF(VLOOKUP(G53,Materialen!$A$2:$I$39,9,0)="",0,VLOOKUP(G53,Materialen!$A$2:$I$39,9,0)),0)*(1+N(O53))+N(J53)*IFERROR(IF(VLOOKUP(I53,Materialen!$A$2:$I$39,9,0)="",0,VLOOKUP(I53,Materialen!$A$2:$I$39,9,0)),0)*(1+N(O53))+N(L53)*IFERROR(IF(VLOOKUP(K53,Materialen!$A$2:$I$39,9,0)="",0,VLOOKUP(K53,Materialen!$A$2:$I$39,9,0)),0)+N(N53)*IFERROR(IF(VLOOKUP(M53,Materialen!$A$2:$I$39,9,0)="",0,VLOOKUP(M53,Materialen!$A$2:$I$39,9,0)),0),2) | Q53: =IF(G53="",0,IF(IFERROR(VLOOKUP(G53,Materialen!$A$2:$I$39,5,0),"N")="J",ROUND(N(H53)*(1+N(O53))*Instellingen!$B$8,2),0)) | S53: =ROUND(N(R53)/60*Instellingen!$B$9,2) | U53: =P53+Q53+S53+N(T53) | V53: =IF(AC53<>"OK","",F53-U53) | W53: =IF(OR(F53=0,AC53<>"OK"),"",V53/F53) | X53: =IF(N(H53)>0,F53/H53,"") | Y53: =IF(N(H53)>0,IFERROR(IF(VLOOKUP(G53,Materialen!$A$2:$I$39,9,0)="",0,VLOOKUP(G53,Materialen!$A$2:$I$39,9,0)),0),"") | Z53: =ROUND(E53*F53,2) | AA53: =IF(AC53<>"OK","",ROUND(E53*U53,2)) | AB53: =IF(AC53<>"OK","",Z53-AA53) | AC53: =IF((IF(G53="",0,IF(IFERROR(IF(VLOOKUP(G53,Materialen!$A$2:$I$39,9,0)="",0,VLOOKUP(G53,Materialen!$A$2:$I$39,9,0)),0)=0,1,0))+IF(I53="",0,IF(IFERROR(IF(VLOOKUP(I53,Materialen!$A$2:$I$39,9,0)="",0,VLOOKUP(I53,Materialen!$A$2:$I$39,9,0)),0)=0,1,0))+IF(K53="",0,IF(IFERROR(IF(VLOOKUP(K53,Materialen!$A$2:$I$39,9,0)="",0,VLOOKUP(K53,Materialen!$A$2:$I$39,9,0)),0)=0,1,0))+IF(M53="",0,IF(IFERROR(IF(VLOOKUP(M53,Materialen!$A$2:$I$39,9,0)="",0,VLOOKUP(M53,Materialen!$A$2:$I$39,9,0)),0)=0,1,0)))>0,"aankoopprijs ontbreekt",IF(AND(G53="",K53="",N(T53)=0,N(R53)=0),"kost invullen (arbeid/overig)","OK"))
A54: 53 | B54: Impression quadrichromie sur PLEXI mat opalin 3mm | C54: > 1 m² et <= 2 m² | D54: m² | E54: 5 | F54: 138 | G54: M35 | H54: 1 | O54: =IF(G54="","",IF(IFERROR(VLOOKUP(G54,Materialen!$A$2:$I$39,4,0),"")="plaat",Instellingen!$B$4,Instellingen!$B$3)) | P54: =ROUND(N(H54)*IFERROR(IF(VLOOKUP(G54,Materialen!$A$2:$I$39,9,0)="",0,VLOOKUP(G54,Materialen!$A$2:$I$39,9,0)),0)*(1+N(O54))+N(J54)*IFERROR(IF(VLOOKUP(I54,Materialen!$A$2:$I$39,9,0)="",0,VLOOKUP(I54,Materialen!$A$2:$I$39,9,0)),0)*(1+N(O54))+N(L54)*IFERROR(IF(VLOOKUP(K54,Materialen!$A$2:$I$39,9,0)="",0,VLOOKUP(K54,Materialen!$A$2:$I$39,9,0)),0)+N(N54)*IFERROR(IF(VLOOKUP(M54,Materialen!$A$2:$I$39,9,0)="",0,VLOOKUP(M54,Materialen!$A$2:$I$39,9,0)),0),2) | Q54: =IF(G54="",0,IF(IFERROR(VLOOKUP(G54,Materialen!$A$2:$I$39,5,0),"N")="J",ROUND(N(H54)*(1+N(O54))*Instellingen!$B$8,2),0)) | S54: =ROUND(N(R54)/60*Instellingen!$B$9,2) | U54: =P54+Q54+S54+N(T54) | V54: =IF(AC54<>"OK","",F54-U54) | W54: =IF(OR(F54=0,AC54<>"OK"),"",V54/F54) | X54: =IF(N(H54)>0,F54/H54,"") | Y54: =IF(N(H54)>0,IFERROR(IF(VLOOKUP(G54,Materialen!$A$2:$I$39,9,0)="",0,VLOOKUP(G54,Materialen!$A$2:$I$39,9,0)),0),"") | Z54: =ROUND(E54*F54,2) | AA54: =IF(AC54<>"OK","",ROUND(E54*U54,2)) | AB54: =IF(AC54<>"OK","",Z54-AA54) | AC54: =IF((IF(G54="",0,IF(IFERROR(IF(VLOOKUP(G54,Materialen!$A$2:$I$39,9,0)="",0,VLOOKUP(G54,Materialen!$A$2:$I$39,9,0)),0)=0,1,0))+IF(I54="",0,IF(IFERROR(IF(VLOOKUP(I54,Materialen!$A$2:$I$39,9,0)="",0,VLOOKUP(I54,Materialen!$A$2:$I$39,9,0)),0)=0,1,0))+IF(K54="",0,IF(IFERROR(IF(VLOOKUP(K54,Materialen!$A$2:$I$39,9,0)="",0,VLOOKUP(K54,Materialen!$A$2:$I$39,9,0)),0)=0,1,0))+IF(M54="",0,IF(IFERROR(IF(VLOOKUP(M54,Materialen!$A$2:$I$39,9,0)="",0,VLOOKUP(M54,Materialen!$A$2:$I$39,9,0)),0)=0,1,0)))>0,"aankoopprijs ontbreekt",IF(AND(G54="",K54="",N(T54)=0,N(R54)=0),"kost invullen (arbeid/overig)","OK"))
A55: 54 | B55: Impression quadrichromie sur PLEXI mat opalin 3mm | C55: > 2 m² et <= 5 m² | D55: m² | E55: 5 | F55: 126 | G55: M35 | H55: 1 | O55: =IF(G55="","",IF(IFERROR(VLOOKUP(G55,Materialen!$A$2:$I$39,4,0),"")="plaat",Instellingen!$B$4,Instellingen!$B$3)) | P55: =ROUND(N(H55)*IFERROR(IF(VLOOKUP(G55,Materialen!$A$2:$I$39,9,0)="",0,VLOOKUP(G55,Materialen!$A$2:$I$39,9,0)),0)*(1+N(O55))+N(J55)*IFERROR(IF(VLOOKUP(I55,Materialen!$A$2:$I$39,9,0)="",0,VLOOKUP(I55,Materialen!$A$2:$I$39,9,0)),0)*(1+N(O55))+N(L55)*IFERROR(IF(VLOOKUP(K55,Materialen!$A$2:$I$39,9,0)="",0,VLOOKUP(K55,Materialen!$A$2:$I$39,9,0)),0)+N(N55)*IFERROR(IF(VLOOKUP(M55,Materialen!$A$2:$I$39,9,0)="",0,VLOOKUP(M55,Materialen!$A$2:$I$39,9,0)),0),2) | Q55: =IF(G55="",0,IF(IFERROR(VLOOKUP(G55,Materialen!$A$2:$I$39,5,0),"N")="J",ROUND(N(H55)*(1+N(O55))*Instellingen!$B$8,2),0)) | S55: =ROUND(N(R55)/60*Instellingen!$B$9,2) | U55: =P55+Q55+S55+N(T55) | V55: =IF(AC55<>"OK","",F55-U55) | W55: =IF(OR(F55=0,AC55<>"OK"),"",V55/F55) | X55: =IF(N(H55)>0,F55/H55,"") | Y55: =IF(N(H55)>0,IFERROR(IF(VLOOKUP(G55,Materialen!$A$2:$I$39,9,0)="",0,VLOOKUP(G55,Materialen!$A$2:$I$39,9,0)),0),"") | Z55: =ROUND(E55*F55,2) | AA55: =IF(AC55<>"OK","",ROUND(E55*U55,2)) | AB55: =IF(AC55<>"OK","",Z55-AA55) | AC55: =IF((IF(G55="",0,IF(IFERROR(IF(VLOOKUP(G55,Materialen!$A$2:$I$39,9,0)="",0,VLOOKUP(G55,Materialen!$A$2:$I$39,9,0)),0)=0,1,0))+IF(I55="",0,IF(IFERROR(IF(VLOOKUP(I55,Materialen!$A$2:$I$39,9,0)="",0,VLOOKUP(I55,Materialen!$A$2:$I$39,9,0)),0)=0,1,0))+IF(K55="",0,IF(IFERROR(IF(VLOOKUP(K55,Materialen!$A$2:$I$39,9,0)="",0,VLOOKUP(K55,Materialen!$A$2:$I$39,9,0)),0)=0,1,0))+IF(M55="",0,IF(IFERROR(IF(VLOOKUP(M55,Materialen!$A$2:$I$39,9,0)="",0,VLOOKUP(M55,Materialen!$A$2:$I$39,9,0)),0)=0,1,0)))>0,"aankoopprijs ontbreekt",IF(AND(G55="",K55="",N(T55)=0,N(R55)=0),"kost invullen (arbeid/overig)","OK"))
A56: 55 | B56: Impression quadrichromie sur PLEXI mat opalin 3mm | C56: > 5 m² et <= 10 m² | D56: m² | E56: 5 | F56: 115 | G56: M35 | H56: 1 | O56: =IF(G56="","",IF(IFERROR(VLOOKUP(G56,Materialen!$A$2:$I$39,4,0),"")="plaat",Instellingen!$B$4,Instellingen!$B$3)) | P56: =ROUND(N(H56)*IFERROR(IF(VLOOKUP(G56,Materialen!$A$2:$I$39,9,0)="",0,VLOOKUP(G56,Materialen!$A$2:$I$39,9,0)),0)*(1+N(O56))+N(J56)*IFERROR(IF(VLOOKUP(I56,Materialen!$A$2:$I$39,9,0)="",0,VLOOKUP(I56,Materialen!$A$2:$I$39,9,0)),0)*(1+N(O56))+N(L56)*IFERROR(IF(VLOOKUP(K56,Materialen!$A$2:$I$39,9,0)="",0,VLOOKUP(K56,Materialen!$A$2:$I$39,9,0)),0)+N(N56)*IFERROR(IF(VLOOKUP(M56,Materialen!$A$2:$I$39,9,0)="",0,VLOOKUP(M56,Materialen!$A$2:$I$39,9,0)),0),2) | Q56: =IF(G56="",0,IF(IFERROR(VLOOKUP(G56,Materialen!$A$2:$I$39,5,0),"N")="J",ROUND(N(H56)*(1+N(O56))*Instellingen!$B$8,2),0)) | S56: =ROUND(N(R56)/60*Instellingen!$B$9,2) | U56: =P56+Q56+S56+N(T56) | V56: =IF(AC56<>"OK","",F56-U56) | W56: =IF(OR(F56=0,AC56<>"OK"),"",V56/F56) | X56: =IF(N(H56)>0,F56/H56,"") | Y56: =IF(N(H56)>0,IFERROR(IF(VLOOKUP(G56,Materialen!$A$2:$I$39,9,0)="",0,VLOOKUP(G56,Materialen!$A$2:$I$39,9,0)),0),"") | Z56: =ROUND(E56*F56,2) | AA56: =IF(AC56<>"OK","",ROUND(E56*U56,2)) | AB56: =IF(AC56<>"OK","",Z56-AA56) | AC56: =IF((IF(G56="",0,IF(IFERROR(IF(VLOOKUP(G56,Materialen!$A$2:$I$39,9,0)="",0,VLOOKUP(G56,Materialen!$A$2:$I$39,9,0)),0)=0,1,0))+IF(I56="",0,IF(IFERROR(IF(VLOOKUP(I56,Materialen!$A$2:$I$39,9,0)="",0,VLOOKUP(I56,Materialen!$A$2:$I$39,9,0)),0)=0,1,0))+IF(K56="",0,IF(IFERROR(IF(VLOOKUP(K56,Materialen!$A$2:$I$39,9,0)="",0,VLOOKUP(K56,Materialen!$A$2:$I$39,9,0)),0)=0,1,0))+IF(M56="",0,IF(IFERROR(IF(VLOOKUP(M56,Materialen!$A$2:$I$39,9,0)="",0,VLOOKUP(M56,Materialen!$A$2:$I$39,9,0)),0)=0,1,0)))>0,"aankoopprijs ontbreekt",IF(AND(G56="",K56="",N(T56)=0,N(R56)=0),"kost invullen (arbeid/overig)","OK"))
A57: 56 | B57: Impression quadrichromie sur PLEXI mat opalin 3mm | C57: > 10 m² et <= 25 m² | D57: m² | E57: 5 | F57: 105 | G57: M35 | H57: 1 | O57: =IF(G57="","",IF(IFERROR(VLOOKUP(G57,Materialen!$A$2:$I$39,4,0),"")="plaat",Instellingen!$B$4,Instellingen!$B$3)) | P57: =ROUND(N(H57)*IFERROR(IF(VLOOKUP(G57,Materialen!$A$2:$I$39,9,0)="",0,VLOOKUP(G57,Materialen!$A$2:$I$39,9,0)),0)*(1+N(O57))+N(J57)*IFERROR(IF(VLOOKUP(I57,Materialen!$A$2:$I$39,9,0)="",0,VLOOKUP(I57,Materialen!$A$2:$I$39,9,0)),0)*(1+N(O57))+N(L57)*IFERROR(IF(VLOOKUP(K57,Materialen!$A$2:$I$39,9,0)="",0,VLOOKUP(K57,Materialen!$A$2:$I$39,9,0)),0)+N(N57)*IFERROR(IF(VLOOKUP(M57,Materialen!$A$2:$I$39,9,0)="",0,VLOOKUP(M57,Materialen!$A$2:$I$39,9,0)),0),2) | Q57: =IF(G57="",0,IF(IFERROR(VLOOKUP(G57,Materialen!$A$2:$I$39,5,0),"N")="J",ROUND(N(H57)*(1+N(O57))*Instellingen!$B$8,2),0)) | S57: =ROUND(N(R57)/60*Instellingen!$B$9,2) | U57: =P57+Q57+S57+N(T57) | V57: =IF(AC57<>"OK","",F57-U57) | W57: =IF(OR(F57=0,AC57<>"OK"),"",V57/F57) | X57: =IF(N(H57)>0,F57/H57,"") | Y57: =IF(N(H57)>0,IFERROR(IF(VLOOKUP(G57,Materialen!$A$2:$I$39,9,0)="",0,VLOOKUP(G57,Materialen!$A$2:$I$39,9,0)),0),"") | Z57: =ROUND(E57*F57,2) | AA57: =IF(AC57<>"OK","",ROUND(E57*U57,2)) | AB57: =IF(AC57<>"OK","",Z57-AA57) | AC57: =IF((IF(G57="",0,IF(IFERROR(IF(VLOOKUP(G57,Materialen!$A$2:$I$39,9,0)="",0,VLOOKUP(G57,Materialen!$A$2:$I$39,9,0)),0)=0,1,0))+IF(I57="",0,IF(IFERROR(IF(VLOOKUP(I57,Materialen!$A$2:$I$39,9,0)="",0,VLOOKUP(I57,Materialen!$A$2:$I$39,9,0)),0)=0,1,0))+IF(K57="",0,IF(IFERROR(IF(VLOOKUP(K57,Materialen!$A$2:$I$39,9,0)="",0,VLOOKUP(K57,Materialen!$A$2:$I$39,9,0)),0)=0,1,0))+IF(M57="",0,IF(IFERROR(IF(VLOOKUP(M57,Materialen!$A$2:$I$39,9,0)="",0,VLOOKUP(M57,Materialen!$A$2:$I$39,9,0)),0)=0,1,0)))>0,"aankoopprijs ontbreekt",IF(AND(G57="",K57="",N(T57)=0,N(R57)=0),"kost invullen (arbeid/overig)","OK"))
A58: 57 | B58: Impression quadrichromie sur PLEXI mat opalin 3mm | C58: > 25 m² | D58: m² | E58: 5 | F58: 98 | G58: M35 | H58: 1 | O58: =IF(G58="","",IF(IFERROR(VLOOKUP(G58,Materialen!$A$2:$I$39,4,0),"")="plaat",Instellingen!$B$4,Instellingen!$B$3)) | P58: =ROUND(N(H58)*IFERROR(IF(VLOOKUP(G58,Materialen!$A$2:$I$39,9,0)="",0,VLOOKUP(G58,Materialen!$A$2:$I$39,9,0)),0)*(1+N(O58))+N(J58)*IFERROR(IF(VLOOKUP(I58,Materialen!$A$2:$I$39,9,0)="",0,VLOOKUP(I58,Materialen!$A$2:$I$39,9,0)),0)*(1+N(O58))+N(L58)*IFERROR(IF(VLOOKUP(K58,Materialen!$A$2:$I$39,9,0)="",0,VLOOKUP(K58,Materialen!$A$2:$I$39,9,0)),0)+N(N58)*IFERROR(IF(VLOOKUP(M58,Materialen!$A$2:$I$39,9,0)="",0,VLOOKUP(M58,Materialen!$A$2:$I$39,9,0)),0),2) | Q58: =IF(G58="",0,IF(IFERROR(VLOOKUP(G58,Materialen!$A$2:$I$39,5,0),"N")="J",ROUND(N(H58)*(1+N(O58))*Instellingen!$B$8,2),0)) | S58: =ROUND(N(R58)/60*Instellingen!$B$9,2) | U58: =P58+Q58+S58+N(T58) | V58: =IF(AC58<>"OK","",F58-U58) | W58: =IF(OR(F58=0,AC58<>"OK"),"",V58/F58) | X58: =IF(N(H58)>0,F58/H58,"") | Y58: =IF(N(H58)>0,IFERROR(IF(VLOOKUP(G58,Materialen!$A$2:$I$39,9,0)="",0,VLOOKUP(G58,Materialen!$A$2:$I$39,9,0)),0),"") | Z58: =ROUND(E58*F58,2) | AA58: =IF(AC58<>"OK","",ROUND(E58*U58,2)) | AB58: =IF(AC58<>"OK","",Z58-AA58) | AC58: =IF((IF(G58="",0,IF(IFERROR(IF(VLOOKUP(G58,Materialen!$A$2:$I$39,9,0)="",0,VLOOKUP(G58,Materialen!$A$2:$I$39,9,0)),0)=0,1,0))+IF(I58="",0,IF(IFERROR(IF(VLOOKUP(I58,Materialen!$A$2:$I$39,9,0)="",0,VLOOKUP(I58,Materialen!$A$2:$I$39,9,0)),0)=0,1,0))+IF(K58="",0,IF(IFERROR(IF(VLOOKUP(K58,Materialen!$A$2:$I$39,9,0)="",0,VLOOKUP(K58,Materialen!$A$2:$I$39,9,0)),0)=0,1,0))+IF(M58="",0,IF(IFERROR(IF(VLOOKUP(M58,Materialen!$A$2:$I$39,9,0)="",0,VLOOKUP(M58,Materialen!$A$2:$I$39,9,0)),0)=0,1,0)))>0,"aankoopprijs ontbreekt",IF(AND(G58="",K58="",N(T58)=0,N(R58)=0),"kost invullen (arbeid/overig)","OK"))
... A64: 63 | B64: Impression noir ou quadrichromie sur carton 2mm | C64: > 25 m² | D64: m² | E64: 5 | F64: 21 | G64: M36 | H64: 1 | O64: =IF(G64="","",IF(IFERROR(VLOOKUP(G64,Materialen!$A$2:$I$39,4,0),"")="plaat",Instellingen!$B$4,Instellingen!$B$3)) | P64: =ROUND(N(H64)*IFERROR(IF(VLOOKUP(G64,Materialen!$A$2:$I$39,9,0)="",0,VLOOKUP(G64,Materialen!$A$2:$I$39,9,0)),0)*(1+N(O64))+N(J64)*IFERROR(IF(VLOOKUP(I64,Materialen!$A$2:$I$39,9,0)="",0,VLOOKUP(I64,Materialen!$A$2:$I$39,9,0)),0)*(1+N(O64))+N(L64)*IFERROR(IF(VLOOKUP(K64,Materialen!$A$2:$I$39,9,0)="",0,VLOOKUP(K64,Materialen!$A$2:$I$39,9,0)),0)+N(N64)*IFERROR(IF(VLOOKUP(M64,Materialen!$A$2:$I$39,9,0)="",0,VLOOKUP(M64,Materialen!$A$2:$I$39,9,0)),0),2) | Q64: =IF(G64="",0,IF(IFERROR(VLOOKUP(G64,Materialen!$A$2:$I$39,5,0),"N")="J",ROUND(N(H64)*(1+N(O64))*Instellingen!$B$8,2),0)) | S64: =ROUND(N(R64)/60*Instellingen!$B$9,2) | U64: =P64+Q64+S64+N(T64) | V64: =IF(AC64<>"OK","",F64-U64) | W64: =IF(OR(F64=0,AC64<>"OK"),"",V64/F64) | X64: =IF(N(H64)>0,F64/H64,"") | Y64: =IF(N(H64)>0,IFERROR(IF(VLOOKUP(G64,Materialen!$A$2:$I$39,9,0)="",0,VLOOKUP(G64,Materialen!$A$2:$I$39,9,0)),0),"") | Z64: =ROUND(E64*F64,2) | AA64: =IF(AC64<>"OK","",ROUND(E64*U64,2)) | AB64: =IF(AC64<>"OK","",Z64-AA64) | AC64: =IF((IF(G64="",0,IF(IFERROR(IF(VLOOKUP(G64,Materialen!$A$2:$I$39,9,0)="",0,VLOOKUP(G64,Materialen!$A$2:$I$39,9,0)),0)=0,1,0))+IF(I64="",0,IF(IFERROR(IF(VLOOKUP(I64,Materialen!$A$2:$I$39,9,0)="",0,VLOOKUP(I64,Materialen!$A$2:$I$39,9,0)),0)=0,1,0))+IF(K64="",0,IF(IFERROR(IF(VLOOKUP(K64,Materialen!$A$2:$I$39,9,0)="",0,VLOOKUP(K64,Materialen!$A$2:$I$39,9,0)),0)=0,1,0))+IF(M64="",0,IF(IFERROR(IF(VLOOKUP(M64,Materialen!$A$2:$I$39,9,0)="",0,VLOOKUP(M64,Materialen!$A$2:$I$39,9,0)),0)=0,1,0)))>0,"aankoopprijs ontbreekt",IF(AND(G64="",K64="",N(T64)=0,N(R64)=0),"kost invullen (arbeid/overig)","OK"))
A65: 64 | B65: Impression noir ou quadrichromie sur carton 1mm | C65: 10 cartels | D65: 10 cartels | E65: 5 | F65: 22 | G65: M37 | H65: 0.3108 | O65: =IF(G65="","",IF(IFERROR(VLOOKUP(G65,Materialen!$A$2:$I$39,4,0),"")="plaat",Instellingen!$B$4,Instellingen!$B$3)) | P65: =ROUND(N(H65)*IFERROR(IF(VLOOKUP(G65,Materialen!$A$2:$I$39,9,0)="",0,VLOOKUP(G65,Materialen!$A$2:$I$39,9,0)),0)*(1+N(O65))+N(J65)*IFERROR(IF(VLOOKUP(I65,Materialen!$A$2:$I$39,9,0)="",0,VLOOKUP(I65,Materialen!$A$2:$I$39,9,0)),0)*(1+N(O65))+N(L65)*IFERROR(IF(VLOOKUP(K65,Materialen!$A$2:$I$39,9,0)="",0,VLOOKUP(K65,Materialen!$A$2:$I$39,9,0)),0)+N(N65)*IFERROR(IF(VLOOKUP(M65,Materialen!$A$2:$I$39,9,0)="",0,VLOOKUP(M65,Materialen!$A$2:$I$39,9,0)),0),2) | Q65: =IF(G65="",0,IF(IFERROR(VLOOKUP(G65,Materialen!$A$2:$I$39,5,0),"N")="J",ROUND(N(H65)*(1+N(O65))*Instellingen!$B$8,2),0)) | S65: =ROUND(N(R65)/60*Instellingen!$B$9,2) | U65: =P65+Q65+S65+N(T65) | V65: =IF(AC65<>"OK","",F65-U65) | W65: =IF(OR(F65=0,AC65<>"OK"),"",V65/F65) | X65: =IF(N(H65)>0,F65/H65,"") | Y65: =IF(N(H65)>0,IFERROR(IF(VLOOKUP(G65,Materialen!$A$2:$I$39,9,0)="",0,VLOOKUP(G65,Materialen!$A$2:$I$39,9,0)),0),"") | Z65: =ROUND(E65*F65,2) | AA65: =IF(AC65<>"OK","",ROUND(E65*U65,2)) | AB65: =IF(AC65<>"OK","",Z65-AA65) | AC65: =IF((IF(G65="",0,IF(IFERROR(IF(VLOOKUP(G65,Materialen!$A$2:$I$39,9,0)="",0,VLOOKUP(G65,Materialen!$A$2:$I$39,9,0)),0)=0,1,0))+IF(I65="",0,IF(IFERROR(IF(VLOOKUP(I65,Materialen!$A$2:$I$39,9,0)="",0,VLOOKUP(I65,Materialen!$A$2:$I$39,9,0)),0)=0,1,0))+IF(K65="",0,IF(IFERROR(IF(VLOOKUP(K65,Materialen!$A$2:$I$39,9,0)="",0,VLOOKUP(K65,Materialen!$A$2:$I$39,9,0)),0)=0,1,0))+IF(M65="",0,IF(IFERROR(IF(VLOOKUP(M65,Materialen!$A$2:$I$39,9,0)="",0,VLOOKUP(M65,Materialen!$A$2:$I$39,9,0)),0)=0,1,0)))>0,"aankoopprijs ontbreekt",IF(AND(G65="",K65="",N(T65)=0,N(R65)=0),"kost invullen (arbeid/overig)","OK")) | AD65: 10 x A5
A66: 65 | B66: Impression noir ou quadrichromie sur carton 1mm | C66: 25 cartels | D66: 25 cartels | E66: 5 | F66: 45 | G66: M37 | H66: 0.777 | O66: =IF(G66="","",IF(IFERROR(VLOOKUP(G66,Materialen!$A$2:$I$39,4,0),"")="plaat",Instellingen!$B$4,Instellingen!$B$3)) | P66: =ROUND(N(H66)*IFERROR(IF(VLOOKUP(G66,Materialen!$A$2:$I$39,9,0)="",0,VLOOKUP(G66,Materialen!$A$2:$I$39,9,0)),0)*(1+N(O66))+N(J66)*IFERROR(IF(VLOOKUP(I66,Materialen!$A$2:$I$39,9,0)="",0,VLOOKUP(I66,Materialen!$A$2:$I$39,9,0)),0)*(1+N(O66))+N(L66)*IFERROR(IF(VLOOKUP(K66,Materialen!$A$2:$I$39,9,0)="",0,VLOOKUP(K66,Materialen!$A$2:$I$39,9,0)),0)+N(N66)*IFERROR(IF(VLOOKUP(M66,Materialen!$A$2:$I$39,9,0)="",0,VLOOKUP(M66,Materialen!$A$2:$I$39,9,0)),0),2) | Q66: =IF(G66="",0,IF(IFERROR(VLOOKUP(G66,Materialen!$A$2:$I$39,5,0),"N")="J",ROUND(N(H66)*(1+N(O66))*Instellingen!$B$8,2),0)) | S66: =ROUND(N(R66)/60*Instellingen!$B$9,2) | U66: =P66+Q66+S66+N(T66) | V66: =IF(AC66<>"OK","",F66-U66) | W66: =IF(OR(F66=0,AC66<>"OK"),"",V66/F66) | X66: =IF(N(H66)>0,F66/H66,"") | Y66: =IF(N(H66)>0,IFERROR(IF(VLOOKUP(G66,Materialen!$A$2:$I$39,9,0)="",0,VLOOKUP(G66,Materialen!$A$2:$I$39,9,0)),0),"") | Z66: =ROUND(E66*F66,2) | AA66: =IF(AC66<>"OK","",ROUND(E66*U66,2)) | AB66: =IF(AC66<>"OK","",Z66-AA66) | AC66: =IF((IF(G66="",0,IF(IFERROR(IF(VLOOKUP(G66,Materialen!$A$2:$I$39,9,0)="",0,VLOOKUP(G66,Materialen!$A$2:$I$39,9,0)),0)=0,1,0))+IF(I66="",0,IF(IFERROR(IF(VLOOKUP(I66,Materialen!$A$2:$I$39,9,0)="",0,VLOOKUP(I66,Materialen!$A$2:$I$39,9,0)),0)=0,1,0))+IF(K66="",0,IF(IFERROR(IF(VLOOKUP(K66,Materialen!$A$2:$I$39,9,0)="",0,VLOOKUP(K66,Materialen!$A$2:$I$39,9,0)),0)=0,1,0))+IF(M66="",0,IF(IFERROR(IF(VLOOKUP(M66,Materialen!$A$2:$I$39,9,0)="",0,VLOOKUP(M66,Materialen!$A$2:$I$39,9,0)),0)=0,1,0)))>0,"aankoopprijs ontbreekt",IF(AND(G66="",K66="",N(T66)=0,N(R66)=0),"kost invullen (arbeid/overig)","OK")) | AD66: 25 x A5
A67: 66 | B67: Impression noir ou quadrichromie sur carton 1mm | C67: 50 cartels | D67: 50 cartels | E67: 5 | F67: 75 | G67: M37 | H67: 1.554 | O67: =IF(G67="","",IF(IFERROR(VLOOKUP(G67,Materialen!$A$2:$I$39,4,0),"")="plaat",Instellingen!$B$4,Instellingen!$B$3)) | P67: =ROUND(N(H67)*IFERROR(IF(VLOOKUP(G67,Materialen!$A$2:$I$39,9,0)="",0,VLOOKUP(G67,Materialen!$A$2:$I$39,9,0)),0)*(1+N(O67))+N(J67)*IFERROR(IF(VLOOKUP(I67,Materialen!$A$2:$I$39,9,0)="",0,VLOOKUP(I67,Materialen!$A$2:$I$39,9,0)),0)*(1+N(O67))+N(L67)*IFERROR(IF(VLOOKUP(K67,Materialen!$A$2:$I$39,9,0)="",0,VLOOKUP(K67,Materialen!$A$2:$I$39,9,0)),0)+N(N67)*IFERROR(IF(VLOOKUP(M67,Materialen!$A$2:$I$39,9,0)="",0,VLOOKUP(M67,Materialen!$A$2:$I$39,9,0)),0),2) | Q67: =IF(G67="",0,IF(IFERROR(VLOOKUP(G67,Materialen!$A$2:$I$39,5,0),"N")="J",ROUND(N(H67)*(1+N(O67))*Instellingen!$B$8,2),0)) | S67: =ROUND(N(R67)/60*Instellingen!$B$9,2) | U67: =P67+Q67+S67+N(T67) | V67: =IF(AC67<>"OK","",F67-U67) | W67: =IF(OR(F67=0,AC67<>"OK"),"",V67/F67) | X67: =IF(N(H67)>0,F67/H67,"") | Y67: =IF(N(H67)>0,IFERROR(IF(VLOOKUP(G67,Materialen!$A$2:$I$39,9,0)="",0,VLOOKUP(G67,Materialen!$A$2:$I$39,9,0)),0),"") | Z67: =ROUND(E67*F67,2) | AA67: =IF(AC67<>"OK","",ROUND(E67*U67,2)) | AB67: =IF(AC67<>"OK","",Z67-AA67) | AC67: =IF((IF(G67="",0,IF(IFERROR(IF(VLOOKUP(G67,Materialen!$A$2:$I$39,9,0)="",0,VLOOKUP(G67,Materialen!$A$2:$I$39,9,0)),0)=0,1,0))+IF(I67="",0,IF(IFERROR(IF(VLOOKUP(I67,Materialen!$A$2:$I$39,9,0)="",0,VLOOKUP(I67,Materialen!$A$2:$I$39,9,0)),0)=0,1,0))+IF(K67="",0,IF(IFERROR(IF(VLOOKUP(K67,Materialen!$A$2:$I$39,9,0)="",0,VLOOKUP(K67,Materialen!$A$2:$I$39,9,0)),0)=0,1,0))+IF(M67="",0,IF(IFERROR(IF(VLOOKUP(M67,Materialen!$A$2:$I$39,9,0)="",0,VLOOKUP(M67,Materialen!$A$2:$I$39,9,0)),0)=0,1,0)))>0,"aankoopprijs ontbreekt",IF(AND(G67="",K67="",N(T67)=0,N(R67)=0),"kost invullen (arbeid/overig)","OK")) | AD67: 50 x A5
A68: 67 | B68: Impression noir ou quadrichromie sur carton 1mm | C68: 100 cartels | D68: 100 cartels | E68: 5 | F68: 130 | G68: M37 | H68: 3.108 | O68: =IF(G68="","",IF(IFERROR(VLOOKUP(G68,Materialen!$A$2:$I$39,4,0),"")="plaat",Instellingen!$B$4,Instellingen!$B$3)) | P68: =ROUND(N(H68)*IFERROR(IF(VLOOKUP(G68,Materialen!$A$2:$I$39,9,0)="",0,VLOOKUP(G68,Materialen!$A$2:$I$39,9,0)),0)*(1+N(O68))+N(J68)*IFERROR(IF(VLOOKUP(I68,Materialen!$A$2:$I$39,9,0)="",0,VLOOKUP(I68,Materialen!$A$2:$I$39,9,0)),0)*(1+N(O68))+N(L68)*IFERROR(IF(VLOOKUP(K68,Materialen!$A$2:$I$39,9,0)="",0,VLOOKUP(K68,Materialen!$A$2:$I$39,9,0)),0)+N(N68)*IFERROR(IF(VLOOKUP(M68,Materialen!$A$2:$I$39,9,0)="",0,VLOOKUP(M68,Materialen!$A$2:$I$39,9,0)),0),2) | Q68: =IF(G68="",0,IF(IFERROR(VLOOKUP(G68,Materialen!$A$2:$I$39,5,0),"N")="J",ROUND(N(H68)*(1+N(O68))*Instellingen!$B$8,2),0)) | S68: =ROUND(N(R68)/60*Instellingen!$B$9,2) | U68: =P68+Q68+S68+N(T68) | V68: =IF(AC68<>"OK","",F68-U68) | W68: =IF(OR(F68=0,AC68<>"OK"),"",V68/F68) | X68: =IF(N(H68)>0,F68/H68,"") | Y68: =IF(N(H68)>0,IFERROR(IF(VLOOKUP(G68,Materialen!$A$2:$I$39,9,0)="",0,VLOOKUP(G68,Materialen!$A$2:$I$39,9,0)),0),"") | Z68: =ROUND(E68*F68,2) | AA68: =IF(AC68<>"OK","",ROUND(E68*U68,2)) | AB68: =IF(AC68<>"OK","",Z68-AA68) | AC68: =IF((IF(G68="",0,IF(IFERROR(IF(VLOOKUP(G68,Materialen!$A$2:$I$39,9,0)="",0,VLOOKUP(G68,Materialen!$A$2:$I$39,9,0)),0)=0,1,0))+IF(I68="",0,IF(IFERROR(IF(VLOOKUP(I68,Materialen!$A$2:$I$39,9,0)="",0,VLOOKUP(I68,Materialen!$A$2:$I$39,9,0)),0)=0,1,0))+IF(K68="",0,IF(IFERROR(IF(VLOOKUP(K68,Materialen!$A$2:$I$39,9,0)="",0,VLOOKUP(K68,Materialen!$A$2:$I$39,9,0)),0)=0,1,0))+IF(M68="",0,IF(IFERROR(IF(VLOOKUP(M68,Materialen!$A$2:$I$39,9,0)="",0,VLOOKUP(M68,Materialen!$A$2:$I$39,9,0)),0)=0,1,0)))>0,"aankoopprijs ontbreekt",IF(AND(G68="",K68="",N(T68)=0,N(R68)=0),"kost invullen (arbeid/overig)","OK")) | AD68: 100 x A5
A69: 68 | B69: Impression noir ou quadrichromie sur carton 1mm | C69: 150 cartels | D69: 150 cartels | E69: 5 | F69: 180 | G69: M37 | H69: 4.662 | O69: =IF(G69="","",IF(IFERROR(VLOOKUP(G69,Materialen!$A$2:$I$39,4,0),"")="plaat",Instellingen!$B$4,Instellingen!$B$3)) | P69: =ROUND(N(H69)*IFERROR(IF(VLOOKUP(G69,Materialen!$A$2:$I$39,9,0)="",0,VLOOKUP(G69,Materialen!$A$2:$I$39,9,0)),0)*(1+N(O69))+N(J69)*IFERROR(IF(VLOOKUP(I69,Materialen!$A$2:$I$39,9,0)="",0,VLOOKUP(I69,Materialen!$A$2:$I$39,9,0)),0)*(1+N(O69))+N(L69)*IFERROR(IF(VLOOKUP(K69,Materialen!$A$2:$I$39,9,0)="",0,VLOOKUP(K69,Materialen!$A$2:$I$39,9,0)),0)+N(N69)*IFERROR(IF(VLOOKUP(M69,Materialen!$A$2:$I$39,9,0)="",0,VLOOKUP(M69,Materialen!$A$2:$I$39,9,0)),0),2) | Q69: =IF(G69="",0,IF(IFERROR(VLOOKUP(G69,Materialen!$A$2:$I$39,5,0),"N")="J",ROUND(N(H69)*(1+N(O69))*Instellingen!$B$8,2),0)) | S69: =ROUND(N(R69)/60*Instellingen!$B$9,2) | U69: =P69+Q69+S69+N(T69) | V69: =IF(AC69<>"OK","",F69-U69) | W69: =IF(OR(F69=0,AC69<>"OK"),"",V69/F69) | X69: =IF(N(H69)>0,F69/H69,"") | Y69: =IF(N(H69)>0,IFERROR(IF(VLOOKUP(G69,Materialen!$A$2:$I$39,9,0)="",0,VLOOKUP(G69,Materialen!$A$2:$I$39,9,0)),0),"") | Z69: =ROUND(E69*F69,2) | AA69: =IF(AC69<>"OK","",ROUND(E69*U69,2)) | AB69: =IF(AC69<>"OK","",Z69-AA69) | AC69: =IF((IF(G69="",0,IF(IFERROR(IF(VLOOKUP(G69,Materialen!$A$2:$I$39,9,0)="",0,VLOOKUP(G69,Materialen!$A$2:$I$39,9,0)),0)=0,1,0))+IF(I69="",0,IF(IFERROR(IF(VLOOKUP(I69,Materialen!$A$2:$I$39,9,0)="",0,VLOOKUP(I69,Materialen!$A$2:$I$39,9,0)),0)=0,1,0))+IF(K69="",0,IF(IFERROR(IF(VLOOKUP(K69,Materialen!$A$2:$I$39,9,0)="",0,VLOOKUP(K69,Materialen!$A$2:$I$39,9,0)),0)=0,1,0))+IF(M69="",0,IF(IFERROR(IF(VLOOKUP(M69,Materialen!$A$2:$I$39,9,0)="",0,VLOOKUP(M69,Materialen!$A$2:$I$39,9,0)),0)=0,1,0)))>0,"aankoopprijs ontbreekt",IF(AND(G69="",K69="",N(T69)=0,N(R69)=0),"kost invullen (arbeid/overig)","OK")) | AD69: 150 x A5
A70: 69 | B70: Impression noir ou quadrichromie sur carton 1mm | C70: 200 cartels | D70: 200 cartels | E70: 5 | F70: 225 | G70: M37 | H70: 6.216 | O70: =IF(G70="","",IF(IFERROR(VLOOKUP(G70,Materialen!$A$2:$I$39,4,0),"")="plaat",Instellingen!$B$4,Instellingen!$B$3)) | P70: =ROUND(N(H70)*IFERROR(IF(VLOOKUP(G70,Materialen!$A$2:$I$39,9,0)="",0,VLOOKUP(G70,Materialen!$A$2:$I$39,9,0)),0)*(1+N(O70))+N(J70)*IFERROR(IF(VLOOKUP(I70,Materialen!$A$2:$I$39,9,0)="",0,VLOOKUP(I70,Materialen!$A$2:$I$39,9,0)),0)*(1+N(O70))+N(L70)*IFERROR(IF(VLOOKUP(K70,Materialen!$A$2:$I$39,9,0)="",0,VLOOKUP(K70,Materialen!$A$2:$I$39,9,0)),0)+N(N70)*IFERROR(IF(VLOOKUP(M70,Materialen!$A$2:$I$39,9,0)="",0,VLOOKUP(M70,Materialen!$A$2:$I$39,9,0)),0),2) | Q70: =IF(G70="",0,IF(IFERROR(VLOOKUP(G70,Materialen!$A$2:$I$39,5,0),"N")="J",ROUND(N(H70)*(1+N(O70))*Instellingen!$B$8,2),0)) | S70: =ROUND(N(R70)/60*Instellingen!$B$9,2) | U70: =P70+Q70+S70+N(T70) | V70: =IF(AC70<>"OK","",F70-U70) | W70: =IF(OR(F70=0,AC70<>"OK"),"",V70/F70) | X70: =IF(N(H70)>0,F70/H70,"") | Y70: =IF(N(H70)>0,IFERROR(IF(VLOOKUP(G70,Materialen!$A$2:$I$39,9,0)="",0,VLOOKUP(G70,Materialen!$A$2:$I$39,9,0)),0),"") | Z70: =ROUND(E70*F70,2) | AA70: =IF(AC70<>"OK","",ROUND(E70*U70,2)) | AB70: =IF(AC70<>"OK","",Z70-AA70) | AC70: =IF((IF(G70="",0,IF(IFERROR(IF(VLOOKUP(G70,Materialen!$A$2:$I$39,9,0)="",0,VLOOKUP(G70,Materialen!$A$2:$I$39,9,0)),0)=0,1,0))+IF(I70="",0,IF(IFERROR(IF(VLOOKUP(I70,Materialen!$A$2:$I$39,9,0)="",0,VLOOKUP(I70,Materialen!$A$2:$I$39,9,0)),0)=0,1,0))+IF(K70="",0,IF(IFERROR(IF(VLOOKUP(K70,Materialen!$A$2:$I$39,9,0)="",0,VLOOKUP(K70,Materialen!$A$2:$I$39,9,0)),0)=0,1,0))+IF(M70="",0,IF(IFERROR(IF(VLOOKUP(M70,Materialen!$A$2:$I$39,9,0)="",0,VLOOKUP(M70,Materialen!$A$2:$I$39,9,0)),0)=0,1,0)))>0,"aankoopprijs ontbreekt",IF(AND(G70="",K70="",N(T70)=0,N(R70)=0),"kost invullen (arbeid/overig)","OK")) | AD70: 200 x A5
A71: 70 | B71: Impression noir ou quadrichromie sur carton 1mm | C71: qté supplém. +10 | D71: 10 quantités supplémentaires | E71: 5 | F71: 11 | G71: M37 | H71: 0.3108 | O71: =IF(G71="","",IF(IFERROR(VLOOKUP(G71,Materialen!$A$2:$I$39,4,0),"")="plaat",Instellingen!$B$4,Instellingen!$B$3)) | P71: =ROUND(N(H71)*IFERROR(IF(VLOOKUP(G71,Materialen!$A$2:$I$39,9,0)="",0,VLOOKUP(G71,Materialen!$A$2:$I$39,9,0)),0)*(1+N(O71))+N(J71)*IFERROR(IF(VLOOKUP(I71,Materialen!$A$2:$I$39,9,0)="",0,VLOOKUP(I71,Materialen!$A$2:$I$39,9,0)),0)*(1+N(O71))+N(L71)*IFERROR(IF(VLOOKUP(K71,Materialen!$A$2:$I$39,9,0)="",0,VLOOKUP(K71,Materialen!$A$2:$I$39,9,0)),0)+N(N71)*IFERROR(IF(VLOOKUP(M71,Materialen!$A$2:$I$39,9,0)="",0,VLOOKUP(M71,Materialen!$A$2:$I$39,9,0)),0),2) | Q71: =IF(G71="",0,IF(IFERROR(VLOOKUP(G71,Materialen!$A$2:$I$39,5,0),"N")="J",ROUND(N(H71)*(1+N(O71))*Instellingen!$B$8,2),0)) | S71: =ROUND(N(R71)/60*Instellingen!$B$9,2) | U71: =P71+Q71+S71+N(T71) | V71: =IF(AC71<>"OK","",F71-U71) | W71: =IF(OR(F71=0,AC71<>"OK"),"",V71/F71) | X71: =IF(N(H71)>0,F71/H71,"") | Y71: =IF(N(H71)>0,IFERROR(IF(VLOOKUP(G71,Materialen!$A$2:$I$39,9,0)="",0,VLOOKUP(G71,Materialen!$A$2:$I$39,9,0)),0),"") | Z71: =ROUND(E71*F71,2) | AA71: =IF(AC71<>"OK","",ROUND(E71*U71,2)) | AB71: =IF(AC71<>"OK","",Z71-AA71) | AC71: =IF((IF(G71="",0,IF(IFERROR(IF(VLOOKUP(G71,Materialen!$A$2:$I$39,9,0)="",0,VLOOKUP(G71,Materialen!$A$2:$I$39,9,0)),0)=0,1,0))+IF(I71="",0,IF(IFERROR(IF(VLOOKUP(I71,Materialen!$A$2:$I$39,9,0)="",0,VLOOKUP(I71,Materialen!$A$2:$I$39,9,0)),0)=0,1,0))+IF(K71="",0,IF(IFERROR(IF(VLOOKUP(K71,Materialen!$A$2:$I$39,9,0)="",0,VLOOKUP(K71,Materialen!$A$2:$I$39,9,0)),0)=0,1,0))+IF(M71="",0,IF(IFERROR(IF(VLOOKUP(M71,Materialen!$A$2:$I$39,9,0)="",0,VLOOKUP(M71,Materialen!$A$2:$I$39,9,0)),0)=0,1,0)))>0,"aankoopprijs ontbreekt",IF(AND(G71="",K71="",N(T71)=0,N(R71)=0),"kost invullen (arbeid/overig)","OK")) | AD71: 10 x A5
A72: 71 | B72: Impression noir ou quadrichromie sur carton 2mm | C72: 10 cartels | D72: 10 cartels | E72: 5 | F72: 25 | G72: M36 | H72: 0.3108 | O72: =IF(G72="","",IF(IFERROR(VLOOKUP(G72,Materialen!$A$2:$I$39,4,0),"")="plaat",Instellingen!$B$4,Instellingen!$B$3)) | P72: =ROUND(N(H72)*IFERROR(IF(VLOOKUP(G72,Materialen!$A$2:$I$39,9,0)="",0,VLOOKUP(G72,Materialen!$A$2:$I$39,9,0)),0)*(1+N(O72))+N(J72)*IFERROR(IF(VLOOKUP(I72,Materialen!$A$2:$I$39,9,0)="",0,VLOOKUP(I72,Materialen!$A$2:$I$39,9,0)),0)*(1+N(O72))+N(L72)*IFERROR(IF(VLOOKUP(K72,Materialen!$A$2:$I$39,9,0)="",0,VLOOKUP(K72,Materialen!$A$2:$I$39,9,0)),0)+N(N72)*IFERROR(IF(VLOOKUP(M72,Materialen!$A$2:$I$39,9,0)="",0,VLOOKUP(M72,Materialen!$A$2:$I$39,9,0)),0),2) | Q72: =IF(G72="",0,IF(IFERROR(VLOOKUP(G72,Materialen!$A$2:$I$39,5,0),"N")="J",ROUND(N(H72)*(1+N(O72))*Instellingen!$B$8,2),0)) | S72: =ROUND(N(R72)/60*Instellingen!$B$9,2) | U72: =P72+Q72+S72+N(T72) | V72: =IF(AC72<>"OK","",F72-U72) | W72: =IF(OR(F72=0,AC72<>"OK"),"",V72/F72) | X72: =IF(N(H72)>0,F72/H72,"") | Y72: =IF(N(H72)>0,IFERROR(IF(VLOOKUP(G72,Materialen!$A$2:$I$39,9,0)="",0,VLOOKUP(G72,Materialen!$A$2:$I$39,9,0)),0),"") | Z72: =ROUND(E72*F72,2) | AA72: =IF(AC72<>"OK","",ROUND(E72*U72,2)) | AB72: =IF(AC72<>"OK","",Z72-AA72) | AC72: =IF((IF(G72="",0,IF(IFERROR(IF(VLOOKUP(G72,Materialen!$A$2:$I$39,9,0)="",0,VLOOKUP(G72,Materialen!$A$2:$I$39,9,0)),0)=0,1,0))+IF(I72="",0,IF(IFERROR(IF(VLOOKUP(I72,Materialen!$A$2:$I$39,9,0)="",0,VLOOKUP(I72,Materialen!$A$2:$I$39,9,0)),0)=0,1,0))+IF(K72="",0,IF(IFERROR(IF(VLOOKUP(K72,Materialen!$A$2:$I$39,9,0)="",0,VLOOKUP(K72,Materialen!$A$2:$I$39,9,0)),0)=0,1,0))+IF(M72="",0,IF(IFERROR(IF(VLOOKUP(M72,Materialen!$A$2:$I$39,9,0)="",0,VLOOKUP(M72,Materialen!$A$2:$I$39,9,0)),0)=0,1,0)))>0,"aankoopprijs ontbreekt",IF(AND(G72="",K72="",N(T72)=0,N(R72)=0),"kost invullen (arbeid/overig)","OK")) | AD72: 10 x A5
A73: 72 | B73: Impression noir ou quadrichromie sur carton 2mm | C73: 25 cartels | D73: 25 cartels | E73: 5 | F73: 50 | G73: M36 | H73: 0.777 | O73: =IF(G73="","",IF(IFERROR(VLOOKUP(G73,Materialen!$A$2:$I$39,4,0),"")="plaat",Instellingen!$B$4,Instellingen!$B$3)) | P73: =ROUND(N(H73)*IFERROR(IF(VLOOKUP(G73,Materialen!$A$2:$I$39,9,0)="",0,VLOOKUP(G73,Materialen!$A$2:$I$39,9,0)),0)*(1+N(O73))+N(J73)*IFERROR(IF(VLOOKUP(I73,Materialen!$A$2:$I$39,9,0)="",0,VLOOKUP(I73,Materialen!$A$2:$I$39,9,0)),0)*(1+N(O73))+N(L73)*IFERROR(IF(VLOOKUP(K73,Materialen!$A$2:$I$39,9,0)="",0,VLOOKUP(K73,Materialen!$A$2:$I$39,9,0)),0)+N(N73)*IFERROR(IF(VLOOKUP(M73,Materialen!$A$2:$I$39,9,0)="",0,VLOOKUP(M73,Materialen!$A$2:$I$39,9,0)),0),2) | Q73: =IF(G73="",0,IF(IFERROR(VLOOKUP(G73,Materialen!$A$2:$I$39,5,0),"N")="J",ROUND(N(H73)*(1+N(O73))*Instellingen!$B$8,2),0)) | S73: =ROUND(N(R73)/60*Instellingen!$B$9,2) | U73: =P73+Q73+S73+N(T73) | V73: =IF(AC73<>"OK","",F73-U73) | W73: =IF(OR(F73=0,AC73<>"OK"),"",V73/F73) | X73: =IF(N(H73)>0,F73/H73,"") | Y73: =IF(N(H73)>0,IFERROR(IF(VLOOKUP(G73,Materialen!$A$2:$I$39,9,0)="",0,VLOOKUP(G73,Materialen!$A$2:$I$39,9,0)),0),"") | Z73: =ROUND(E73*F73,2) | AA73: =IF(AC73<>"OK","",ROUND(E73*U73,2)) | AB73: =IF(AC73<>"OK","",Z73-AA73) | AC73: =IF((IF(G73="",0,IF(IFERROR(IF(VLOOKUP(G73,Materialen!$A$2:$I$39,9,0)="",0,VLOOKUP(G73,Materialen!$A$2:$I$39,9,0)),0)=0,1,0))+IF(I73="",0,IF(IFERROR(IF(VLOOKUP(I73,Materialen!$A$2:$I$39,9,0)="",0,VLOOKUP(I73,Materialen!$A$2:$I$39,9,0)),0)=0,1,0))+IF(K73="",0,IF(IFERROR(IF(VLOOKUP(K73,Materialen!$A$2:$I$39,9,0)="",0,VLOOKUP(K73,Materialen!$A$2:$I$39,9,0)),0)=0,1,0))+IF(M73="",0,IF(IFERROR(IF(VLOOKUP(M73,Materialen!$A$2:$I$39,9,0)="",0,VLOOKUP(M73,Materialen!$A$2:$I$39,9,0)),0)=0,1,0)))>0,"aankoopprijs ontbreekt",IF(AND(G73="",K73="",N(T73)=0,N(R73)=0),"kost invullen (arbeid/overig)","OK")) | AD73: 25 x A5
A74: 73 | B74: Impression noir ou quadrichromie sur carton 2mm | C74: 50 cartels | D74: 50 cartels | E74: 5 | F74: 85 | G74: M36 | H74: 1.554 | O74: =IF(G74="","",IF(IFERROR(VLOOKUP(G74,Materialen!$A$2:$I$39,4,0),"")="plaat",Instellingen!$B$4,Instellingen!$B$3)) | P74: =ROUND(N(H74)*IFERROR(IF(VLOOKUP(G74,Materialen!$A$2:$I$39,9,0)="",0,VLOOKUP(G74,Materialen!$A$2:$I$39,9,0)),0)*(1+N(O74))+N(J74)*IFERROR(IF(VLOOKUP(I74,Materialen!$A$2:$I$39,9,0)="",0,VLOOKUP(I74,Materialen!$A$2:$I$39,9,0)),0)*(1+N(O74))+N(L74)*IFERROR(IF(VLOOKUP(K74,Materialen!$A$2:$I$39,9,0)="",0,VLOOKUP(K74,Materialen!$A$2:$I$39,9,0)),0)+N(N74)*IFERROR(IF(VLOOKUP(M74,Materialen!$A$2:$I$39,9,0)="",0,VLOOKUP(M74,Materialen!$A$2:$I$39,9,0)),0),2) | Q74: =IF(G74="",0,IF(IFERROR(VLOOKUP(G74,Materialen!$A$2:$I$39,5,0),"N")="J",ROUND(N(H74)*(1+N(O74))*Instellingen!$B$8,2),0)) | S74: =ROUND(N(R74)/60*Instellingen!$B$9,2) | U74: =P74+Q74+S74+N(T74) | V74: =IF(AC74<>"OK","",F74-U74) | W74: =IF(OR(F74=0,AC74<>"OK"),"",V74/F74) | X74: =IF(N(H74)>0,F74/H74,"") | Y74: =IF(N(H74)>0,IFERROR(IF(VLOOKUP(G74,Materialen!$A$2:$I$39,9,0)="",0,VLOOKUP(G74,Materialen!$A$2:$I$39,9,0)),0),"") | Z74: =ROUND(E74*F74,2) | AA74: =IF(AC74<>"OK","",ROUND(E74*U74,2)) | AB74: =IF(AC74<>"OK","",Z74-AA74) | AC74: =IF((IF(G74="",0,IF(IFERROR(IF(VLOOKUP(G74,Materialen!$A$2:$I$39,9,0)="",0,VLOOKUP(G74,Materialen!$A$2:$I$39,9,0)),0)=0,1,0))+IF(I74="",0,IF(IFERROR(IF(VLOOKUP(I74,Materialen!$A$2:$I$39,9,0)="",0,VLOOKUP(I74,Materialen!$A$2:$I$39,9,0)),0)=0,1,0))+IF(K74="",0,IF(IFERROR(IF(VLOOKUP(K74,Materialen!$A$2:$I$39,9,0)="",0,VLOOKUP(K74,Materialen!$A$2:$I$39,9,0)),0)=0,1,0))+IF(M74="",0,IF(IFERROR(IF(VLOOKUP(M74,Materialen!$A$2:$I$39,9,0)="",0,VLOOKUP(M74,Materialen!$A$2:$I$39,9,0)),0)=0,1,0)))>0,"aankoopprijs ontbreekt",IF(AND(G74="",K74="",N(T74)=0,N(R74)=0),"kost invullen (arbeid/overig)","OK")) | AD74: 50 x A5
A75: 74 | B75: Impression noir ou quadrichromie sur carton 2mm | C75: 100 cartels | D75: 100 cartels | E75: 5 | F75: 150 | G75: M36 | H75: 3.108 | O75: =IF(G75="","",IF(IFERROR(VLOOKUP(G75,Materialen!$A$2:$I$39,4,0),"")="plaat",Instellingen!$B$4,Instellingen!$B$3)) | P75: =ROUND(N(H75)*IFERROR(IF(VLOOKUP(G75,Materialen!$A$2:$I$39,9,0)="",0,VLOOKUP(G75,Materialen!$A$2:$I$39,9,0)),0)*(1+N(O75))+N(J75)*IFERROR(IF(VLOOKUP(I75,Materialen!$A$2:$I$39,9,0)="",0,VLOOKUP(I75,Materialen!$A$2:$I$39,9,0)),0)*(1+N(O75))+N(L75)*IFERROR(IF(VLOOKUP(K75,Materialen!$A$2:$I$39,9,0)="",0,VLOOKUP(K75,Materialen!$A$2:$I$39,9,0)),0)+N(N75)*IFERROR(IF(VLOOKUP(M75,Materialen!$A$2:$I$39,9,0)="",0,VLOOKUP(M75,Materialen!$A$2:$I$39,9,0)),0),2) | Q75: =IF(G75="",0,IF(IFERROR(VLOOKUP(G75,Materialen!$A$2:$I$39,5,0),"N")="J",ROUND(N(H75)*(1+N(O75))*Instellingen!$B$8,2),0)) | S75: =ROUND(N(R75)/60*Instellingen!$B$9,2) | U75: =P75+Q75+S75+N(T75) | V75: =IF(AC75<>"OK","",F75-U75) | W75: =IF(OR(F75=0,AC75<>"OK"),"",V75/F75) | X75: =IF(N(H75)>0,F75/H75,"") | Y75: =IF(N(H75)>0,IFERROR(IF(VLOOKUP(G75,Materialen!$A$2:$I$39,9,0)="",0,VLOOKUP(G75,Materialen!$A$2:$I$39,9,0)),0),"") | Z75: =ROUND(E75*F75,2) | AA75: =IF(AC75<>"OK","",ROUND(E75*U75,2)) | AB75: =IF(AC75<>"OK","",Z75-AA75) | AC75: =IF((IF(G75="",0,IF(IFERROR(IF(VLOOKUP(G75,Materialen!$A$2:$I$39,9,0)="",0,VLOOKUP(G75,Materialen!$A$2:$I$39,9,0)),0)=0,1,0))+IF(I75="",0,IF(IFERROR(IF(VLOOKUP(I75,Materialen!$A$2:$I$39,9,0)="",0,VLOOKUP(I75,Materialen!$A$2:$I$39,9,0)),0)=0,1,0))+IF(K75="",0,IF(IFERROR(IF(VLOOKUP(K75,Materialen!$A$2:$I$39,9,0)="",0,VLOOKUP(K75,Materialen!$A$2:$I$39,9,0)),0)=0,1,0))+IF(M75="",0,IF(IFERROR(IF(VLOOKUP(M75,Materialen!$A$2:$I$39,9,0)="",0,VLOOKUP(M75,Materialen!$A$2:$I$39,9,0)),0)=0,1,0)))>0,"aankoopprijs ontbreekt",IF(AND(G75="",K75="",N(T75)=0,N(R75)=0),"kost invullen (arbeid/overig)","OK")) | AD75: 100 x A5
A76: 75 | B76: Impression noir ou quadrichromie sur carton 2mm | C76: 150 cartels | D76: 150 cartels | E76: 5 | F76: 205 | G76: M36 | H76: 4.662 | O76: =IF(G76="","",IF(IFERROR(VLOOKUP(G76,Materialen!$A$2:$I$39,4,0),"")="plaat",Instellingen!$B$4,Instellingen!$B$3)) | P76: =ROUND(N(H76)*IFERROR(IF(VLOOKUP(G76,Materialen!$A$2:$I$39,9,0)="",0,VLOOKUP(G76,Materialen!$A$2:$I$39,9,0)),0)*(1+N(O76))+N(J76)*IFERROR(IF(VLOOKUP(I76,Materialen!$A$2:$I$39,9,0)="",0,VLOOKUP(I76,Materialen!$A$2:$I$39,9,0)),0)*(1+N(O76))+N(L76)*IFERROR(IF(VLOOKUP(K76,Materialen!$A$2:$I$39,9,0)="",0,VLOOKUP(K76,Materialen!$A$2:$I$39,9,0)),0)+N(N76)*IFERROR(IF(VLOOKUP(M76,Materialen!$A$2:$I$39,9,0)="",0,VLOOKUP(M76,Materialen!$A$2:$I$39,9,0)),0),2) | Q76: =IF(G76="",0,IF(IFERROR(VLOOKUP(G76,Materialen!$A$2:$I$39,5,0),"N")="J",ROUND(N(H76)*(1+N(O76))*Instellingen!$B$8,2),0)) | S76: =ROUND(N(R76)/60*Instellingen!$B$9,2) | U76: =P76+Q76+S76+N(T76) | V76: =IF(AC76<>"OK","",F76-U76) | W76: =IF(OR(F76=0,AC76<>"OK"),"",V76/F76) | X76: =IF(N(H76)>0,F76/H76,"") | Y76: =IF(N(H76)>0,IFERROR(IF(VLOOKUP(G76,Materialen!$A$2:$I$39,9,0)="",0,VLOOKUP(G76,Materialen!$A$2:$I$39,9,0)),0),"") | Z76: =ROUND(E76*F76,2) | AA76: =IF(AC76<>"OK","",ROUND(E76*U76,2)) | AB76: =IF(AC76<>"OK","",Z76-AA76) | AC76: =IF((IF(G76="",0,IF(IFERROR(IF(VLOOKUP(G76,Materialen!$A$2:$I$39,9,0)="",0,VLOOKUP(G76,Materialen!$A$2:$I$39,9,0)),0)=0,1,0))+IF(I76="",0,IF(IFERROR(IF(VLOOKUP(I76,Materialen!$A$2:$I$39,9,0)="",0,VLOOKUP(I76,Materialen!$A$2:$I$39,9,0)),0)=0,1,0))+IF(K76="",0,IF(IFERROR(IF(VLOOKUP(K76,Materialen!$A$2:$I$39,9,0)="",0,VLOOKUP(K76,Materialen!$A$2:$I$39,9,0)),0)=0,1,0))+IF(M76="",0,IF(IFERROR(IF(VLOOKUP(M76,Materialen!$A$2:$I$39,9,0)="",0,VLOOKUP(M76,Materialen!$A$2:$I$39,9,0)),0)=0,1,0)))>0,"aankoopprijs ontbreekt",IF(AND(G76="",K76="",N(T76)=0,N(R76)=0),"kost invullen (arbeid/overig)","OK")) | AD76: 150 x A5
... A78: 77 | B78: Impression noir ou quadrichromie sur carton 2mm | C78: qté supplém. +10 | D78: 10 quantités supplémentaires | E78: 5 | F78: 12 | G78: M36 | H78: 0.3108 | O78: =IF(G78="","",IF(IFERROR(VLOOKUP(G78,Materialen!$A$2:$I$39,4,0),"")="plaat",Instellingen!$B$4,Instellingen!$B$3)) | P78: =ROUND(N(H78)*IFERROR(IF(VLOOKUP(G78,Materialen!$A$2:$I$39,9,0)="",0,VLOOKUP(G78,Materialen!$A$2:$I$39,9,0)),0)*(1+N(O78))+N(J78)*IFERROR(IF(VLOOKUP(I78,Materialen!$A$2:$I$39,9,0)="",0,VLOOKUP(I78,Materialen!$A$2:$I$39,9,0)),0)*(1+N(O78))+N(L78)*IFERROR(IF(VLOOKUP(K78,Materialen!$A$2:$I$39,9,0)="",0,VLOOKUP(K78,Materialen!$A$2:$I$39,9,0)),0)+N(N78)*IFERROR(IF(VLOOKUP(M78,Materialen!$A$2:$I$39,9,0)="",0,VLOOKUP(M78,Materialen!$A$2:$I$39,9,0)),0),2) | Q78: =IF(G78="",0,IF(IFERROR(VLOOKUP(G78,Materialen!$A$2:$I$39,5,0),"N")="J",ROUND(N(H78)*(1+N(O78))*Instellingen!$B$8,2),0)) | S78: =ROUND(N(R78)/60*Instellingen!$B$9,2) | U78: =P78+Q78+S78+N(T78) | V78: =IF(AC78<>"OK","",F78-U78) | W78: =IF(OR(F78=0,AC78<>"OK"),"",V78/F78) | X78: =IF(N(H78)>0,F78/H78,"") | Y78: =IF(N(H78)>0,IFERROR(IF(VLOOKUP(G78,Materialen!$A$2:$I$39,9,0)="",0,VLOOKUP(G78,Materialen!$A$2:$I$39,9,0)),0),"") | Z78: =ROUND(E78*F78,2) | AA78: =IF(AC78<>"OK","",ROUND(E78*U78,2)) | AB78: =IF(AC78<>"OK","",Z78-AA78) | AC78: =IF((IF(G78="",0,IF(IFERROR(IF(VLOOKUP(G78,Materialen!$A$2:$I$39,9,0)="",0,VLOOKUP(G78,Materialen!$A$2:$I$39,9,0)),0)=0,1,0))+IF(I78="",0,IF(IFERROR(IF(VLOOKUP(I78,Materialen!$A$2:$I$39,9,0)="",0,VLOOKUP(I78,Materialen!$A$2:$I$39,9,0)),0)=0,1,0))+IF(K78="",0,IF(IFERROR(IF(VLOOKUP(K78,Materialen!$A$2:$I$39,9,0)="",0,VLOOKUP(K78,Materialen!$A$2:$I$39,9,0)),0)=0,1,0))+IF(M78="",0,IF(IFERROR(IF(VLOOKUP(M78,Materialen!$A$2:$I$39,9,0)="",0,VLOOKUP(M78,Materialen!$A$2:$I$39,9,0)),0)=0,1,0)))>0,"aankoopprijs ontbreekt",IF(AND(G78="",K78="",N(T78)=0,N(R78)=0),"kost invullen (arbeid/overig)","OK")) | AD78: 10 x A5
A79: 78 | B79: Impression digitale quadrichromie sur vinyle autocollant monomère pour l'intérieur | C79: >= A2 et <= 1 m² | D79: m² | E79: 5 | F79: 34 | G79: M15 | H79: 1 | O79: =IF(G79="","",IF(IFERROR(VLOOKUP(G79,Materialen!$A$2:$I$39,4,0),"")="plaat",Instellingen!$B$4,Instellingen!$B$3)) | P79: =ROUND(N(H79)*IFERROR(IF(VLOOKUP(G79,Materialen!$A$2:$I$39,9,0)="",0,VLOOKUP(G79,Materialen!$A$2:$I$39,9,0)),0)*(1+N(O79))+N(J79)*IFERROR(IF(VLOOKUP(I79,Materialen!$A$2:$I$39,9,0)="",0,VLOOKUP(I79,Materialen!$A$2:$I$39,9,0)),0)*(1+N(O79))+N(L79)*IFERROR(IF(VLOOKUP(K79,Materialen!$A$2:$I$39,9,0)="",0,VLOOKUP(K79,Materialen!$A$2:$I$39,9,0)),0)+N(N79)*IFERROR(IF(VLOOKUP(M79,Materialen!$A$2:$I$39,9,0)="",0,VLOOKUP(M79,Materialen!$A$2:$I$39,9,0)),0),2) | Q79: =IF(G79="",0,IF(IFERROR(VLOOKUP(G79,Materialen!$A$2:$I$39,5,0),"N")="J",ROUND(N(H79)*(1+N(O79))*Instellingen!$B$8,2),0)) | S79: =ROUND(N(R79)/60*Instellingen!$B$9,2) | U79: =P79+Q79+S79+N(T79) | V79: =IF(AC79<>"OK","",F79-U79) | W79: =IF(OR(F79=0,AC79<>"OK"),"",V79/F79) | X79: =IF(N(H79)>0,F79/H79,"") | Y79: =IF(N(H79)>0,IFERROR(IF(VLOOKUP(G79,Materialen!$A$2:$I$39,9,0)="",0,VLOOKUP(G79,Materialen!$A$2:$I$39,9,0)),0),"") | Z79: =ROUND(E79*F79,2) | AA79: =IF(AC79<>"OK","",ROUND(E79*U79,2)) | AB79: =IF(AC79<>"OK","",Z79-AA79) | AC79: =IF((IF(G79="",0,IF(IFERROR(IF(VLOOKUP(G79,Materialen!$A$2:$I$39,9,0)="",0,VLOOKUP(G79,Materialen!$A$2:$I$39,9,0)),0)=0,1,0))+IF(I79="",0,IF(IFERROR(IF(VLOOKUP(I79,Materialen!$A$2:$I$39,9,0)="",0,VLOOKUP(I79,Materialen!$A$2:$I$39,9,0)),0)=0,1,0))+IF(K79="",0,IF(IFERROR(IF(VLOOKUP(K79,Materialen!$A$2:$I$39,9,0)="",0,VLOOKUP(K79,Materialen!$A$2:$I$39,9,0)),0)=0,1,0))+IF(M79="",0,IF(IFERROR(IF(VLOOKUP(M79,Materialen!$A$2:$I$39,9,0)="",0,VLOOKUP(M79,Materialen!$A$2:$I$39,9,0)),0)=0,1,0)))>0,"aankoopprijs ontbreekt",IF(AND(G79="",K79="",N(T79)=0,N(R79)=0),"kost invullen (arbeid/overig)","OK"))
A80: 79 | B80: Impression digitale quadrichromie sur vinyle autocollant monomère pour l'intérieur | C80: > 1 m² et <= 2 m² | D80: m² | E80: 5 | F80: 30 | G80: M15 | H80: 1 | O80: =IF(G80="","",IF(IFERROR(VLOOKUP(G80,Materialen!$A$2:$I$39,4,0),"")="plaat",Instellingen!$B$4,Instellingen!$B$3)) | P80: =ROUND(N(H80)*IFERROR(IF(VLOOKUP(G80,Materialen!$A$2:$I$39,9,0)="",0,VLOOKUP(G80,Materialen!$A$2:$I$39,9,0)),0)*(1+N(O80))+N(J80)*IFERROR(IF(VLOOKUP(I80,Materialen!$A$2:$I$39,9,0)="",0,VLOOKUP(I80,Materialen!$A$2:$I$39,9,0)),0)*(1+N(O80))+N(L80)*IFERROR(IF(VLOOKUP(K80,Materialen!$A$2:$I$39,9,0)="",0,VLOOKUP(K80,Materialen!$A$2:$I$39,9,0)),0)+N(N80)*IFERROR(IF(VLOOKUP(M80,Materialen!$A$2:$I$39,9,0)="",0,VLOOKUP(M80,Materialen!$A$2:$I$39,9,0)),0),2) | Q80: =IF(G80="",0,IF(IFERROR(VLOOKUP(G80,Materialen!$A$2:$I$39,5,0),"N")="J",ROUND(N(H80)*(1+N(O80))*Instellingen!$B$8,2),0)) | S80: =ROUND(N(R80)/60*Instellingen!$B$9,2) | U80: =P80+Q80+S80+N(T80) | V80: =IF(AC80<>"OK","",F80-U80) | W80: =IF(OR(F80=0,AC80<>"OK"),"",V80/F80) | X80: =IF(N(H80)>0,F80/H80,"") | Y80: =IF(N(H80)>0,IFERROR(IF(VLOOKUP(G80,Materialen!$A$2:$I$39,9,0)="",0,VLOOKUP(G80,Materialen!$A$2:$I$39,9,0)),0),"") | Z80: =ROUND(E80*F80,2) | AA80: =IF(AC80<>"OK","",ROUND(E80*U80,2)) | AB80: =IF(AC80<>"OK","",Z80-AA80) | AC80: =IF((IF(G80="",0,IF(IFERROR(IF(VLOOKUP(G80,Materialen!$A$2:$I$39,9,0)="",0,VLOOKUP(G80,Materialen!$A$2:$I$39,9,0)),0)=0,1,0))+IF(I80="",0,IF(IFERROR(IF(VLOOKUP(I80,Materialen!$A$2:$I$39,9,0)="",0,VLOOKUP(I80,Materialen!$A$2:$I$39,9,0)),0)=0,1,0))+IF(K80="",0,IF(IFERROR(IF(VLOOKUP(K80,Materialen!$A$2:$I$39,9,0)="",0,VLOOKUP(K80,Materialen!$A$2:$I$39,9,0)),0)=0,1,0))+IF(M80="",0,IF(IFERROR(IF(VLOOKUP(M80,Materialen!$A$2:$I$39,9,0)="",0,VLOOKUP(M80,Materialen!$A$2:$I$39,9,0)),0)=0,1,0)))>0,"aankoopprijs ontbreekt",IF(AND(G80="",K80="",N(T80)=0,N(R80)=0),"kost invullen (arbeid/overig)","OK"))
A81: 80 | B81: Impression digitale quadrichromie sur vinyle autocollant monomère pour l'intérieur | C81: > 2 m² et <= 5 m² | D81: m² | E81: 5 | F81: 27 | G81: M15 | H81: 1 | O81: =IF(G81="","",IF(IFERROR(VLOOKUP(G81,Materialen!$A$2:$I$39,4,0),"")="plaat",Instellingen!$B$4,Instellingen!$B$3)) | P81: =ROUND(N(H81)*IFERROR(IF(VLOOKUP(G81,Materialen!$A$2:$I$39,9,0)="",0,VLOOKUP(G81,Materialen!$A$2:$I$39,9,0)),0)*(1+N(O81))+N(J81)*IFERROR(IF(VLOOKUP(I81,Materialen!$A$2:$I$39,9,0)="",0,VLOOKUP(I81,Materialen!$A$2:$I$39,9,0)),0)*(1+N(O81))+N(L81)*IFERROR(IF(VLOOKUP(K81,Materialen!$A$2:$I$39,9,0)="",0,VLOOKUP(K81,Materialen!$A$2:$I$39,9,0)),0)+N(N81)*IFERROR(IF(VLOOKUP(M81,Materialen!$A$2:$I$39,9,0)="",0,VLOOKUP(M81,Materialen!$A$2:$I$39,9,0)),0),2) | Q81: =IF(G81="",0,IF(IFERROR(VLOOKUP(G81,Materialen!$A$2:$I$39,5,0),"N")="J",ROUND(N(H81)*(1+N(O81))*Instellingen!$B$8,2),0)) | S81: =ROUND(N(R81)/60*Instellingen!$B$9,2) | U81: =P81+Q81+S81+N(T81) | V81: =IF(AC81<>"OK","",F81-U81) | W81: =IF(OR(F81=0,AC81<>"OK"),"",V81/F81) | X81: =IF(N(H81)>0,F81/H81,"") | Y81: =IF(N(H81)>0,IFERROR(IF(VLOOKUP(G81,Materialen!$A$2:$I$39,9,0)="",0,VLOOKUP(G81,Materialen!$A$2:$I$39,9,0)),0),"") | Z81: =ROUND(E81*F81,2) | AA81: =IF(AC81<>"OK","",ROUND(E81*U81,2)) | AB81: =IF(AC81<>"OK","",Z81-AA81) | AC81: =IF((IF(G81="",0,IF(IFERROR(IF(VLOOKUP(G81,Materialen!$A$2:$I$39,9,0)="",0,VLOOKUP(G81,Materialen!$A$2:$I$39,9,0)),0)=0,1,0))+IF(I81="",0,IF(IFERROR(IF(VLOOKUP(I81,Materialen!$A$2:$I$39,9,0)="",0,VLOOKUP(I81,Materialen!$A$2:$I$39,9,0)),0)=0,1,0))+IF(K81="",0,IF(IFERROR(IF(VLOOKUP(K81,Materialen!$A$2:$I$39,9,0)="",0,VLOOKUP(K81,Materialen!$A$2:$I$39,9,0)),0)=0,1,0))+IF(M81="",0,IF(IFERROR(IF(VLOOKUP(M81,Materialen!$A$2:$I$39,9,0)="",0,VLOOKUP(M81,Materialen!$A$2:$I$39,9,0)),0)=0,1,0)))>0,"aankoopprijs ontbreekt",IF(AND(G81="",K81="",N(T81)=0,N(R81)=0),"kost invullen (arbeid/overig)","OK"))
A82: 81 | B82: Impression digitale quadrichromie sur vinyle autocollant monomère pour l'intérieur | C82: > 5 m² et <= 10 m² | D82: m² | E82: 5 | F82: 24 | G82: M15 | H82: 1 | O82: =IF(G82="","",IF(IFERROR(VLOOKUP(G82,Materialen!$A$2:$I$39,4,0),"")="plaat",Instellingen!$B$4,Instellingen!$B$3)) | P82: =ROUND(N(H82)*IFERROR(IF(VLOOKUP(G82,Materialen!$A$2:$I$39,9,0)="",0,VLOOKUP(G82,Materialen!$A$2:$I$39,9,0)),0)*(1+N(O82))+N(J82)*IFERROR(IF(VLOOKUP(I82,Materialen!$A$2:$I$39,9,0)="",0,VLOOKUP(I82,Materialen!$A$2:$I$39,9,0)),0)*(1+N(O82))+N(L82)*IFERROR(IF(VLOOKUP(K82,Materialen!$A$2:$I$39,9,0)="",0,VLOOKUP(K82,Materialen!$A$2:$I$39,9,0)),0)+N(N82)*IFERROR(IF(VLOOKUP(M82,Materialen!$A$2:$I$39,9,0)="",0,VLOOKUP(M82,Materialen!$A$2:$I$39,9,0)),0),2) | Q82: =IF(G82="",0,IF(IFERROR(VLOOKUP(G82,Materialen!$A$2:$I$39,5,0),"N")="J",ROUND(N(H82)*(1+N(O82))*Instellingen!$B$8,2),0)) | S82: =ROUND(N(R82)/60*Instellingen!$B$9,2) | U82: =P82+Q82+S82+N(T82) | V82: =IF(AC82<>"OK","",F82-U82) | W82: =IF(OR(F82=0,AC82<>"OK"),"",V82/F82) | X82: =IF(N(H82)>0,F82/H82,"") | Y82: =IF(N(H82)>0,IFERROR(IF(VLOOKUP(G82,Materialen!$A$2:$I$39,9,0)="",0,VLOOKUP(G82,Materialen!$A$2:$I$39,9,0)),0),"") | Z82: =ROUND(E82*F82,2) | AA82: =IF(AC82<>"OK","",ROUND(E82*U82,2)) | AB82: =IF(AC82<>"OK","",Z82-AA82) | AC82: =IF((IF(G82="",0,IF(IFERROR(IF(VLOOKUP(G82,Materialen!$A$2:$I$39,9,0)="",0,VLOOKUP(G82,Materialen!$A$2:$I$39,9,0)),0)=0,1,0))+IF(I82="",0,IF(IFERROR(IF(VLOOKUP(I82,Materialen!$A$2:$I$39,9,0)="",0,VLOOKUP(I82,Materialen!$A$2:$I$39,9,0)),0)=0,1,0))+IF(K82="",0,IF(IFERROR(IF(VLOOKUP(K82,Materialen!$A$2:$I$39,9,0)="",0,VLOOKUP(K82,Materialen!$A$2:$I$39,9,0)),0)=0,1,0))+IF(M82="",0,IF(IFERROR(IF(VLOOKUP(M82,Materialen!$A$2:$I$39,9,0)="",0,VLOOKUP(M82,Materialen!$A$2:$I$39,9,0)),0)=0,1,0)))>0,"aankoopprijs ontbreekt",IF(AND(G82="",K82="",N(T82)=0,N(R82)=0),"kost invullen (arbeid/overig)","OK"))
A83: 82 | B83: Impression digitale quadrichromie sur vinyle autocollant monomère pour l'intérieur | C83: > 10 m² et <= 25 m² | D83: m² | E83: 5 | F83: 22 | G83: M15 | H83: 1 | O83: =IF(G83="","",IF(IFERROR(VLOOKUP(G83,Materialen!$A$2:$I$39,4,0),"")="plaat",Instellingen!$B$4,Instellingen!$B$3)) | P83: =ROUND(N(H83)*IFERROR(IF(VLOOKUP(G83,Materialen!$A$2:$I$39,9,0)="",0,VLOOKUP(G83,Materialen!$A$2:$I$39,9,0)),0)*(1+N(O83))+N(J83)*IFERROR(IF(VLOOKUP(I83,Materialen!$A$2:$I$39,9,0)="",0,VLOOKUP(I83,Materialen!$A$2:$I$39,9,0)),0)*(1+N(O83))+N(L83)*IFERROR(IF(VLOOKUP(K83,Materialen!$A$2:$I$39,9,0)="",0,VLOOKUP(K83,Materialen!$A$2:$I$39,9,0)),0)+N(N83)*IFERROR(IF(VLOOKUP(M83,Materialen!$A$2:$I$39,9,0)="",0,VLOOKUP(M83,Materialen!$A$2:$I$39,9,0)),0),2) | Q83: =IF(G83="",0,IF(IFERROR(VLOOKUP(G83,Materialen!$A$2:$I$39,5,0),"N")="J",ROUND(N(H83)*(1+N(O83))*Instellingen!$B$8,2),0)) | S83: =ROUND(N(R83)/60*Instellingen!$B$9,2) | U83: =P83+Q83+S83+N(T83) | V83: =IF(AC83<>"OK","",F83-U83) | W83: =IF(OR(F83=0,AC83<>"OK"),"",V83/F83) | X83: =IF(N(H83)>0,F83/H83,"") | Y83: =IF(N(H83)>0,IFERROR(IF(VLOOKUP(G83,Materialen!$A$2:$I$39,9,0)="",0,VLOOKUP(G83,Materialen!$A$2:$I$39,9,0)),0),"") | Z83: =ROUND(E83*F83,2) | AA83: =IF(AC83<>"OK","",ROUND(E83*U83,2)) | AB83: =IF(AC83<>"OK","",Z83-AA83) | AC83: =IF((IF(G83="",0,IF(IFERROR(IF(VLOOKUP(G83,Materialen!$A$2:$I$39,9,0)="",0,VLOOKUP(G83,Materialen!$A$2:$I$39,9,0)),0)=0,1,0))+IF(I83="",0,IF(IFERROR(IF(VLOOKUP(I83,Materialen!$A$2:$I$39,9,0)="",0,VLOOKUP(I83,Materialen!$A$2:$I$39,9,0)),0)=0,1,0))+IF(K83="",0,IF(IFERROR(IF(VLOOKUP(K83,Materialen!$A$2:$I$39,9,0)="",0,VLOOKUP(K83,Materialen!$A$2:$I$39,9,0)),0)=0,1,0))+IF(M83="",0,IF(IFERROR(IF(VLOOKUP(M83,Materialen!$A$2:$I$39,9,0)="",0,VLOOKUP(M83,Materialen!$A$2:$I$39,9,0)),0)=0,1,0)))>0,"aankoopprijs ontbreekt",IF(AND(G83="",K83="",N(T83)=0,N(R83)=0),"kost invullen (arbeid/overig)","OK"))
A84: 83 | B84: Impression digitale quadrichromie sur vinyle autocollant monomère pour l'intérieur | C84: > 25 m² | D84: m² | E84: 5 | F84: 20 | G84: M15 | H84: 1 | O84: =IF(G84="","",IF(IFERROR(VLOOKUP(G84,Materialen!$A$2:$I$39,4,0),"")="plaat",Instellingen!$B$4,Instellingen!$B$3)) | P84: =ROUND(N(H84)*IFERROR(IF(VLOOKUP(G84,Materialen!$A$2:$I$39,9,0)="",0,VLOOKUP(G84,Materialen!$A$2:$I$39,9,0)),0)*(1+N(O84))+N(J84)*IFERROR(IF(VLOOKUP(I84,Materialen!$A$2:$I$39,9,0)="",0,VLOOKUP(I84,Materialen!$A$2:$I$39,9,0)),0)*(1+N(O84))+N(L84)*IFERROR(IF(VLOOKUP(K84,Materialen!$A$2:$I$39,9,0)="",0,VLOOKUP(K84,Materialen!$A$2:$I$39,9,0)),0)+N(N84)*IFERROR(IF(VLOOKUP(M84,Materialen!$A$2:$I$39,9,0)="",0,VLOOKUP(M84,Materialen!$A$2:$I$39,9,0)),0),2) | Q84: =IF(G84="",0,IF(IFERROR(VLOOKUP(G84,Materialen!$A$2:$I$39,5,0),"N")="J",ROUND(N(H84)*(1+N(O84))*Instellingen!$B$8,2),0)) | S84: =ROUND(N(R84)/60*Instellingen!$B$9,2) | U84: =P84+Q84+S84+N(T84) | V84: =IF(AC84<>"OK","",F84-U84) | W84: =IF(OR(F84=0,AC84<>"OK"),"",V84/F84) | X84: =IF(N(H84)>0,F84/H84,"") | Y84: =IF(N(H84)>0,IFERROR(IF(VLOOKUP(G84,Materialen!$A$2:$I$39,9,0)="",0,VLOOKUP(G84,Materialen!$A$2:$I$39,9,0)),0),"") | Z84: =ROUND(E84*F84,2) | AA84: =IF(AC84<>"OK","",ROUND(E84*U84,2)) | AB84: =IF(AC84<>"OK","",Z84-AA84) | AC84: =IF((IF(G84="",0,IF(IFERROR(IF(VLOOKUP(G84,Materialen!$A$2:$I$39,9,0)="",0,VLOOKUP(G84,Materialen!$A$2:$I$39,9,0)),0)=0,1,0))+IF(I84="",0,IF(IFERROR(IF(VLOOKUP(I84,Materialen!$A$2:$I$39,9,0)="",0,VLOOKUP(I84,Materialen!$A$2:$I$39,9,0)),0)=0,1,0))+IF(K84="",0,IF(IFERROR(IF(VLOOKUP(K84,Materialen!$A$2:$I$39,9,0)="",0,VLOOKUP(K84,Materialen!$A$2:$I$39,9,0)),0)=0,1,0))+IF(M84="",0,IF(IFERROR(IF(VLOOKUP(M84,Materialen!$A$2:$I$39,9,0)="",0,VLOOKUP(M84,Materialen!$A$2:$I$39,9,0)),0)=0,1,0)))>0,"aankoopprijs ontbreekt",IF(AND(G84="",K84="",N(T84)=0,N(R84)=0),"kost invullen (arbeid/overig)","OK"))
A85: 84 | B85: Impression noir ou quadrichromie sur dibond 2mm | C85: >= A2 et <= 1 m² | D85: m² | E85: 5 | F85: 85 | G85: M39 | H85: 1 | O85: =IF(G85="","",IF(IFERROR(VLOOKUP(G85,Materialen!$A$2:$I$39,4,0),"")="plaat",Instellingen!$B$4,Instellingen!$B$3)) | P85: =ROUND(N(H85)*IFERROR(IF(VLOOKUP(G85,Materialen!$A$2:$I$39,9,0)="",0,VLOOKUP(G85,Materialen!$A$2:$I$39,9,0)),0)*(1+N(O85))+N(J85)*IFERROR(IF(VLOOKUP(I85,Materialen!$A$2:$I$39,9,0)="",0,VLOOKUP(I85,Materialen!$A$2:$I$39,9,0)),0)*(1+N(O85))+N(L85)*IFERROR(IF(VLOOKUP(K85,Materialen!$A$2:$I$39,9,0)="",0,VLOOKUP(K85,Materialen!$A$2:$I$39,9,0)),0)+N(N85)*IFERROR(IF(VLOOKUP(M85,Materialen!$A$2:$I$39,9,0)="",0,VLOOKUP(M85,Materialen!$A$2:$I$39,9,0)),0),2) | Q85: =IF(G85="",0,IF(IFERROR(VLOOKUP(G85,Materialen!$A$2:$I$39,5,0),"N")="J",ROUND(N(H85)*(1+N(O85))*Instellingen!$B$8,2),0)) | S85: =ROUND(N(R85)/60*Instellingen!$B$9,2) | U85: =P85+Q85+S85+N(T85) | V85: =IF(AC85<>"OK","",F85-U85) | W85: =IF(OR(F85=0,AC85<>"OK"),"",V85/F85) | X85: =IF(N(H85)>0,F85/H85,"") | Y85: =IF(N(H85)>0,IFERROR(IF(VLOOKUP(G85,Materialen!$A$2:$I$39,9,0)="",0,VLOOKUP(G85,Materialen!$A$2:$I$39,9,0)),0),"") | Z85: =ROUND(E85*F85,2) | AA85: =IF(AC85<>"OK","",ROUND(E85*U85,2)) | AB85: =IF(AC85<>"OK","",Z85-AA85) | AC85: =IF((IF(G85="",0,IF(IFERROR(IF(VLOOKUP(G85,Materialen!$A$2:$I$39,9,0)="",0,VLOOKUP(G85,Materialen!$A$2:$I$39,9,0)),0)=0,1,0))+IF(I85="",0,IF(IFERROR(IF(VLOOKUP(I85,Materialen!$A$2:$I$39,9,0)="",0,VLOOKUP(I85,Materialen!$A$2:$I$39,9,0)),0)=0,1,0))+IF(K85="",0,IF(IFERROR(IF(VLOOKUP(K85,Materialen!$A$2:$I$39,9,0)="",0,VLOOKUP(K85,Materialen!$A$2:$I$39,9,0)),0)=0,1,0))+IF(M85="",0,IF(IFERROR(IF(VLOOKUP(M85,Materialen!$A$2:$I$39,9,0)="",0,VLOOKUP(M85,Materialen!$A$2:$I$39,9,0)),0)=0,1,0)))>0,"aankoopprijs ontbreekt",IF(AND(G85="",K85="",N(T85)=0,N(R85)=0),"kost invullen (arbeid/overig)","OK"))
A86: 85 | B86: Impression noir ou quadrichromie sur dibond 2mm | C86: > 1 m² et <= 2 m² | D86: m² | E86: 5 | F86: 74 | G86: M39 | H86: 1 | O86: =IF(G86="","",IF(IFERROR(VLOOKUP(G86,Materialen!$A$2:$I$39,4,0),"")="plaat",Instellingen!$B$4,Instellingen!$B$3)) | P86: =ROUND(N(H86)*IFERROR(IF(VLOOKUP(G86,Materialen!$A$2:$I$39,9,0)="",0,VLOOKUP(G86,Materialen!$A$2:$I$39,9,0)),0)*(1+N(O86))+N(J86)*IFERROR(IF(VLOOKUP(I86,Materialen!$A$2:$I$39,9,0)="",0,VLOOKUP(I86,Materialen!$A$2:$I$39,9,0)),0)*(1+N(O86))+N(L86)*IFERROR(IF(VLOOKUP(K86,Materialen!$A$2:$I$39,9,0)="",0,VLOOKUP(K86,Materialen!$A$2:$I$39,9,0)),0)+N(N86)*IFERROR(IF(VLOOKUP(M86,Materialen!$A$2:$I$39,9,0)="",0,VLOOKUP(M86,Materialen!$A$2:$I$39,9,0)),0),2) | Q86: =IF(G86="",0,IF(IFERROR(VLOOKUP(G86,Materialen!$A$2:$I$39,5,0),"N")="J",ROUND(N(H86)*(1+N(O86))*Instellingen!$B$8,2),0)) | S86: =ROUND(N(R86)/60*Instellingen!$B$9,2) | U86: =P86+Q86+S86+N(T86) | V86: =IF(AC86<>"OK","",F86-U86) | W86: =IF(OR(F86=0,AC86<>"OK"),"",V86/F86) | X86: =IF(N(H86)>0,F86/H86,"") | Y86: =IF(N(H86)>0,IFERROR(IF(VLOOKUP(G86,Materialen!$A$2:$I$39,9,0)="",0,VLOOKUP(G86,Materialen!$A$2:$I$39,9,0)),0),"") | Z86: =ROUND(E86*F86,2) | AA86: =IF(AC86<>"OK","",ROUND(E86*U86,2)) | AB86: =IF(AC86<>"OK","",Z86-AA86) | AC86: =IF((IF(G86="",0,IF(IFERROR(IF(VLOOKUP(G86,Materialen!$A$2:$I$39,9,0)="",0,VLOOKUP(G86,Materialen!$A$2:$I$39,9,0)),0)=0,1,0))+IF(I86="",0,IF(IFERROR(IF(VLOOKUP(I86,Materialen!$A$2:$I$39,9,0)="",0,VLOOKUP(I86,Materialen!$A$2:$I$39,9,0)),0)=0,1,0))+IF(K86="",0,IF(IFERROR(IF(VLOOKUP(K86,Materialen!$A$2:$I$39,9,0)="",0,VLOOKUP(K86,Materialen!$A$2:$I$39,9,0)),0)=0,1,0))+IF(M86="",0,IF(IFERROR(IF(VLOOKUP(M86,Materialen!$A$2:$I$39,9,0)="",0,VLOOKUP(M86,Materialen!$A$2:$I$39,9,0)),0)=0,1,0)))>0,"aankoopprijs ontbreekt",IF(AND(G86="",K86="",N(T86)=0,N(R86)=0),"kost invullen (arbeid/overig)","OK"))
A87: 86 | B87: Impression noir ou quadrichromie sur dibond 2mm | C87: > 2 m² et <= 5 m² | D87: m² | E87: 5 | F87: 66 | G87: M39 | H87: 1 | O87: =IF(G87="","",IF(IFERROR(VLOOKUP(G87,Materialen!$A$2:$I$39,4,0),"")="plaat",Instellingen!$B$4,Instellingen!$B$3)) | P87: =ROUND(N(H87)*IFERROR(IF(VLOOKUP(G87,Materialen!$A$2:$I$39,9,0)="",0,VLOOKUP(G87,Materialen!$A$2:$I$39,9,0)),0)*(1+N(O87))+N(J87)*IFERROR(IF(VLOOKUP(I87,Materialen!$A$2:$I$39,9,0)="",0,VLOOKUP(I87,Materialen!$A$2:$I$39,9,0)),0)*(1+N(O87))+N(L87)*IFERROR(IF(VLOOKUP(K87,Materialen!$A$2:$I$39,9,0)="",0,VLOOKUP(K87,Materialen!$A$2:$I$39,9,0)),0)+N(N87)*IFERROR(IF(VLOOKUP(M87,Materialen!$A$2:$I$39,9,0)="",0,VLOOKUP(M87,Materialen!$A$2:$I$39,9,0)),0),2) | Q87: =IF(G87="",0,IF(IFERROR(VLOOKUP(G87,Materialen!$A$2:$I$39,5,0),"N")="J",ROUND(N(H87)*(1+N(O87))*Instellingen!$B$8,2),0)) | S87: =ROUND(N(R87)/60*Instellingen!$B$9,2) | U87: =P87+Q87+S87+N(T87) | V87: =IF(AC87<>"OK","",F87-U87) | W87: =IF(OR(F87=0,AC87<>"OK"),"",V87/F87) | X87: =IF(N(H87)>0,F87/H87,"") | Y87: =IF(N(H87)>0,IFERROR(IF(VLOOKUP(G87,Materialen!$A$2:$I$39,9,0)="",0,VLOOKUP(G87,Materialen!$A$2:$I$39,9,0)),0),"") | Z87: =ROUND(E87*F87,2) | AA87: =IF(AC87<>"OK","",ROUND(E87*U87,2)) | AB87: =IF(AC87<>"OK","",Z87-AA87) | AC87: =IF((IF(G87="",0,IF(IFERROR(IF(VLOOKUP(G87,Materialen!$A$2:$I$39,9,0)="",0,VLOOKUP(G87,Materialen!$A$2:$I$39,9,0)),0)=0,1,0))+IF(I87="",0,IF(IFERROR(IF(VLOOKUP(I87,Materialen!$A$2:$I$39,9,0)="",0,VLOOKUP(I87,Materialen!$A$2:$I$39,9,0)),0)=0,1,0))+IF(K87="",0,IF(IFERROR(IF(VLOOKUP(K87,Materialen!$A$2:$I$39,9,0)="",0,VLOOKUP(K87,Materialen!$A$2:$I$39,9,0)),0)=0,1,0))+IF(M87="",0,IF(IFERROR(IF(VLOOKUP(M87,Materialen!$A$2:$I$39,9,0)="",0,VLOOKUP(M87,Materialen!$A$2:$I$39,9,0)),0)=0,1,0)))>0,"aankoopprijs ontbreekt",IF(AND(G87="",K87="",N(T87)=0,N(R87)=0),"kost invullen (arbeid/overig)","OK"))
A88: 87 | B88: Impression noir ou quadrichromie sur dibond 2mm | C88: > 5 m² et <= 10 m² | D88: m² | E88: 5 | F88: 59 | G88: M39 | H88: 1 | O88: =IF(G88="","",IF(IFERROR(VLOOKUP(G88,Materialen!$A$2:$I$39,4,0),"")="plaat",Instellingen!$B$4,Instellingen!$B$3)) | P88: =ROUND(N(H88)*IFERROR(IF(VLOOKUP(G88,Materialen!$A$2:$I$39,9,0)="",0,VLOOKUP(G88,Materialen!$A$2:$I$39,9,0)),0)*(1+N(O88))+N(J88)*IFERROR(IF(VLOOKUP(I88,Materialen!$A$2:$I$39,9,0)="",0,VLOOKUP(I88,Materialen!$A$2:$I$39,9,0)),0)*(1+N(O88))+N(L88)*IFERROR(IF(VLOOKUP(K88,Materialen!$A$2:$I$39,9,0)="",0,VLOOKUP(K88,Materialen!$A$2:$I$39,9,0)),0)+N(N88)*IFERROR(IF(VLOOKUP(M88,Materialen!$A$2:$I$39,9,0)="",0,VLOOKUP(M88,Materialen!$A$2:$I$39,9,0)),0),2) | Q88: =IF(G88="",0,IF(IFERROR(VLOOKUP(G88,Materialen!$A$2:$I$39,5,0),"N")="J",ROUND(N(H88)*(1+N(O88))*Instellingen!$B$8,2),0)) | S88: =ROUND(N(R88)/60*Instellingen!$B$9,2) | U88: =P88+Q88+S88+N(T88) | V88: =IF(AC88<>"OK","",F88-U88) | W88: =IF(OR(F88=0,AC88<>"OK"),"",V88/F88) | X88: =IF(N(H88)>0,F88/H88,"") | Y88: =IF(N(H88)>0,IFERROR(IF(VLOOKUP(G88,Materialen!$A$2:$I$39,9,0)="",0,VLOOKUP(G88,Materialen!$A$2:$I$39,9,0)),0),"") | Z88: =ROUND(E88*F88,2) | AA88: =IF(AC88<>"OK","",ROUND(E88*U88,2)) | AB88: =IF(AC88<>"OK","",Z88-AA88) | AC88: =IF((IF(G88="",0,IF(IFERROR(IF(VLOOKUP(G88,Materialen!$A$2:$I$39,9,0)="",0,VLOOKUP(G88,Materialen!$A$2:$I$39,9,0)),0)=0,1,0))+IF(I88="",0,IF(IFERROR(IF(VLOOKUP(I88,Materialen!$A$2:$I$39,9,0)="",0,VLOOKUP(I88,Materialen!$A$2:$I$39,9,0)),0)=0,1,0))+IF(K88="",0,IF(IFERROR(IF(VLOOKUP(K88,Materialen!$A$2:$I$39,9,0)="",0,VLOOKUP(K88,Materialen!$A$2:$I$39,9,0)),0)=0,1,0))+IF(M88="",0,IF(IFERROR(IF(VLOOKUP(M88,Materialen!$A$2:$I$39,9,0)="",0,VLOOKUP(M88,Materialen!$A$2:$I$39,9,0)),0)=0,1,0)))>0,"aankoopprijs ontbreekt",IF(AND(G88="",K88="",N(T88)=0,N(R88)=0),"kost invullen (arbeid/overig)","OK"))
A89: 88 | B89: Impression noir ou quadrichromie sur dibond 2mm | C89: > 10 m² et <= 25 m² | D89: m² | E89: 5 | F89: 53 | G89: M39 | H89: 1 | O89: =IF(G89="","",IF(IFERROR(VLOOKUP(G89,Materialen!$A$2:$I$39,4,0),"")="plaat",Instellingen!$B$4,Instellingen!$B$3)) | P89: =ROUND(N(H89)*IFERROR(IF(VLOOKUP(G89,Materialen!$A$2:$I$39,9,0)="",0,VLOOKUP(G89,Materialen!$A$2:$I$39,9,0)),0)*(1+N(O89))+N(J89)*IFERROR(IF(VLOOKUP(I89,Materialen!$A$2:$I$39,9,0)="",0,VLOOKUP(I89,Materialen!$A$2:$I$39,9,0)),0)*(1+N(O89))+N(L89)*IFERROR(IF(VLOOKUP(K89,Materialen!$A$2:$I$39,9,0)="",0,VLOOKUP(K89,Materialen!$A$2:$I$39,9,0)),0)+N(N89)*IFERROR(IF(VLOOKUP(M89,Materialen!$A$2:$I$39,9,0)="",0,VLOOKUP(M89,Materialen!$A$2:$I$39,9,0)),0),2) | Q89: =IF(G89="",0,IF(IFERROR(VLOOKUP(G89,Materialen!$A$2:$I$39,5,0),"N")="J",ROUND(N(H89)*(1+N(O89))*Instellingen!$B$8,2),0)) | S89: =ROUND(N(R89)/60*Instellingen!$B$9,2) | U89: =P89+Q89+S89+N(T89) | V89: =IF(AC89<>"OK","",F89-U89) | W89: =IF(OR(F89=0,AC89<>"OK"),"",V89/F89) | X89: =IF(N(H89)>0,F89/H89,"") | Y89: =IF(N(H89)>0,IFERROR(IF(VLOOKUP(G89,Materialen!$A$2:$I$39,9,0)="",0,VLOOKUP(G89,Materialen!$A$2:$I$39,9,0)),0),"") | Z89: =ROUND(E89*F89,2) | AA89: =IF(AC89<>"OK","",ROUND(E89*U89,2)) | AB89: =IF(AC89<>"OK","",Z89-AA89) | AC89: =IF((IF(G89="",0,IF(IFERROR(IF(VLOOKUP(G89,Materialen!$A$2:$I$39,9,0)="",0,VLOOKUP(G89,Materialen!$A$2:$I$39,9,0)),0)=0,1,0))+IF(I89="",0,IF(IFERROR(IF(VLOOKUP(I89,Materialen!$A$2:$I$39,9,0)="",0,VLOOKUP(I89,Materialen!$A$2:$I$39,9,0)),0)=0,1,0))+IF(K89="",0,IF(IFERROR(IF(VLOOKUP(K89,Materialen!$A$2:$I$39,9,0)="",0,VLOOKUP(K89,Materialen!$A$2:$I$39,9,0)),0)=0,1,0))+IF(M89="",0,IF(IFERROR(IF(VLOOKUP(M89,Materialen!$A$2:$I$39,9,0)="",0,VLOOKUP(M89,Materialen!$A$2:$I$39,9,0)),0)=0,1,0)))>0,"aankoopprijs ontbreekt",IF(AND(G89="",K89="",N(T89)=0,N(R89)=0),"kost invullen (arbeid/overig)","OK"))
A90: 89 | B90: Impression noir ou quadrichromie sur dibond 2mm | C90: > 25 m² | D90: m² | E90: 5 | F90: 48 | G90: M39 | H90: 1 | O90: =IF(G90="","",IF(IFERROR(VLOOKUP(G90,Materialen!$A$2:$I$39,4,0),"")="plaat",Instellingen!$B$4,Instellingen!$B$3)) | P90: =ROUND(N(H90)*IFERROR(IF(VLOOKUP(G90,Materialen!$A$2:$I$39,9,0)="",0,VLOOKUP(G90,Materialen!$A$2:$I$39,9,0)),0)*(1+N(O90))+N(J90)*IFERROR(IF(VLOOKUP(I90,Materialen!$A$2:$I$39,9,0)="",0,VLOOKUP(I90,Materialen!$A$2:$I$39,9,0)),0)*(1+N(O90))+N(L90)*IFERROR(IF(VLOOKUP(K90,Materialen!$A$2:$I$39,9,0)="",0,VLOOKUP(K90,Materialen!$A$2:$I$39,9,0)),0)+N(N90)*IFERROR(IF(VLOOKUP(M90,Materialen!$A$2:$I$39,9,0)="",0,VLOOKUP(M90,Materialen!$A$2:$I$39,9,0)),0),2) | Q90: =IF(G90="",0,IF(IFERROR(VLOOKUP(G90,Materialen!$A$2:$I$39,5,0),"N")="J",ROUND(N(H90)*(1+N(O90))*Instellingen!$B$8,2),0)) | S90: =ROUND(N(R90)/60*Instellingen!$B$9,2) | U90: =P90+Q90+S90+N(T90) | V90: =IF(AC90<>"OK","",F90-U90) | W90: =IF(OR(F90=0,AC90<>"OK"),"",V90/F90) | X90: =IF(N(H90)>0,F90/H90,"") | Y90: =IF(N(H90)>0,IFERROR(IF(VLOOKUP(G90,Materialen!$A$2:$I$39,9,0)="",0,VLOOKUP(G90,Materialen!$A$2:$I$39,9,0)),0),"") | Z90: =ROUND(E90*F90,2) | AA90: =IF(AC90<>"OK","",ROUND(E90*U90,2)) | AB90: =IF(AC90<>"OK","",Z90-AA90) | AC90: =IF((IF(G90="",0,IF(IFERROR(IF(VLOOKUP(G90,Materialen!$A$2:$I$39,9,0)="",0,VLOOKUP(G90,Materialen!$A$2:$I$39,9,0)),0)=0,1,0))+IF(I90="",0,IF(IFERROR(IF(VLOOKUP(I90,Materialen!$A$2:$I$39,9,0)="",0,VLOOKUP(I90,Materialen!$A$2:$I$39,9,0)),0)=0,1,0))+IF(K90="",0,IF(IFERROR(IF(VLOOKUP(K90,Materialen!$A$2:$I$39,9,0)="",0,VLOOKUP(K90,Materialen!$A$2:$I$39,9,0)),0)=0,1,0))+IF(M90="",0,IF(IFERROR(IF(VLOOKUP(M90,Materialen!$A$2:$I$39,9,0)="",0,VLOOKUP(M90,Materialen!$A$2:$I$39,9,0)),0)=0,1,0)))>0,"aankoopprijs ontbreekt",IF(AND(G90="",K90="",N(T90)=0,N(R90)=0),"kost invullen (arbeid/overig)","OK"))
... A96: 95 | B96: Impression noir ou quadrichromie sur dibond 3mm | C96: > 25 m² | D96: m² | E96: 5 | F96: 54 | G96: M40 | H96: 1 | O96: =IF(G96="","",IF(IFERROR(VLOOKUP(G96,Materialen!$A$2:$I$39,4,0),"")="plaat",Instellingen!$B$4,Instellingen!$B$3)) | P96: =ROUND(N(H96)*IFERROR(IF(VLOOKUP(G96,Materialen!$A$2:$I$39,9,0)="",0,VLOOKUP(G96,Materialen!$A$2:$I$39,9,0)),0)*(1+N(O96))+N(J96)*IFERROR(IF(VLOOKUP(I96,Materialen!$A$2:$I$39,9,0)="",0,VLOOKUP(I96,Materialen!$A$2:$I$39,9,0)),0)*(1+N(O96))+N(L96)*IFERROR(IF(VLOOKUP(K96,Materialen!$A$2:$I$39,9,0)="",0,VLOOKUP(K96,Materialen!$A$2:$I$39,9,0)),0)+N(N96)*IFERROR(IF(VLOOKUP(M96,Materialen!$A$2:$I$39,9,0)="",0,VLOOKUP(M96,Materialen!$A$2:$I$39,9,0)),0),2) | Q96: =IF(G96="",0,IF(IFERROR(VLOOKUP(G96,Materialen!$A$2:$I$39,5,0),"N")="J",ROUND(N(H96)*(1+N(O96))*Instellingen!$B$8,2),0)) | S96: =ROUND(N(R96)/60*Instellingen!$B$9,2) | U96: =P96+Q96+S96+N(T96) | V96: =IF(AC96<>"OK","",F96-U96) | W96: =IF(OR(F96=0,AC96<>"OK"),"",V96/F96) | X96: =IF(N(H96)>0,F96/H96,"") | Y96: =IF(N(H96)>0,IFERROR(IF(VLOOKUP(G96,Materialen!$A$2:$I$39,9,0)="",0,VLOOKUP(G96,Materialen!$A$2:$I$39,9,0)),0),"") | Z96: =ROUND(E96*F96,2) | AA96: =IF(AC96<>"OK","",ROUND(E96*U96,2)) | AB96: =IF(AC96<>"OK","",Z96-AA96) | AC96: =IF((IF(G96="",0,IF(IFERROR(IF(VLOOKUP(G96,Materialen!$A$2:$I$39,9,0)="",0,VLOOKUP(G96,Materialen!$A$2:$I$39,9,0)),0)=0,1,0))+IF(I96="",0,IF(IFERROR(IF(VLOOKUP(I96,Materialen!$A$2:$I$39,9,0)="",0,VLOOKUP(I96,Materialen!$A$2:$I$39,9,0)),0)=0,1,0))+IF(K96="",0,IF(IFERROR(IF(VLOOKUP(K96,Materialen!$A$2:$I$39,9,0)="",0,VLOOKUP(K96,Materialen!$A$2:$I$39,9,0)),0)=0,1,0))+IF(M96="",0,IF(IFERROR(IF(VLOOKUP(M96,Materialen!$A$2:$I$39,9,0)="",0,VLOOKUP(M96,Materialen!$A$2:$I$39,9,0)),0)=0,1,0)))>0,"aankoopprijs ontbreekt",IF(AND(G96="",K96="",N(T96)=0,N(R96)=0),"kost invullen (arbeid/overig)","OK"))
A97: 96 | B97: 2cm | C97: >= A2 et <= 1 m² | D97: m² | E97: 5 | F97: 85 | G97: M41 | H97: 1 | I97: M42 | J97: 1 | O97: =IF(G97="","",IF(IFERROR(VLOOKUP(G97,Materialen!$A$2:$I$39,4,0),"")="plaat",Instellingen!$B$4,Instellingen!$B$3)) | P97: =ROUND(N(H97)*IFERROR(IF(VLOOKUP(G97,Materialen!$A$2:$I$39,9,0)="",0,VLOOKUP(G97,Materialen!$A$2:$I$39,9,0)),0)*(1+N(O97))+N(J97)*IFERROR(IF(VLOOKUP(I97,Materialen!$A$2:$I$39,9,0)="",0,VLOOKUP(I97,Materialen!$A$2:$I$39,9,0)),0)*(1+N(O97))+N(L97)*IFERROR(IF(VLOOKUP(K97,Materialen!$A$2:$I$39,9,0)="",0,VLOOKUP(K97,Materialen!$A$2:$I$39,9,0)),0)+N(N97)*IFERROR(IF(VLOOKUP(M97,Materialen!$A$2:$I$39,9,0)="",0,VLOOKUP(M97,Materialen!$A$2:$I$39,9,0)),0),2) | Q97: =IF(G97="",0,IF(IFERROR(VLOOKUP(G97,Materialen!$A$2:$I$39,5,0),"N")="J",ROUND(N(H97)*(1+N(O97))*Instellingen!$B$8,2),0)) | S97: =ROUND(N(R97)/60*Instellingen!$B$9,2) | U97: =P97+Q97+S97+N(T97) | V97: =IF(AC97<>"OK","",F97-U97) | W97: =IF(OR(F97=0,AC97<>"OK"),"",V97/F97) | X97: =IF(N(H97)>0,F97/H97,"") | Y97: =IF(N(H97)>0,IFERROR(IF(VLOOKUP(G97,Materialen!$A$2:$I$39,9,0)="",0,VLOOKUP(G97,Materialen!$A$2:$I$39,9,0)),0),"") | Z97: =ROUND(E97*F97,2) | AA97: =IF(AC97<>"OK","",ROUND(E97*U97,2)) | AB97: =IF(AC97<>"OK","",Z97-AA97) | AC97: =IF((IF(G97="",0,IF(IFERROR(IF(VLOOKUP(G97,Materialen!$A$2:$I$39,9,0)="",0,VLOOKUP(G97,Materialen!$A$2:$I$39,9,0)),0)=0,1,0))+IF(I97="",0,IF(IFERROR(IF(VLOOKUP(I97,Materialen!$A$2:$I$39,9,0)="",0,VLOOKUP(I97,Materialen!$A$2:$I$39,9,0)),0)=0,1,0))+IF(K97="",0,IF(IFERROR(IF(VLOOKUP(K97,Materialen!$A$2:$I$39,9,0)="",0,VLOOKUP(K97,Materialen!$A$2:$I$39,9,0)),0)=0,1,0))+IF(M97="",0,IF(IFERROR(IF(VLOOKUP(M97,Materialen!$A$2:$I$39,9,0)="",0,VLOOKUP(M97,Materialen!$A$2:$I$39,9,0)),0)=0,1,0)))>0,"aankoopprijs ontbreekt",IF(AND(G97="",K97="",N(T97)=0,N(R97)=0),"kost invullen (arbeid/overig)","OK")) | AD97: Wieden/plotten = vooral arbeid
A98: 97 | B98: 2cm | C98: > 1 m² et <= 2 m² | D98: m² | E98: 5 | F98: 75 | G98: M41 | H98: 1 | I98: M42 | J98: 1 | O98: =IF(G98="","",IF(IFERROR(VLOOKUP(G98,Materialen!$A$2:$I$39,4,0),"")="plaat",Instellingen!$B$4,Instellingen!$B$3)) | P98: =ROUND(N(H98)*IFERROR(IF(VLOOKUP(G98,Materialen!$A$2:$I$39,9,0)="",0,VLOOKUP(G98,Materialen!$A$2:$I$39,9,0)),0)*(1+N(O98))+N(J98)*IFERROR(IF(VLOOKUP(I98,Materialen!$A$2:$I$39,9,0)="",0,VLOOKUP(I98,Materialen!$A$2:$I$39,9,0)),0)*(1+N(O98))+N(L98)*IFERROR(IF(VLOOKUP(K98,Materialen!$A$2:$I$39,9,0)="",0,VLOOKUP(K98,Materialen!$A$2:$I$39,9,0)),0)+N(N98)*IFERROR(IF(VLOOKUP(M98,Materialen!$A$2:$I$39,9,0)="",0,VLOOKUP(M98,Materialen!$A$2:$I$39,9,0)),0),2) | Q98: =IF(G98="",0,IF(IFERROR(VLOOKUP(G98,Materialen!$A$2:$I$39,5,0),"N")="J",ROUND(N(H98)*(1+N(O98))*Instellingen!$B$8,2),0)) | S98: =ROUND(N(R98)/60*Instellingen!$B$9,2) | U98: =P98+Q98+S98+N(T98) | V98: =IF(AC98<>"OK","",F98-U98) | W98: =IF(OR(F98=0,AC98<>"OK"),"",V98/F98) | X98: =IF(N(H98)>0,F98/H98,"") | Y98: =IF(N(H98)>0,IFERROR(IF(VLOOKUP(G98,Materialen!$A$2:$I$39,9,0)="",0,VLOOKUP(G98,Materialen!$A$2:$I$39,9,0)),0),"") | Z98: =ROUND(E98*F98,2) | AA98: =IF(AC98<>"OK","",ROUND(E98*U98,2)) | AB98: =IF(AC98<>"OK","",Z98-AA98) | AC98: =IF((IF(G98="",0,IF(IFERROR(IF(VLOOKUP(G98,Materialen!$A$2:$I$39,9,0)="",0,VLOOKUP(G98,Materialen!$A$2:$I$39,9,0)),0)=0,1,0))+IF(I98="",0,IF(IFERROR(IF(VLOOKUP(I98,Materialen!$A$2:$I$39,9,0)="",0,VLOOKUP(I98,Materialen!$A$2:$I$39,9,0)),0)=0,1,0))+IF(K98="",0,IF(IFERROR(IF(VLOOKUP(K98,Materialen!$A$2:$I$39,9,0)="",0,VLOOKUP(K98,Materialen!$A$2:$I$39,9,0)),0)=0,1,0))+IF(M98="",0,IF(IFERROR(IF(VLOOKUP(M98,Materialen!$A$2:$I$39,9,0)="",0,VLOOKUP(M98,Materialen!$A$2:$I$39,9,0)),0)=0,1,0)))>0,"aankoopprijs ontbreekt",IF(AND(G98="",K98="",N(T98)=0,N(R98)=0),"kost invullen (arbeid/overig)","OK")) | AD98: Wieden/plotten = vooral arbeid
